Workbook

Sheet Control 233
A1: Atlas 2.0 · control de migración de 233 entradas | B1: Atlas 2.0 · control de migración de 233 entradas | C1: Atlas 2.0 · control de migración de 233 entradas | D1: Atlas 2.0 · control de migración de 233 entradas | E1: Atlas 2.0 · control de migración de 233 entradas | F1: Atlas 2.0 · control de migración de 233 entradas | G1: Atlas 2.0 · control de migración de 233 entradas | H1: Atlas 2.0 · control de migración de 233 entradas
A2: Plan editorial y técnico por lotes. No modifica el corpus público ni autoriza una integración en main. | B2: Plan editorial y técnico por lotes. No modifica el corpus público ni autoriza una integración en main. | C2: Plan editorial y técnico por lotes. No modifica el corpus público ni autoriza una integración en main. | D2: Plan editorial y técnico por lotes. No modifica el corpus público ni autoriza una integración en main. | E2: Plan editorial y técnico por lotes. No modifica el corpus público ni autoriza una integración en main. | F2: Plan editorial y técnico por lotes. No modifica el corpus público ni autoriza una integración en main. | G2: Plan editorial y técnico por lotes. No modifica el corpus público ni autoriza una integración en main. | H2: Plan editorial y técnico por lotes. No modifica el corpus público ni autoriza una integración en main.
A4: Indicador | B4: Valor | D4: Reglas de cierre | E4: Reglas de cierre | F4: Reglas de cierre | G4: Reglas de cierre | H4: Reglas de cierre
A5: Entradas fuente v1.15.0 | B5: =COUNTA('Plan 233'!$A$5:$A$237) -> 233 | D5: 1. La fuente pública permanece intacta durante toda la migración.
A6: Nodos efectivos proyectados | B6: =B5-COUNTIF('Plan 233'!$K$5:$K$237,"revisada_redireccion") -> 232 | D6: 2. Cada lote conserva f, l, tr, y y los identificadores heredados.
A7: Clasificaciones confirmadas (P00+A01+A02) | B7: 27 | D7: 3. Ninguna candidatura se vuelve confirmación sin fuente y fundamento.
A8: Redirecciones aprobadas (P00+A01+A02) | B8: 17 | D8: 4. Una relación se revisa cuando ambos extremos ya fueron revisados.
A9: Entradas listas para generar | B9: =COUNTIF('Plan 233'!$W$5:$W$237,"SÍ") -> 1 | D9: 5. Cada lote exige generador reproducible, validador, diff y aprobación.
A10: Entradas aún no listas | B10: =B5-B9 -> 232 | D10: 6. Cada lote ocupa un commit propio y puede revertirse sin tocar otros.
A11: Lotes totales | B11: 16 | D11: 7. C1, C2 y C5 no se rellenan para equilibrar cifras.
A12: Lotes cerrados | B12: 4 | D12: 8. La publicación solo se considera después de cerrar los 16 lotes, incluido T01.
A13: Relaciones fuente v1.15.0 | B13: =COUNTA('Plan relaciones'!$A$5:$A$592) -> 588
A14: Corroboradas en fuente | B14: =COUNTIF('Plan relaciones'!$H$5:$H$592,"corroborada") -> 382 | D14: Punto de partida comprobado | E14: Punto de partida comprobado | F14: Punto de partida comprobado | G14: Punto de partida comprobado | H14: Punto de partida comprobado
A15: Por corroborar en fuente | B15: =COUNTIF('Plan relaciones'!$H$5:$H$592,"por_corroborar") -> 206 | D15: v1.15.0: 233 entradas, 588 relaciones y 30 lugares.
A16: Corroboradas tras dictamen | B16: 362 | D16: P00, S01, A01 y A02 están cerrados como capas de transición reproducibles.
A17: Por corroborar tras dictamen | B17: 226 | D17: El parche conceptual fddd441 no altera el corpus público ni reabre esos lotes.
A18: Relaciones listas para generar | B18: 43 | D18: Siguiente acción: T01 sobre el campo tr; A03 queda detrás de T01. No cambiar a main.

Sheet Lotes
A1: Atlas 2.0 · dieciséis lotes revisables | B1: Atlas 2.0 · dieciséis lotes revisables | C1: Atlas 2.0 · dieciséis lotes revisables | D1: Atlas 2.0 · dieciséis lotes revisables | E1: Atlas 2.0 · dieciséis lotes revisables | F1: Atlas 2.0 · dieciséis lotes revisables | G1: Atlas 2.0 · dieciséis lotes revisables | H1: Atlas 2.0 · dieciséis lotes revisables | I1: Atlas 2.0 · dieciséis lotes revisables | J1: Atlas 2.0 · dieciséis lotes revisables | K1: Atlas 2.0 · dieciséis lotes revisables | L1: Atlas 2.0 · dieciséis lotes revisables | M1: Atlas 2.0 · dieciséis lotes revisables | N1: Atlas 2.0 · dieciséis lotes revisables
A2: Máximo 18 entradas por lote intelectual. T01 es un pase técnico transversal sobre las 233 entradas y no reclasifica corrientes. | B2: Máximo 18 entradas por lote intelectual. T01 es un pase técnico transversal sobre las 233 entradas y no reclasifica corrientes. | C2: Máximo 18 entradas por lote intelectual. T01 es un pase técnico transversal sobre las 233 entradas y no reclasifica corrientes. | D2: Máximo 18 entradas por lote intelectual. T01 es un pase técnico transversal sobre las 233 entradas y no reclasifica corrientes. | E2: Máximo 18 entradas por lote intelectual. T01 es un pase técnico transversal sobre las 233 entradas y no reclasifica corrientes. | F2: Máximo 18 entradas por lote intelectual. T01 es un pase técnico transversal sobre las 233 entradas y no reclasifica corrientes. | G2: Máximo 18 entradas por lote intelectual. T01 es un pase técnico transversal sobre las 233 entradas y no reclasifica corrientes. | H2: Máximo 18 entradas por lote intelectual. T01 es un pase técnico transversal sobre las 233 entradas y no reclasifica corrientes. | I2: Máximo 18 entradas por lote intelectual. T01 es un pase técnico transversal sobre las 233 entradas y no reclasifica corrientes. | J2: Máximo 18 entradas por lote intelectual. T01 es un pase técnico transversal sobre las 233 entradas y no reclasifica corrientes. | K2: Máximo 18 entradas por lote intelectual. T01 es un pase técnico transversal sobre las 233 entradas y no reclasifica corrientes. | L2: Máximo 18 entradas por lote intelectual. T01 es un pase técnico transversal sobre las 233 entradas y no reclasifica corrientes. | M2: Máximo 18 entradas por lote intelectual. T01 es un pase técnico transversal sobre las 233 entradas y no reclasifica corrientes. | N2: Máximo 18 entradas por lote intelectual. T01 es un pase técnico transversal sobre las 233 entradas y no reclasifica corrientes.
A4: Secuencia | B4: Lote | C4: Enfoque | D4: Criterio editorial | E4: Entradas | F4: Relaciones asignadas | G4: Internas | H4: Frontera | I4: Corroboradas iniciales | J4: Por corroborar iniciales | K4: Estado | L4: Dependencia | M4: Criterio de aceptación | N4: Reversión
A5: 1 | B5: P00 | C5: Piloto aprobado | D5: Diez casos representativos; ocho clasificaciones confirmadas, una redirección y un nodo compuesto que permanece pendiente. | E5: 10 | F5: 3 | G5: 3 | H5: 0 | I5: 2 | J5: 1 | K5: cerrado_capa_transicion | L5: — | M5: 100 % de entradas y relaciones asignadas con fuente/fundamento, aprobación académica, QA=pasa y validador con 0 errores y 0 advertencias. | N5: Commit propio; revertir únicamente ese commit y regenerar desde la fuente heredada.
A6: 2 | B6: S01 | C6: Bloqueos bibliográficos e identidad | D6: Resolver divisiones, referencias incompletas, correcciones de tipo y metadatos antes de ampliar la clasificación. | E6: 11 | F6: 12 | G6: 7 | H6: 5 | I6: 6 | J6: 6 | K6: cerrado_capa_transicion | L6: P00 | M6: 100 % de entradas y relaciones asignadas con fuente/fundamento, aprobación académica, QA=pasa y validador con 0 errores y 0 advertencias. | N6: Commit propio; revertir únicamente ese commit y regenerar desde la fuente heredada.
A7: 3 | B7: A01 | C7: Candidatura única · tramo 1 | D7: Confirmar o corregir la candidatura única mediante fuente y fundamento escrito. | E7: 18 | F7: 14 | G7: 7 | H7: 7 | I7: 13 | J7: 1 | K7: cerrado_capa_transicion | L7: S01 | M7: 100 % de entradas y relaciones asignadas con fuente/fundamento, aprobación académica, QA=pasa y validador con 0 errores y 0 advertencias. | N7: Commit propio; revertir únicamente ese commit y regenerar desde la fuente heredada.
A8: 4 | B8: A02 | C8: Candidatura única · tramo 2 | D8: Confirmar o corregir la candidatura única mediante fuente y fundamento escrito. | E8: 18 | F8: 14 | G8: 2 | H8: 12 | I8: 11 | J8: 3 | K8: cerrado_capa_transicion | L8: A01 | M8: 100 % de entradas y relaciones asignadas con fuente/fundamento, aprobación académica, QA=pasa y validador con 0 errores y 0 advertencias. | N8: Commit propio; revertir únicamente ese commit y regenerar desde la fuente heredada.
A9: 5 | B9: T01 | C9: Descomposición controlada del campo tr | D9: Conservar tr y separar lengua de publicación, orilla de producción, territorio estudiado y alcance comparativo. La extracción mecánica solo propone; ninguna propuesta se confirma sin revisión humana. | E9: 233 | F9: 0 | G9: 0 | H9: 0 | I9: 0 | J9: 0 | K9: siguiente | L9: A02 | M9: 233 valores originales conservados; 233 revisiones explícitas; ninguna lengua u orilla confirmada por inferencia; QA con 0 errores y aprobación académica. | N9: Commit propio; revertir solo T01. No escribir en datos-atlas.js/json ni alterar P00, S01, A01 o A02.
A10: 6 | B10: A03 | C10: Candidatura única · tramo 3 | D10: Confirmar o corregir la candidatura única mediante fuente y fundamento escrito. | E10: 18 | F10: 24 | G10: 8 | H10: 16 | I10: 18 | J10: 6 | K10: pendiente | L10: T01 | M10: 100 % de entradas y relaciones asignadas con fuente/fundamento, aprobación académica, QA=pasa y validador con 0 errores y 0 advertencias. | N10: Commit propio; revertir únicamente ese commit y regenerar desde la fuente heredada.
A11: 7 | B11: B01 | C11: Candidaturas múltiples · tramo 1 | D11: Leer para decidir qué corriente organiza el argumento; las coetiquetas solo orientan. | E11: 17 | F11: 42 | G11: 18 | H11: 24 | I11: 33 | J11: 9 | K11: pendiente | L11: A03 | M11: 100 % de entradas y relaciones asignadas con fuente/fundamento, aprobación académica, QA=pasa y validador con 0 errores y 0 advertencias. | N11: Commit propio; revertir únicamente ese commit y regenerar desde la fuente heredada.
A12: 8 | B12: B02 | C12: Candidaturas múltiples · tramo 2 | D12: Leer para decidir qué corriente organiza el argumento; las coetiquetas solo orientan. | E12: 16 | F12: 40 | G12: 7 | H12: 33 | I12: 23 | J12: 17 | K12: pendiente | L12: B01 | M12: 100 % de entradas y relaciones asignadas con fuente/fundamento, aprobación académica, QA=pasa y validador con 0 errores y 0 advertencias. | N12: Commit propio; revertir únicamente ese commit y regenerar desde la fuente heredada.
A13: 9 | B13: B03 | C13: Candidaturas múltiples · tramo 3 | D13: Leer para decidir qué corriente organiza el argumento; las coetiquetas solo orientan. | E13: 16 | F13: 40 | G13: 4 | H13: 36 | I13: 32 | J13: 8 | K13: pendiente | L13: B02 | M13: 100 % de entradas y relaciones asignadas con fuente/fundamento, aprobación académica, QA=pasa y validador con 0 errores y 0 advertencias. | N13: Commit propio; revertir únicamente ese commit y regenerar desde la fuente heredada.
A14: 10 | B14: B04 | C14: Candidaturas múltiples · tramo 4 | D14: Leer para decidir qué corriente organiza el argumento; las coetiquetas solo orientan. | E14: 16 | F14: 39 | G14: 6 | H14: 33 | I14: 17 | J14: 22 | K14: pendiente | L14: B03 | M14: 100 % de entradas y relaciones asignadas con fuente/fundamento, aprobación académica, QA=pasa y validador con 0 errores y 0 advertencias. | N14: Commit propio; revertir únicamente ese commit y regenerar desde la fuente heredada.
A15: 11 | B15: B05 | C15: Candidaturas múltiples · tramo 5 | D15: Leer para decidir qué corriente organiza el argumento; las coetiquetas solo orientan. | E15: 16 | F15: 41 | G15: 10 | H15: 31 | I15: 18 | J15: 23 | K15: pendiente | L15: B04 | M15: 100 % de entradas y relaciones asignadas con fuente/fundamento, aprobación académica, QA=pasa y validador con 0 errores y 0 advertencias. | N15: Commit propio; revertir únicamente ese commit y regenerar desde la fuente heredada.
A16: 12 | B16: C01 | C16: Colonialidad y candidatura · tramo 1 | D16: Distinguir invasión, régimen esclavista, administración imperial y persistencia contemporánea. | E16: 16 | F16: 64 | G16: 6 | H16: 58 | I16: 44 | J16: 20 | K16: pendiente | L16: B05 | M16: 100 % de entradas y relaciones asignadas con fuente/fundamento, aprobación académica, QA=pasa y validador con 0 errores y 0 advertencias. | N16: Commit propio; revertir únicamente ese commit y regenerar desde la fuente heredada.
... A20: 16 | B20: DE01 | C20: Sin destino derivable | D20: Lectura completa: colonialidad sola o etiquetas que pasan a marcas; queda prohibida la clasificación por título. | E20: 16 | F20: 78 | G20: 10 | H20: 68 | I20: 45 | J20: 33 | K20: pendiente | L20: C04 | M20: 100 % de entradas y relaciones asignadas con fuente/fundamento, aprobación académica, QA=pasa y validador con 0 errores y 0 advertencias. | N20: Commit propio; revertir únicamente ese commit y regenerar desde la fuente heredada.

Sheet Plan 233
A1: Atlas 2.0 · plan operativo de 233 entradas | B1: Atlas 2.0 · plan operativo de 233 entradas | C1: Atlas 2.0 · plan operativo de 233 entradas | D1: Atlas 2.0 · plan operativo de 233 entradas | E1: Atlas 2.0 · plan operativo de 233 entradas | F1: Atlas 2.0 · plan operativo de 233 entradas | G1: Atlas 2.0 · plan operativo de 233 entradas | H1: Atlas 2.0 · plan operativo de 233 entradas | I1: Atlas 2.0 · plan operativo de 233 entradas | J1: Atlas 2.0 · plan operativo de 233 entradas | K1: Atlas 2.0 · plan operativo de 233 entradas | L1: Atlas 2.0 · plan operativo de 233 entradas | M1: Atlas 2.0 · plan operativo de 233 entradas | N1: Atlas 2.0 · plan operativo de 233 entradas | O1: Atlas 2.0 · plan operativo de 233 entradas | P1: Atlas 2.0 · plan operativo de 233 entradas | Q1: Atlas 2.0 · plan operativo de 233 entradas | R1: Atlas 2.0 · plan operativo de 233 entradas | S1: Atlas 2.0 · plan operativo de 233 entradas | T1: Atlas 2.0 · plan operativo de 233 entradas | U1: Atlas 2.0 · plan operativo de 233 entradas | V1: Atlas 2.0 · plan operativo de 233 entradas | W1: Atlas 2.0 · plan operativo de 233 entradas | X1: Atlas 2.0 · plan operativo de 233 entradas
A2: Las columnas A–G conservan el contexto heredado. Las decisiones 2.0 empiezan en K y no se confirman automáticamente. | B2: Las columnas A–G conservan el contexto heredado. Las decisiones 2.0 empiezan en K y no se confirman automáticamente. | C2: Las columnas A–G conservan el contexto heredado. Las decisiones 2.0 empiezan en K y no se confirman automáticamente. | D2: Las columnas A–G conservan el contexto heredado. Las decisiones 2.0 empiezan en K y no se confirman automáticamente. | E2: Las columnas A–G conservan el contexto heredado. Las decisiones 2.0 empiezan en K y no se confirman automáticamente. | F2: Las columnas A–G conservan el contexto heredado. Las decisiones 2.0 empiezan en K y no se confirman automáticamente. | G2: Las columnas A–G conservan el contexto heredado. Las decisiones 2.0 empiezan en K y no se confirman automáticamente. | H2: Las columnas A–G conservan el contexto heredado. Las decisiones 2.0 empiezan en K y no se confirman automáticamente. | I2: Las columnas A–G conservan el contexto heredado. Las decisiones 2.0 empiezan en K y no se confirman automáticamente. | J2: Las columnas A–G conservan el contexto heredado. Las decisiones 2.0 empiezan en K y no se confirman automáticamente. | K2: Las columnas A–G conservan el contexto heredado. Las decisiones 2.0 empiezan en K y no se confirman automáticamente. | L2: Las columnas A–G conservan el contexto heredado. Las decisiones 2.0 empiezan en K y no se confirman automáticamente. | M2: Las columnas A–G conservan el contexto heredado. Las decisiones 2.0 empiezan en K y no se confirman automáticamente. | N2: Las columnas A–G conservan el contexto heredado. Las decisiones 2.0 empiezan en K y no se confirman automáticamente. | O2: Las columnas A–G conservan el contexto heredado. Las decisiones 2.0 empiezan en K y no se confirman automáticamente. | P2: Las columnas A–G conservan el contexto heredado. Las decisiones 2.0 empiezan en K y no se confirman automáticamente. | Q2: Las columnas A–G conservan el contexto heredado. Las decisiones 2.0 empiezan en K y no se confirman automáticamente. | R2: Las columnas A–G conservan el contexto heredado. Las decisiones 2.0 empiezan en K y no se confirman automáticamente. | S2: Las columnas A–G conservan el contexto heredado. Las decisiones 2.0 empiezan en K y no se confirman automáticamente. | T2: Las columnas A–G conservan el contexto heredado. Las decisiones 2.0 empiezan en K y no se confirman automáticamente. | U2: Las columnas A–G conservan el contexto heredado. Las decisiones 2.0 empiezan en K y no se confirman automáticamente. | V2: Las columnas A–G conservan el contexto heredado. Las decisiones 2.0 empiezan en K y no se confirman automáticamente. | W2: Las columnas A–G conservan el contexto heredado. Las decisiones 2.0 empiezan en K y no se confirman automáticamente. | X2: Las columnas A–G conservan el contexto heredado. Las decisiones 2.0 empiezan en K y no se confirman automáticamente.
A4: id | B4: Título | C4: Autoría | D4: Año heredado | E4: Estado de candidatura | F4: Corriente(s) candidata(s) | G4: Proceso | H4: Lote | I4: Orden | J4: Complejidad | K4: Estado editorial | L4: Corriente principal 2.0 | M4: Secundarias 2.0 | N4: Operaciones epistémicas | O4: Temporalidades | P4: Orillas / rutas | Q4: Fuente de decisión | R4: Fundamento | S4: Responsable | T4: Fecha revisión | U4: QA técnico | V4: Aprobación académica | W4: Listo para generar | X4: Pendientes / nota
A5: mintz | B5: Caribbean Transformations / Sweetness and Power | C5: Sidney W. Mintz | D5: 1974–85 | E5: A · candidatura preliminar única | F5: C4 · Postplantación, trabajo y desposesión | G5: división + migración | H5: P00 | I5: 1 | J5: piloto aprobado | K5: pendiente_revision_con_texto | O5: {"valor_heredado":"1974–85","publicacion":null,"requiere_revision":true} | R5: El nodo reúne dos obras con argumentos diferentes; no se confirma una corriente única hasta revisar cada componente. | S5: Dirección académica de Pensamiento Caribe | T5: 46242 | U5: pasa | V5: aprobada | W5: =IF(OR(AND(K5="confirmada",L5<>"",N5<>"",O5<>"",P5<>"",Q5<>"",R5<>"",S5<>"",T5<>"",U5="pasa",V5="aprobada",OR(X5="",X5="—")),AND(K5="revisada_redireccion",Q5<>"",R5<>"",S5<>"",T5<>"",U5="pasa",V5="aprobada",OR(X5="",X5="—"))),"SÍ","NO") -> NO | X5: corriente_por_componente; mecanismo_capitalismo_racial; operaciones; orillas
A6: trouillot | B6: The Caribbean Region: An Open Frontier | C6: Michel-Rolph Trouillot | D6: 1992 | E6: C · reparto de colonialidad y candidaturas | F6: C9 · Memorias, espiritualidades y archivos vivos | G6: reclasificación | H6: C04 | I6: 1 | J6: reparto de colonialidad | K6: sin_iniciar | U6: pendiente | V6: pendiente | W6: =IF(OR(AND(K6="confirmada",L6<>"",N6<>"",O6<>"",P6<>"",Q6<>"",R6<>"",S6<>"",T6<>"",U6="pasa",V6="aprobada",OR(X6="",X6="—")),AND(K6="revisada_redireccion",Q6<>"",R6<>"",S6<>"",T6<>"",U6="pasa",V6="aprobada",OR(X6="",X6="—"))),"SÍ","NO") -> NO
A7: casimir | B7: The Haitians: A Decolonial History | C7: Jean Casimir | D7: 2020 | E7: C · reparto de colonialidad y candidaturas | F7: C4 · Postplantación, trabajo y desposesión | G7: reclasificación | H7: C01 | I7: 10 | J7: reparto de colonialidad | K7: sin_iniciar | U7: pendiente | V7: pendiente | W7: =IF(OR(AND(K7="confirmada",L7<>"",N7<>"",O7<>"",P7<>"",Q7<>"",R7<>"",S7<>"",T7<>"",U7="pasa",V7="aprobada",OR(X7="",X7="—")),AND(K7="revisada_redireccion",Q7<>"",R7<>"",S7<>"",T7<>"",U7="pasa",V7="aprobada",OR(X7="",X7="—"))),"SÍ","NO") -> NO
A8: price | B8: Maroon Societies | C8: Richard Price (ed.) | D8: 1973 | E8: B · varias candidaturas preliminares | F8: C3 · Fugas, cimarronajes y emancipaciones | C9 · Memorias, espiritualidades y archivos vivos | G8: reclasificación | H8: P00 | I8: 2 | J8: piloto aprobado | K8: confirmada | L8: fugas_cimarronajes_emancipaciones | N8: reconstruir un archivo; comparar orillas | O8: {"publicacion":{"valor":1973,"era":"EC","precision":"exacta"}} | Q8: https://search.worldcat.org/oclc/805137?tab=details https://www.press.jhu.edu/books/title/1940/maroon-societies | R8: El volumen organiza una comparación hemisférica de comunidades cimarronas y combina fuentes históricas y estudios antropológicos. | S8: Dirección académica de Pensamiento Caribe | T8: 46242 | U8: pasa | V8: aprobada | W8: =IF(OR(AND(K8="confirmada",L8<>"",N8<>"",O8<>"",P8<>"",Q8<>"",R8<>"",S8<>"",T8<>"",U8="pasa",V8="aprobada",OR(X8="",X8="—")),AND(K8="revisada_redireccion",Q8<>"",R8<>"",S8<>"",T8<>"",U8="pasa",V8="aprobada",OR(X8="",X8="—"))),"SÍ","NO") -> NO | X8: orillas
A9: fouchard | B9: Les marrons de la liberté | C9: Jean Fouchard | D9: 1972 | E9: B · varias candidaturas preliminares | F9: C3 · Fugas, cimarronajes y emancipaciones | C7 · Soberanías, fronteras y ocupaciones | G9: reclasificación | H9: B01 | I9: 17 | J9: elección entre candidaturas | K9: sin_iniciar | U9: pendiente | V9: pendiente | W9: =IF(OR(AND(K9="confirmada",L9<>"",N9<>"",O9<>"",P9<>"",Q9<>"",R9<>"",S9<>"",T9<>"",U9="pasa",V9="aprobada",OR(X9="",X9="—")),AND(K9="revisada_redireccion",Q9<>"",R9<>"",S9<>"",T9<>"",U9="pasa",V9="aprobada",OR(X9="",X9="—"))),"SÍ","NO") -> NO
A10: roberts | B10: Freedom as Marronage | C10: Neil Roberts | D10: 2015 | E10: B · varias candidaturas preliminares | F10: C3 · Fugas, cimarronajes y emancipaciones | C7 · Soberanías, fronteras y ocupaciones | G10: reclasificación | H10: B01 | I10: 16 | J10: elección entre candidaturas | K10: sin_iniciar | U10: pendiente | V10: pendiente | W10: =IF(OR(AND(K10="confirmada",L10<>"",N10<>"",O10<>"",P10<>"",Q10<>"",R10<>"",S10<>"",T10<>"",U10="pasa",V10="aprobada",OR(X10="",X10="—")),AND(K10="revisada_redireccion",Q10<>"",R10<>"",S10<>"",T10<>"",U10="pasa",V10="aprobada",OR(X10="",X10="—"))),"SÍ","NO") -> NO
A11: totumo | B11: Los acuerdos y la idealización del palenque en la provincia de Cartagena: el caso del Totumo (1714-1767) | C11: Dolcey Romero Jaramillo | E11: B · varias candidaturas preliminares | F11: C3 · Fugas, cimarronajes y emancipaciones | C9 · Memorias, espiritualidades y archivos vivos | G11: corrección bibliográfica + reclasificación | H11: P00 | I11: 3 | J11: piloto aprobado | K11: confirmada | L11: fugas_cimarronajes_emancipaciones | N11: reconstruir un archivo; confrontar una categoría | O11: {"publicacion":{"valor":2020,"era":"EC","precision":"exacta"},"periodo_estudiado":{"inicio":{"valor":1714,"era":"EC","precision":"exacta"},"fin":{"valor":1767,"era":"EC","precision":"exacta"}}} | Q11: https://revistas.uniatlantico.edu.co/index.php/Historia_Caribe/article/view/2403 https://doi.org/10.15648/hc.37.2020.9 | R11: El artículo reconstruye acuerdos entre cimarrones y autoridades coloniales y cuestiona la idealización del palenque como libertad absoluta. | S11: Dirección académica de Pensamiento Caribe | T11: 46242 | U11: pasa | V11: aprobada | W11: =IF(OR(AND(K11="confirmada",L11<>"",N11<>"",O11<>"",P11<>"",Q11<>"",R11<>"",S11<>"",T11<>"",U11="pasa",V11="aprobada",OR(X11="",X11="—")),AND(K11="revisada_redireccion",Q11<>"",R11<>"",S11<>"",T11<>"",U11="pasa",V11="aprobada",OR(X11="",X11="—"))),"SÍ","NO") -> NO | X11: orillas
A12: ortiz | B12: Contrapunteo cubano / Transculturación | C12: Fernando Ortiz | D12: 1940 | E12: B · varias candidaturas preliminares | F12: C8 · Creolizaciones, traducciones y opacidades | C4 · Postplantación, trabajo y desposesión | G12: división + reclasificación | H12: S01 | I12: 3 | J12: bloqueo editorial | K12: sin_iniciar | U12: pendiente | V12: pendiente | W12: =IF(OR(AND(K12="confirmada",L12<>"",N12<>"",O12<>"",P12<>"",Q12<>"",R12<>"",S12<>"",T12<>"",U12="pasa",V12="aprobada",OR(X12="",X12="—")),AND(K12="revisada_redireccion",Q12<>"",R12<>"",S12<>"",T12<>"",U12="pasa",V12="aprobada",OR(X12="",X12="—"))),"SÍ","NO") -> NO
A13: glissant | B13: Poétique de la Relation / Le discours antillais | C13: Édouard Glissant | D13: 1981–90 | E13: C · reparto de colonialidad y candidaturas | F13: C8 · Creolizaciones, traducciones y opacidades | G13: división + reclasificación | H13: S01 | I13: 7 | J13: bloqueo editorial | K13: sin_iniciar | U13: pendiente | V13: pendiente | W13: =IF(OR(AND(K13="confirmada",L13<>"",N13<>"",O13<>"",P13<>"",Q13<>"",R13<>"",S13<>"",T13<>"",U13="pasa",V13="aprobada",OR(X13="",X13="—")),AND(K13="revisada_redireccion",Q13<>"",R13<>"",S13<>"",T13<>"",U13="pasa",V13="aprobada",OR(X13="",X13="—"))),"SÍ","NO") -> NO
A14: brathwaite | B14: Nation Language / Tidalectics | C14: Kamau Brathwaite | D14: 1984 | E14: B · varias candidaturas preliminares | F14: C8 · Creolizaciones, traducciones y opacidades | C9 · Memorias, espiritualidades y archivos vivos | G14: división + reclasificación | H14: S01 | I14: 5 | J14: bloqueo editorial | K14: sin_iniciar | U14: pendiente | V14: pendiente | W14: =IF(OR(AND(K14="confirmada",L14<>"",N14<>"",O14<>"",P14<>"",Q14<>"",R14<>"",S14<>"",T14<>"",U14="pasa",V14="aprobada",OR(X14="",X14="—")),AND(K14="revisada_redireccion",Q14<>"",R14<>"",S14<>"",T14<>"",U14="pasa",V14="aprobada",OR(X14="",X14="—"))),"SÍ","NO") -> NO
A15: creolite | B15: Éloge de la créolité | C15: Bernabé, Chamoiseau, Confiant | D15: 1989 | E15: A · candidatura preliminar única | F15: C8 · Creolizaciones, traducciones y opacidades | G15: migración | H15: A03 | I15: 8 | J15: confirmación de candidatura única | K15: sin_iniciar | U15: pendiente | V15: pendiente | W15: =IF(OR(AND(K15="confirmada",L15<>"",N15<>"",O15<>"",P15<>"",Q15<>"",R15<>"",S15<>"",T15<>"",U15="pasa",V15="aprobada",OR(X15="",X15="—")),AND(K15="revisada_redireccion",Q15<>"",R15<>"",S15<>"",T15<>"",U15="pasa",V15="aprobada",OR(X15="",X15="—"))),"SÍ","NO") -> NO
A16: monahan | B16: Creolizing Practices of Freedom: Recognition and Dissonance / The Creolizing Subject: Race, Reason, and the Politics of Purity | C16: Michael Monahan | D16: 2011–23 | E16: C · reparto de colonialidad y candidaturas | F16: C8 · Creolizaciones, traducciones y opacidades | G16: división + reclasificación | H16: S01 | I16: 6 | J16: bloqueo editorial | K16: sin_iniciar | U16: pendiente | V16: pendiente | W16: =IF(OR(AND(K16="confirmada",L16<>"",N16<>"",O16<>"",P16<>"",Q16<>"",R16<>"",S16<>"",T16<>"",U16="pasa",V16="aprobada",OR(X16="",X16="—")),AND(K16="revisada_redireccion",Q16<>"",R16<>"",S16<>"",T16<>"",U16="pasa",V16="aprobada",OR(X16="",X16="—"))),"SÍ","NO") -> NO
A17: vete | B17: The Caribbean Oral Tradition | C17: Hanétha Vété-Congolo (ed.) | D17: 2016 | E17: B · varias candidaturas preliminares | F17: C8 · Creolizaciones, traducciones y opacidades | C9 · Memorias, espiritualidades y archivos vivos | G17: reclasificación | H17: B04 | I17: 14 | J17: elección entre candidaturas | K17: sin_iniciar | U17: pendiente | V17: pendiente | W17: =IF(OR(AND(K17="confirmada",L17<>"",N17<>"",O17<>"",P17<>"",Q17<>"",R17<>"",S17<>"",T17<>"",U17="pasa",V17="aprobada",OR(X17="",X17="—")),AND(K17="revisada_redireccion",Q17<>"",R17<>"",S17<>"",T17<>"",U17="pasa",V17="aprobada",OR(X17="",X17="—"))),"SÍ","NO") -> NO
A18: chande | B18: Sonoridades del Chandé en el Caribe seco | C18: borrador / archivo | E18: B · varias candidaturas preliminares | F18: C8 · Creolizaciones, traducciones y opacidades | C9 · Memorias, espiritualidades y archivos vivos | G18: corrección bibliográfica + reclasificación | H18: P00 | I18: 4 | J18: piloto aprobado | K18: confirmada | L18: memorias_espiritualidades_archivos_vivos | M18: creolizaciones_traducciones_opacidades | N18: producir etnografía; escuchar; preservar una memoria; documentar una práctica; teorizar | O18: {"publicacion":{"valor":2016,"era":"EC","precision":"exacta"}} | P18: orillas: La Loma, El Paso, Cesar [territorio estudiado] | Q18: https://dialnet.unirioja.es/descarga/articulo/5888296.pdf https://doi.org/10.15648/cl.24.2016.6 | R18: El texto comprende el Chandé como pensamiento, saber y memoria mediante diálogo comunitario y respeto por el silencio de sabedoras y sabedores. | S18: Dirección académica de Pensamiento Caribe | T18: 46242 | U18: pasa | V18: aprobada | W18: =IF(OR(AND(K18="confirmada",L18<>"",N18<>"",O18<>"",P18<>"",Q18<>"",R18<>"",S18<>"",T18<>"",U18="pasa",V18="aprobada",OR(X18="",X18="—")),AND(K18="revisada_redireccion",Q18<>"",R18<>"",S18<>"",T18<>"",U18="pasa",V18="aprobada",OR(X18="",X18="—"))),"SÍ","NO") -> NO | X18: fechas_del_trabajo_de_campo; duracion_historica; coordenadas_orilla
A19: quintero | B19: Cuerpo y cultura: las músicas «mulatas» y la subversión del baile | C19: Ángel Quintero Rivera | D19: 2009 | E19: B · varias candidaturas preliminares | F19: C8 · Creolizaciones, traducciones y opacidades | C3 · Fugas, cimarronajes y emancipaciones | G19: reclasificación | H19: B03 | I19: 16 | J19: elección entre candidaturas | K19: sin_iniciar | U19: pendiente | V19: pendiente | W19: =IF(OR(AND(K19="confirmada",L19<>"",N19<>"",O19<>"",P19<>"",Q19<>"",R19<>"",S19<>"",T19<>"",U19="pasa",V19="aprobada",OR(X19="",X19="—")),AND(K19="revisada_redireccion",Q19<>"",R19<>"",S19<>"",T19<>"",U19="pasa",V19="aprobada",OR(X19="",X19="—"))),"SÍ","NO") -> NO
A20: perezmorales | B20: Cartagena's Privateers | C20: Edgardo Pérez Morales | D20: 2018 | E20: E · sin correspondencia directa en la taxonomía anterior | G20: reclasificación | H20: DE01 | I20: 15 | J20: sin correspondencia directa | K20: sin_iniciar | U20: pendiente | V20: pendiente | W20: =IF(OR(AND(K20="confirmada",L20<>"",N20<>"",O20<>"",P20<>"",Q20<>"",R20<>"",S20<>"",T20<>"",U20="pasa",V20="aprobada",OR(X20="",X20="—")),AND(K20="revisada_redireccion",Q20<>"",R20<>"",S20<>"",T20<>"",U20="pasa",V20="aprobada",OR(X20="",X20="—"))),"SÍ","NO") -> NO
A21: sherwood | B21: After Abolition: Britain and the Slave Trade | C21: Marika Sherwood | D21: 2007 | E21: E · sin correspondencia directa en la taxonomía anterior | G21: reclasificación | H21: DE01 | I21: 6 | J21: sin correspondencia directa | K21: sin_iniciar | U21: pendiente | V21: pendiente | W21: =IF(OR(AND(K21="confirmada",L21<>"",N21<>"",O21<>"",P21<>"",Q21<>"",R21<>"",S21<>"",T21<>"",U21="pasa",V21="aprobada",OR(X21="",X21="—")),AND(K21="revisada_redireccion",Q21<>"",R21<>"",S21<>"",T21<>"",U21="pasa",V21="aprobada",OR(X21="",X21="—"))),"SÍ","NO") -> NO
A22: cabrera | B22: El Monte | C22: Lydia Cabrera | D22: 1954 | E22: B · varias candidaturas preliminares | F22: C9 · Memorias, espiritualidades y archivos vivos | C8 · Creolizaciones, traducciones y opacidades | G22: reclasificación | H22: B05 | I22: 10 | J22: elección entre candidaturas | K22: sin_iniciar | U22: pendiente | V22: pendiente | W22: =IF(OR(AND(K22="confirmada",L22<>"",N22<>"",O22<>"",P22<>"",Q22<>"",R22<>"",S22<>"",T22<>"",U22="pasa",V22="aprobada",OR(X22="",X22="—")),AND(K22="revisada_redireccion",Q22<>"",R22<>"",S22<>"",T22<>"",U22="pasa",V22="aprobada",OR(X22="",X22="—"))),"SÍ","NO") -> NO
A23: tambu | B23: Tambú: Curaçao's African-Caribbean Ritual | C23: Nanette de Jong | D23: 2012 | E23: B · varias candidaturas preliminares | F23: C9 · Memorias, espiritualidades y archivos vivos | C8 · Creolizaciones, traducciones y opacidades | G23: reclasificación | H23: B05 | I23: 15 | J23: elección entre candidaturas | K23: sin_iniciar | U23: pendiente | V23: pendiente | W23: =IF(OR(AND(K23="confirmada",L23<>"",N23<>"",O23<>"",P23<>"",Q23<>"",R23<>"",S23<>"",T23<>"",U23="pasa",V23="aprobada",OR(X23="",X23="—")),AND(K23="revisada_redireccion",Q23<>"",R23<>"",S23<>"",T23<>"",U23="pasa",V23="aprobada",OR(X23="",X23="—"))),"SÍ","NO") -> NO
A24: bonilla | B24: Non-Sovereign Futures | C24: Yarimar Bonilla | D24: 2015 | E24: C · reparto de colonialidad y candidaturas | F24: C7 · Soberanías, fronteras y ocupaciones | G24: reclasificación | H24: C02 | I24: 13 | J24: reparto de colonialidad | K24: sin_iniciar | U24: pendiente | V24: pendiente | W24: =IF(OR(AND(K24="confirmada",L24<>"",N24<>"",O24<>"",P24<>"",Q24<>"",R24<>"",S24<>"",T24<>"",U24="pasa",V24="aprobada",OR(X24="",X24="—")),AND(K24="revisada_redireccion",Q24<>"",R24<>"",S24<>"",T24<>"",U24="pasa",V24="aprobada",OR(X24="",X24="—"))),"SÍ","NO") -> NO
A25: lindskoog | B25: Detain and Punish: Haitian Refugees | C25: Carl Lindskoog | D25: 2018 | E25: A · candidatura preliminar única | F25: C7 · Soberanías, fronteras y ocupaciones | G25: migración | H25: A03 | I25: 5 | J25: confirmación de candidatura única | K25: sin_iniciar | U25: pendiente | V25: pendiente | W25: =IF(OR(AND(K25="confirmada",L25<>"",N25<>"",O25<>"",P25<>"",Q25<>"",R25<>"",S25<>"",T25<>"",U25="pasa",V25="aprobada",OR(X25="",X25="—")),AND(K25="revisada_redireccion",Q25<>"",R25<>"",S25<>"",T25<>"",U25="pasa",V25="aprobada",OR(X25="",X25="—"))),"SÍ","NO") -> NO
A26: ferdinand | B26: Une écologie décoloniale | C26: Malcom Ferdinand | D26: 2019 | E26: C · reparto de colonialidad y candidaturas | F26: C6 · Huracanes, ecologías y materialidades vivas | G26: reclasificación | H26: C01 | I26: 16 | J26: reparto de colonialidad | K26: sin_iniciar | U26: pendiente | V26: pendiente | W26: =IF(OR(AND(K26="confirmada",L26<>"",N26<>"",O26<>"",P26<>"",Q26<>"",R26<>"",S26<>"",T26<>"",U26="pasa",V26="aprobada",OR(X26="",X26="—")),AND(K26="revisada_redireccion",Q26<>"",R26<>"",S26<>"",T26<>"",U26="pasa",V26="aprobada",OR(X26="",X26="—"))),"SÍ","NO") -> NO
A27: beyondsun | B27: Beyond Sun and Sand | C27: Baver & Lynch (eds.) | D27: 2006 | E27: A · candidatura preliminar única | F27: C6 · Huracanes, ecologías y materialidades vivas | G27: migración | H27: A02 | I27: 6 | J27: confirmación de candidatura única | K27: sin_iniciar | U27: pendiente | V27: pendiente | W27: =IF(OR(AND(K27="confirmada",L27<>"",N27<>"",O27<>"",P27<>"",Q27<>"",R27<>"",S27<>"",T27<>"",U27="pasa",V27="aprobada",OR(X27="",X27="—")),AND(K27="revisada_redireccion",Q27<>"",R27<>"",S27<>"",T27<>"",U27="pasa",V27="aprobada",OR(X27="",X27="—"))),"SÍ","NO") -> NO
A28: aftershocks | B28: Aftershocks of Disaster (huracán María) | C28: Bonilla & LeBrón (eds.) | D28: 2019 | E28: B · varias candidaturas preliminares | F28: C6 · Huracanes, ecologías y materialidades vivas | C7 · Soberanías, fronteras y ocupaciones | G28: reclasificación | H28: B03 | I28: 2 | J28: elección entre candidaturas | K28: sin_iniciar | U28: pendiente | V28: pendiente | W28: =IF(OR(AND(K28="confirmada",L28<>"",N28<>"",O28<>"",P28<>"",Q28<>"",R28<>"",S28<>"",T28<>"",U28="pasa",V28="aprobada",OR(X28="",X28="—")),AND(K28="revisada_redireccion",Q28<>"",R28<>"",S28<>"",T28<>"",U28="pasa",V28="aprobada",OR(X28="",X28="—"))),"SÍ","NO") -> NO
A29: rodney | B29: How Europe Underdeveloped Africa | C29: Walter Rodney | D29: 1972 | E29: D · reparto de colonialidad | G29: reclasificación | H29: DE01 | I29: 2 | J29: colonialidad sin destino derivable | K29: sin_iniciar | U29: pendiente | V29: pendiente | W29: =IF(OR(AND(K29="confirmada",L29<>"",N29<>"",O29<>"",P29<>"",Q29<>"",R29<>"",S29<>"",T29<>"",U29="pasa",V29="aprobada",OR(X29="",X29="—")),AND(K29="revisada_redireccion",Q29<>"",R29<>"",S29<>"",T29<>"",U29="pasa",V29="aprobada",OR(X29="",X29="—"))),"SÍ","NO") -> NO
A30: araujo | B30: Reparations for Slavery and the Slave Trade: A Transnational and Comparative History | C30: Ana Lucia Araujo | D30: 2017 | E30: A · candidatura preliminar única | F30: C9 · Memorias, espiritualidades y archivos vivos | G30: migración | H30: A03 | I30: 12 | J30: confirmación de candidatura única | K30: sin_iniciar | U30: pendiente | V30: pendiente | W30: =IF(OR(AND(K30="confirmada",L30<>"",N30<>"",O30<>"",P30<>"",Q30<>"",R30<>"",S30<>"",T30<>"",U30="pasa",V30="aprobada",OR(X30="",X30="—")),AND(K30="revisada_redireccion",Q30<>"",R30<>"",S30<>"",T30<>"",U30="pasa",V30="aprobada",OR(X30="",X30="—"))),"SÍ","NO") -> NO
A31: manoalzada | B31: A mano alzada: diáspora intelectual afrocolombiana | C31: archivo | D31: 2013 | E31: B · varias candidaturas preliminares | F31: C9 · Memorias, espiritualidades y archivos vivos | C7 · Soberanías, fronteras y ocupaciones | G31: corrección bibliográfica + reclasificación | H31: S01 | I31: 9 | J31: bloqueo editorial | K31: sin_iniciar | U31: pendiente | V31: pendiente | W31: =IF(OR(AND(K31="confirmada",L31<>"",N31<>"",O31<>"",P31<>"",Q31<>"",R31<>"",S31<>"",T31<>"",U31="pasa",V31="aprobada",OR(X31="",X31="—")),AND(K31="revisada_redireccion",Q31<>"",R31<>"",S31<>"",T31<>"",U31="pasa",V31="aprobada",OR(X31="",X31="—"))),"SÍ","NO") -> NO
A32: gudynas | B32: Extractivismos | C32: Eduardo Gudynas | D32: 2015 | E32: A · candidatura preliminar única | F32: C6 · Huracanes, ecologías y materialidades vivas | G32: migración | H32: A02 | I32: 5 | J32: confirmación de candidatura única | K32: sin_iniciar | U32: pendiente | V32: pendiente | W32: =IF(OR(AND(K32="confirmada",L32<>"",N32<>"",O32<>"",P32<>"",Q32<>"",R32<>"",S32<>"",T32<>"",U32="pasa",V32="aprobada",OR(X32="",X32="—")),AND(K32="revisada_redireccion",Q32<>"",R32<>"",S32<>"",T32<>"",U32="pasa",V32="aprobada",OR(X32="",X32="—"))),"SÍ","NO") -> NO
A33: esquiva | B33: La esquiva promesa de desarrollo | C33: archivo | E33: E · sin correspondencia directa en la taxonomía anterior | G33: corrección bibliográfica + reclasificación | H33: S01 | I33: 11 | J33: bloqueo editorial | K33: sin_iniciar | U33: pendiente | V33: pendiente | W33: =IF(OR(AND(K33="confirmada",L33<>"",N33<>"",O33<>"",P33<>"",Q33<>"",R33<>"",S33<>"",T33<>"",U33="pasa",V33="aprobada",OR(X33="",X33="—")),AND(K33="revisada_redireccion",Q33<>"",R33<>"",S33<>"",T33<>"",U33="pasa",V33="aprobada",OR(X33="",X33="—"))),"SÍ","NO") -> NO
A34: workercane | B34: Worker in the Cane: A Puerto Rican Life History | C34: Sidney W. Mintz | D34: 1960 | E34: A · candidatura preliminar única | F34: C4 · Postplantación, trabajo y desposesión | G34: migración | H34: A02 | I34: 2 | J34: confirmación de candidatura única | K34: sin_iniciar | U34: pendiente | V34: pendiente | W34: =IF(OR(AND(K34="confirmada",L34<>"",N34<>"",O34<>"",P34<>"",Q34<>"",R34<>"",S34<>"",T34<>"",U34="pasa",V34="aprobada",OR(X34="",X34="—")),AND(K34="revisada_redireccion",Q34<>"",R34<>"",S34<>"",T34<>"",U34="pasa",V34="aprobada",OR(X34="",X34="—"))),"SÍ","NO") -> NO
A35: steward | B35: The People of Puerto Rico: A Study in Social Anthropology | C35: Julian Steward et al. (con Mintz, Wolf, Padilla Seda) | D35: 1956 | E35: A · candidatura preliminar única | F35: C4 · Postplantación, trabajo y desposesión | G35: fusión + migración | H35: P00 | I35: 5 | J35: piloto aprobado | K35: confirmada | L35: postplantacion_trabajo_desposesion | N35: producir etnografía; comparar orillas; teorizar | O35: {"publicacion":{"valor":1956,"era":"EC","precision":"exacta"}} | Q35: https://eric.ed.gov/?id=ED019306 https://files.archon.library.illinois.edu/uasfa/1502021.pdf | R35: La obra compara subculturas puertorriqueñas configuradas por entornos y regímenes económicos locales; el identificador más antiguo conserva los enlaces citables. | S35: Dirección académica de Pensamiento Caribe | T35: 46242 | U35: pasa | V35: aprobada | W35: =IF(OR(AND(K35="confirmada",L35<>"",N35<>"",O35<>"",P35<>"",Q35<>"",R35<>"",S35<>"",T35<>"",U35="pasa",V35="aprobada",OR(X35="",X35="—")),AND(K35="revisada_redireccion",Q35<>"",R35<>"",S35<>"",T35<>"",U35="pasa",V35="aprobada",OR(X35="",X35="—"))),"SÍ","NO") -> NO | X35: orillas
A36: olwigstjohn | B36: Cultural Adaptation and Resistance on St. John | C36: Karen Fog Olwig | D36: 1985 | E36: B · varias candidaturas preliminares | F36: C4 · Postplantación, trabajo y desposesión | C9 · Memorias, espiritualidades y archivos vivos | G36: reclasificación | H36: B02 | I36: 16 | J36: elección entre candidaturas | K36: sin_iniciar | U36: pendiente | V36: pendiente | W36: =IF(OR(AND(K36="confirmada",L36<>"",N36<>"",O36<>"",P36<>"",Q36<>"",R36<>"",S36<>"",T36<>"",U36="pasa",V36="aprobada",OR(X36="",X36="—")),AND(K36="revisada_redireccion",Q36<>"",R36<>"",S36<>"",T36<>"",U36="pasa",V36="aprobada",OR(X36="",X36="—"))),"SÍ","NO") -> NO
A37: hagedorn | B37: Divine Utterances: The Performance of Afro-Cuban Santería | C37: Katherine J. Hagedorn | D37: 2001 | E37: B · varias candidaturas preliminares | F37: C9 · Memorias, espiritualidades y archivos vivos | C8 · Creolizaciones, traducciones y opacidades | G37: reclasificación | H37: B05 | I37: 9 | J37: elección entre candidaturas | K37: sin_iniciar | U37: pendiente | V37: pendiente | W37: =IF(OR(AND(K37="confirmada",L37<>"",N37<>"",O37<>"",P37<>"",Q37<>"",R37<>"",S37<>"",T37<>"",U37="pasa",V37="aprobada",OR(X37="",X37="—")),AND(K37="revisada_redireccion",Q37<>"",R37<>"",S37<>"",T37<>"",U37="pasa",V37="aprobada",OR(X37="",X37="—"))),"SÍ","NO") -> NO
A38: pricefirst | B38: First-Time: The Historical Vision of an Afro-American People | C38: Richard Price | D38: 1983 | E38: B · varias candidaturas preliminares | F38: C3 · Fugas, cimarronajes y emancipaciones | C9 · Memorias, espiritualidades y archivos vivos | G38: reclasificación | H38: B02 | I38: 3 | J38: elección entre candidaturas | K38: sin_iniciar | U38: pendiente | V38: pendiente | W38: =IF(OR(AND(K38="confirmada",L38<>"",N38<>"",O38<>"",P38<>"",Q38<>"",R38<>"",S38<>"",T38<>"",U38="pasa",V38="aprobada",OR(X38="",X38="—")),AND(K38="revisada_redireccion",Q38<>"",R38<>"",S38<>"",T38<>"",U38="pasa",V38="aprobada",OR(X38="",X38="—"))),"SÍ","NO") -> NO
A39: dunham | B39: Island Possessed | C39: Katherine Dunham | D39: 1969 | E39: B · varias candidaturas preliminares | F39: C9 · Memorias, espiritualidades y archivos vivos | C8 · Creolizaciones, traducciones y opacidades | G39: reclasificación | H39: B05 | I39: 11 | J39: elección entre candidaturas | K39: sin_iniciar | U39: pendiente | V39: pendiente | W39: =IF(OR(AND(K39="confirmada",L39<>"",N39<>"",O39<>"",P39<>"",Q39<>"",R39<>"",S39<>"",T39<>"",U39="pasa",V39="aprobada",OR(X39="",X39="—")),AND(K39="revisada_redireccion",Q39<>"",R39<>"",S39<>"",T39<>"",U39="pasa",V39="aprobada",OR(X39="",X39="—"))),"SÍ","NO") -> NO
A40: friedemannlengua | B40: Lengua y sociedad en el Palenque de San Basilio | C40: Carlos Patiño Rosselli & Nina S. de Friedemann | D40: 1983 | E40: B · varias candidaturas preliminares | F40: C8 · Creolizaciones, traducciones y opacidades | C3 · Fugas, cimarronajes y emancipaciones | G40: reclasificación | H40: B04 | I40: 1 | J40: elección entre candidaturas | K40: sin_iniciar | U40: pendiente | V40: pendiente | W40: =IF(OR(AND(K40="confirmada",L40<>"",N40<>"",O40<>"",P40<>"",Q40<>"",R40<>"",S40<>"",T40<>"",U40="pasa",V40="aprobada",OR(X40="",X40="—")),AND(K40="revisada_redireccion",Q40<>"",R40<>"",S40<>"",T40<>"",U40="pasa",V40="aprobada",OR(X40="",X40="—"))),"SÍ","NO") -> NO
A41: mamalola | B41: Mama Lola: A Vodou Priestess in Brooklyn | C41: Karen McCarthy Brown | D41: 1991 | E41: B · varias candidaturas preliminares | F41: C9 · Memorias, espiritualidades y archivos vivos | C8 · Creolizaciones, traducciones y opacidades | G41: reclasificación | H41: B05 | I41: 13 | J41: elección entre candidaturas | K41: sin_iniciar | U41: pendiente | V41: pendiente | W41: =IF(OR(AND(K41="confirmada",L41<>"",N41<>"",O41<>"",P41<>"",Q41<>"",R41<>"",S41<>"",T41<>"",U41="pasa",V41="aprobada",OR(X41="",X41="—")),AND(K41="revisada_redireccion",Q41<>"",R41<>"",S41<>"",T41<>"",U41="pasa",V41="aprobada",OR(X41="",X41="—"))),"SÍ","NO") -> NO
A42: besson | B42: Martha Brae's Two Histories | C42: Jean Besson | D42: 2002 | E42: B · varias candidaturas preliminares | F42: C4 · Postplantación, trabajo y desposesión | C7 · Soberanías, fronteras y ocupaciones | G42: reclasificación | H42: B02 | I42: 11 | J42: elección entre candidaturas | K42: sin_iniciar | U42: pendiente | V42: pendiente | W42: =IF(OR(AND(K42="confirmada",L42<>"",N42<>"",O42<>"",P42<>"",Q42<>"",R42<>"",S42<>"",T42<>"",U42="pasa",V42="aprobada",OR(X42="",X42="—")),AND(K42="revisada_redireccion",Q42<>"",R42<>"",S42<>"",T42<>"",U42="pasa",V42="aprobada",OR(X42="",X42="—"))),"SÍ","NO") -> NO
A43: taylor | B43: Nation Dance: Religion, Identity, and Cultural Difference in the Caribbean | C43: Patrick Taylor (ed.) | D43: 2001 | E43: B · varias candidaturas preliminares | F43: C9 · Memorias, espiritualidades y archivos vivos | C8 · Creolizaciones, traducciones y opacidades | G43: reclasificación | H43: B05 | I43: 14 | J43: elección entre candidaturas | K43: sin_iniciar | U43: pendiente | V43: pendiente | W43: =IF(OR(AND(K43="confirmada",L43<>"",N43<>"",O43<>"",P43<>"",Q43<>"",R43<>"",S43<>"",T43<>"",U43="pasa",V43="aprobada",OR(X43="",X43="—")),AND(K43="revisada_redireccion",Q43<>"",R43<>"",S43<>"",T43<>"",U43="pasa",V43="aprobada",OR(X43="",X43="—"))),"SÍ","NO") -> NO
A44: peasantscapital | B44: Peasants and Capital: Dominica in the World Economy | C44: Michel-Rolph Trouillot | D44: 1988 | E44: A · candidatura preliminar única | F44: C4 · Postplantación, trabajo y desposesión | G44: migración | H44: A02 | I44: 1 | J44: confirmación de candidatura única | K44: sin_iniciar | U44: pendiente | V44: pendiente | W44: =IF(OR(AND(K44="confirmada",L44<>"",N44<>"",O44<>"",P44<>"",Q44<>"",R44<>"",S44<>"",T44<>"",U44="pasa",V44="aprobada",OR(X44="",X44="—")),AND(K44="revisada_redireccion",Q44<>"",R44<>"",S44<>"",T44<>"",U44="pasa",V44="aprobada",OR(X44="",X44="—"))),"SÍ","NO") -> NO
A45: chevannes | B45: Rastafari: Roots and Ideology | C45: Barry Chevannes | D45: 1994 | E45: B · varias candidaturas preliminares | F45: C9 · Memorias, espiritualidades y archivos vivos | C3 · Fugas, cimarronajes y emancipaciones | G45: reclasificación | H45: B05 | I45: 1 | J45: elección entre candidaturas | K45: sin_iniciar | U45: pendiente | V45: pendiente | W45: =IF(OR(AND(K45="confirmada",L45<>"",N45<>"",O45<>"",P45<>"",Q45<>"",R45<>"",S45<>"",T45<>"",U45="pasa",V45="aprobada",OR(X45="",X45="—")),AND(K45="revisada_redireccion",Q45<>"",R45<>"",S45<>"",T45<>"",U45="pasa",V45="aprobada",OR(X45="",X45="—"))),"SÍ","NO") -> NO
A46: escalante | B46: El Palenque de San Basilio | C46: Aquiles Escalante | D46: 1954 | E46: B · varias candidaturas preliminares | F46: C3 · Fugas, cimarronajes y emancipaciones | C9 · Memorias, espiritualidades y archivos vivos | G46: reclasificación | H46: B02 | I46: 2 | J46: elección entre candidaturas | K46: sin_iniciar | U46: pendiente | V46: pendiente | W46: =IF(OR(AND(K46="confirmada",L46<>"",N46<>"",O46<>"",P46<>"",Q46<>"",R46<>"",S46<>"",T46<>"",U46="pasa",V46="aprobada",OR(X46="",X46="—")),AND(K46="revisada_redireccion",Q46<>"",R46<>"",S46<>"",T46<>"",U46="pasa",V46="aprobada",OR(X46="",X46="—"))),"SÍ","NO") -> NO
A47: rebeldestiny | B47: Rebel Destiny: Among the Bush Negroes of Dutch Guiana | C47: Melville & Frances Herskovits | D47: 1934 | E47: B · varias candidaturas preliminares | F47: C3 · Fugas, cimarronajes y emancipaciones | C9 · Memorias, espiritualidades y archivos vivos | G47: reclasificación | H47: B02 | I47: 5 | J47: elección entre candidaturas | K47: sin_iniciar | U47: pendiente | V47: pendiente | W47: =IF(OR(AND(K47="confirmada",L47<>"",N47<>"",O47<>"",P47<>"",Q47<>"",R47<>"",S47<>"",T47<>"",U47="pasa",V47="aprobada",OR(X47="",X47="—")),AND(K47="revisada_redireccion",Q47<>"",R47<>"",S47<>"",T47<>"",U47="pasa",V47="aprobada",OR(X47="",X47="—"))),"SÍ","NO") -> NO
... A54: alabi | B54: Alabi's World | C54: Richard Price | D54: 1990 | E54: B · varias candidaturas preliminares | F54: C3 · Fugas, cimarronajes y emancipaciones | C7 · Soberanías, fronteras y ocupaciones | G54: reclasificación | H54: B01 | I54: 14 | J54: elección entre candidaturas | K54: sin_iniciar | U54: pendiente | V54: pendiente | W54: =IF(OR(AND(K54="confirmada",L54<>"",N54<>"",O54<>"",P54<>"",Q54<>"",R54<>"",S54<>"",T54<>"",U54="pasa",V54="aprobada",OR(X54="",X54="—")),AND(K54="revisada_redireccion",Q54<>"",R54<>"",S54<>"",T54<>"",U54="pasa",V54="aprobada",OR(X54="",X54="—"))),"SÍ","NO") -> NO
A55: exceptviolence | B55: Exceptional Violence: Embodied Citizenship in Transnational Jamaica | C55: Deborah A. Thomas | D55: 2011 | E55: E · sin correspondencia directa en la taxonomía anterior | G55: reclasificación | H55: DE01 | I55: 16 | J55: sin correspondencia directa | K55: sin_iniciar | U55: pendiente | V55: pendiente | W55: =IF(OR(AND(K55="confirmada",L55<>"",N55<>"",O55<>"",P55<>"",Q55<>"",R55<>"",S55<>"",T55<>"",U55="pasa",V55="aprobada",OR(X55="",X55="—")),AND(K55="revisada_redireccion",Q55<>"",R55<>"",S55<>"",T55<>"",U55="pasa",V55="aprobada",OR(X55="",X55="—"))),"SÍ","NO") -> NO
A56: modernblackness | B56: Modern Blackness: Nationalism, Globalization, and the Politics of Culture in Jamaica | C56: Deborah A. Thomas | D56: 2004 | E56: A · candidatura preliminar única | F56: C8 · Creolizaciones, traducciones y opacidades | G56: migración | H56: A03 | I56: 6 | J56: confirmación de candidatura única | K56: sin_iniciar | U56: pendiente | V56: pendiente | W56: =IF(OR(AND(K56="confirmada",L56<>"",N56<>"",O56<>"",P56<>"",Q56<>"",R56<>"",S56<>"",T56<>"",U56="pasa",V56="aprobada",OR(X56="",X56="—")),AND(K56="revisada_redireccion",Q56<>"",R56<>"",S56<>"",T56<>"",U56="pasa",V56="aprobada",OR(X56="",X56="—"))),"SÍ","NO") -> NO
A57: citizenshipedge | B57: Citizenship on the Edge: Sex, Gender, Race | C57: Nancy J. Hirschmann & Deborah A. Thomas (eds.) | D57: 2019 | E57: B · varias candidaturas preliminares | F57: C10 · Cuerpos, parentescos y eróticas | C7 · Soberanías, fronteras y ocupaciones | G57: reclasificación | H57: B01 | I57: 3 | J57: elección entre candidaturas | K57: sin_iniciar | U57: pendiente | V57: pendiente | W57: =IF(OR(AND(K57="confirmada",L57<>"",N57<>"",O57<>"",P57<>"",Q57<>"",R57<>"",S57<>"",T57<>"",U57="pasa",V57="aprobada",OR(X57="",X57="—")),AND(K57="revisada_redireccion",Q57<>"",R57<>"",S57<>"",T57<>"",U57="pasa",V57="aprobada",OR(X57="",X57="—"))),"SÍ","NO") -> NO
A58: politicallife | B58: Political Life in the Wake of the Plantation: Sovereignty, Witnessing, Repair | C58: Deborah A. Thomas | D58: 2019 | E58: A · candidatura preliminar única | F58: C4 · Postplantación, trabajo y desposesión | G58: migración | H58: A02 | I58: 4 | J58: confirmación de candidatura única | K58: sin_iniciar | U58: pendiente | V58: pendiente | W58: =IF(OR(AND(K58="confirmada",L58<>"",N58<>"",O58<>"",P58<>"",Q58<>"",R58<>"",S58<>"",T58<>"",U58="pasa",V58="aprobada",OR(X58="",X58="—")),AND(K58="revisada_redireccion",Q58<>"",R58<>"",S58<>"",T58<>"",U58="pasa",V58="aprobada",OR(X58="",X58="—"))),"SÍ","NO") -> NO
A59: downtownladies | B59: Downtown Ladies: Informal Commercial Importers, a Haitian Anthropologist, and Self-Making in Jamaica | C59: Gina Athena Ulysse | D59: 2007 | E59: A · candidatura preliminar única | F59: C10 · Cuerpos, parentescos y eróticas | G59: migración | H59: A01 | I59: 2 | J59: confirmación de candidatura única | K59: sin_iniciar | U59: pendiente | V59: pendiente | W59: =IF(OR(AND(K59="confirmada",L59<>"",N59<>"",O59<>"",P59<>"",Q59<>"",R59<>"",S59<>"",T59<>"",U59="pasa",V59="aprobada",OR(X59="",X59="—")),AND(K59="revisada_redireccion",Q59<>"",R59<>"",S59<>"",T59<>"",U59="pasa",V59="aprobada",OR(X59="",X59="—"))),"SÍ","NO") -> NO
A60: reddock | B60: Women, Labour and Politics in Trinidad and Tobago: A History | C60: Rhoda Reddock | D60: 1994 | E60: A · candidatura preliminar única | F60: C10 · Cuerpos, parentescos y eróticas | G60: migración | H60: A01 | I60: 6 | J60: confirmación de candidatura única | K60: sin_iniciar | U60: pendiente | V60: pendiente | W60: =IF(OR(AND(K60="confirmada",L60<>"",N60<>"",O60<>"",P60<>"",Q60<>"",R60<>"",S60<>"",T60<>"",U60="pasa",V60="aprobada",OR(X60="",X60="—")),AND(K60="revisada_redireccion",Q60<>"",R60<>"",S60<>"",T60<>"",U60="pasa",V60="aprobada",OR(X60="",X60="—"))),"SÍ","NO") -> NO
A61: caribjourneys | B61: Caribbean Journeys: An Ethnography of Migration and Home in Three Family Networks | C61: Karen Fog Olwig | D61: 2007 | E61: B · varias candidaturas preliminares | F61: C7 · Soberanías, fronteras y ocupaciones | C9 · Memorias, espiritualidades y archivos vivos | G61: reclasificación | H61: B03 | I61: 10 | J61: elección entre candidaturas | K61: sin_iniciar | U61: pendiente | V61: pendiente | W61: =IF(OR(AND(K61="confirmada",L61<>"",N61<>"",O61<>"",P61<>"",Q61<>"",R61<>"",S61<>"",T61<>"",U61="pasa",V61="aprobada",OR(X61="",X61="—")),AND(K61="revisada_redireccion",Q61<>"",R61<>"",S61<>"",T61<>"",U61="pasa",V61="aprobada",OR(X61="",X61="—"))),"SÍ","NO") -> NO
A62: globalculture | B62: Global Culture, Island Identity: Continuity and Change in the Afro-Caribbean Community of Nevis | C62: Karen Fog Olwig | D62: 1993 | E62: B · varias candidaturas preliminares | F62: C4 · Postplantación, trabajo y desposesión | C7 · Soberanías, fronteras y ocupaciones | G62: reclasificación | H62: B02 | I62: 10 | J62: elección entre candidaturas | K62: sin_iniciar | U62: pendiente | V62: pendiente | W62: =IF(OR(AND(K62="confirmada",L62<>"",N62<>"",O62<>"",P62<>"",Q62<>"",R62<>"",S62<>"",T62<>"",U62="pasa",V62="aprobada",OR(X62="",X62="—")),AND(K62="revisada_redireccion",Q62<>"",R62<>"",S62<>"",T62<>"",U62="pasa",V62="aprobada",OR(X62="",X62="—"))),"SÍ","NO") -> NO
A63: islandscity | B63: Islands in the City: West Indian Migration to New York | C63: Nancy Foner (ed.) | D63: 2001 | E63: A · candidatura preliminar única | F63: C7 · Soberanías, fronteras y ocupaciones | G63: migración | H63: A02 | I63: 14 | J63: confirmación de candidatura única | K63: sin_iniciar | U63: pendiente | V63: pendiente | W63: =IF(OR(AND(K63="confirmada",L63<>"",N63<>"",O63<>"",P63<>"",Q63<>"",R63<>"",S63<>"",T63<>"",U63="pasa",V63="aprobada",OR(X63="",X63="—")),AND(K63="revisada_redireccion",Q63<>"",R63<>"",S63<>"",T63<>"",U63="pasa",V63="aprobada",OR(X63="",X63="—"))),"SÍ","NO") -> NO
A64: callaloonation | B64: Callaloo Nation: Metaphors of Race and Religious Identity among South Asians in Trinidad | C64: Aisha Khan | D64: 2004 | E64: B · varias candidaturas preliminares | F64: C8 · Creolizaciones, traducciones y opacidades | C9 · Memorias, espiritualidades y archivos vivos | G64: reclasificación | H64: B04 | I64: 7 | J64: elección entre candidaturas | K64: sin_iniciar | U64: pendiente | V64: pendiente | W64: =IF(OR(AND(K64="confirmada",L64<>"",N64<>"",O64<>"",P64<>"",Q64<>"",R64<>"",S64<>"",T64<>"",U64="pasa",V64="aprobada",OR(X64="",X64="—")),AND(K64="revisada_redireccion",Q64<>"",R64<>"",S64<>"",T64<>"",U64="pasa",V64="aprobada",OR(X64="",X64="—"))),"SÍ","NO") -> NO
A65: reconfdominic | B65: Reconfiguring Dominicanness | C65: Kimberly Eison Simmons | D65: 2002 | E65: D · reparto de colonialidad | G65: reclasificación | H65: DE01 | I65: 4 | J65: colonialidad sin destino derivable | K65: sin_iniciar | U65: pendiente | V65: pendiente | W65: =IF(OR(AND(K65="confirmada",L65<>"",N65<>"",O65<>"",P65<>"",Q65<>"",R65<>"",S65<>"",T65<>"",U65="pasa",V65="aprobada",OR(X65="",X65="—")),AND(K65="revisada_redireccion",Q65<>"",R65<>"",S65<>"",T65<>"",U65="pasa",V65="aprobada",OR(X65="",X65="—"))),"SÍ","NO") -> NO
A66: cuijla | B66: Cuijla: Esbozo etnográfico de un pueblo negro | C66: Gonzalo Aguirre Beltrán | D66: 1958 | E66: B · varias candidaturas preliminares | F66: C4 · Postplantación, trabajo y desposesión | C9 · Memorias, espiritualidades y archivos vivos | G66: reclasificación | H66: B02 | I66: 15 | J66: elección entre candidaturas | K66: sin_iniciar | U66: pendiente | V66: pendiente | W66: =IF(OR(AND(K66="confirmada",L66<>"",N66<>"",O66<>"",P66<>"",Q66<>"",R66<>"",S66<>"",T66<>"",U66="pasa",V66="aprobada",OR(X66="",X66="—")),AND(K66="revisada_redireccion",Q66<>"",R66<>"",S66<>"",T66<>"",U66="pasa",V66="aprobada",OR(X66="",X66="—"))),"SÍ","NO") -> NO
A67: chocolatecorn | B67: Chocolate and Corn Flour: History, Race, and Place in the Making of Black Mexico | C67: Laura A. Lewis | D67: 2012 | E67: C · reparto de colonialidad y candidaturas | F67: C9 · Memorias, espiritualidades y archivos vivos | G67: reclasificación | H67: C03 | I67: 11 | J67: reparto de colonialidad | K67: sin_iniciar | U67: pendiente | V67: pendiente | W67: =IF(OR(AND(K67="confirmada",L67<>"",N67<>"",O67<>"",P67<>"",Q67<>"",R67<>"",S67<>"",T67<>"",U67="pasa",V67="aprobada",OR(X67="",X67="—")),AND(K67="revisada_redireccion",Q67<>"",R67<>"",S67<>"",T67<>"",U67="pasa",V67="aprobada",OR(X67="",X67="—"))),"SÍ","NO") -> NO
A68: womenancestors | B68: Women and the Ancestors: Black Carib Kinship and Ritual | C68: Virginia Kerns | D68: 1983 | E68: B · varias candidaturas preliminares | F68: C10 · Cuerpos, parentescos y eróticas | C9 · Memorias, espiritualidades y archivos vivos | G68: reclasificación | H68: B01 | I68: 13 | J68: elección entre candidaturas | K68: sin_iniciar | U68: pendiente | V68: pendiente | W68: =IF(OR(AND(K68="confirmada",L68<>"",N68<>"",O68<>"",P68<>"",Q68<>"",R68<>"",S68<>"",T68<>"",U68="pasa",V68="aprobada",OR(X68="",X68="—")),AND(K68="revisada_redireccion",Q68<>"",R68<>"",S68<>"",T68<>"",U68="pasa",V68="aprobada",OR(X68="",X68="—"))),"SÍ","NO") -> NO
A69: afrocentroam | B69: Afro Central Americans in New York City: Garifuna Tales of Transnational Movements in Racialized Space | C69: Sarah England | D69: 2006 | E69: A · candidatura preliminar única | F69: C7 · Soberanías, fronteras y ocupaciones | G69: migración | H69: A02 | I69: 12 | J69: confirmación de candidatura única | K69: sin_iniciar | U69: pendiente | V69: pendiente | W69: =IF(OR(AND(K69="confirmada",L69<>"",N69<>"",O69<>"",P69<>"",Q69<>"",R69<>"",S69<>"",T69<>"",U69="pasa",V69="aprobada",OR(X69="",X69="—")),AND(K69="revisada_redireccion",Q69<>"",R69<>"",S69<>"",T69<>"",U69="pasa",V69="aprobada",OR(X69="",X69="—"))),"SÍ","NO") -> NO
A70: cunin | B70: Identidades a flor de piel: lo 'negro' entre apariencias y pertenencias | C70: Elisabeth Cunin | D70: 2003 | E70: D · reparto de colonialidad | G70: reclasificación | H70: DE01 | I70: 11 | J70: colonialidad sin destino derivable | K70: sin_iniciar | U70: pendiente | V70: pendiente | W70: =IF(OR(AND(K70="confirmada",L70<>"",N70<>"",O70<>"",P70<>"",Q70<>"",R70<>"",S70<>"",T70<>"",U70="pasa",V70="aprobada",OR(X70="",X70="—")),AND(K70="revisada_redireccion",Q70<>"",R70<>"",S70<>"",T70<>"",U70="pasa",V70="aprobada",OR(X70="",X70="—"))),"SÍ","NO") -> NO
A71: figueroa | B71: Realismo mágico, vallenato y violencia política en el Caribe colombiano | C71: José Antonio Figueroa | E71: A · candidatura preliminar única | F71: C8 · Creolizaciones, traducciones y opacidades | G71: corrección bibliográfica + migración | H71: S01 | I71: 8 | J71: bloqueo editorial | K71: sin_iniciar | U71: pendiente | V71: pendiente | W71: =IF(OR(AND(K71="confirmada",L71<>"",N71<>"",O71<>"",P71<>"",Q71<>"",R71<>"",S71<>"",T71<>"",U71="pasa",V71="aprobada",OR(X71="",X71="—")),AND(K71="revisada_redireccion",Q71<>"",R71<>"",S71<>"",T71<>"",U71="pasa",V71="aprobada",OR(X71="",X71="—"))),"SÍ","NO") -> NO
A72: tinsley | B72: Ezili's Mirrors: Imagining Black Queer Genders | C72: Omise'eke Natasha Tinsley | D72: 2018 | E72: B · varias candidaturas preliminares | F72: C10 · Cuerpos, parentescos y eróticas | C9 · Memorias, espiritualidades y archivos vivos | G72: reclasificación | H72: B01 | I72: 11 | J72: elección entre candidaturas | K72: sin_iniciar | U72: pendiente | V72: pendiente | W72: =IF(OR(AND(K72="confirmada",L72<>"",N72<>"",O72<>"",P72<>"",Q72<>"",R72<>"",S72<>"",T72<>"",U72="pasa",V72="aprobada",OR(X72="",X72="—")),AND(K72="revisada_redireccion",Q72<>"",R72<>"",S72<>"",T72<>"",U72="pasa",V72="aprobada",OR(X72="",X72="—"))),"SÍ","NO") -> NO
A73: alexander | B73: Pedagogies of Crossing: Feminism, Sexual Politics, Memory, and the Sacred | C73: M. Jacqui Alexander | D73: 2005 | E73: B · varias candidaturas preliminares | F73: C10 · Cuerpos, parentescos y eróticas | C9 · Memorias, espiritualidades y archivos vivos | G73: reclasificación | H73: B01 | I73: 12 | J73: elección entre candidaturas | K73: sin_iniciar | U73: pendiente | V73: pendiente | W73: =IF(OR(AND(K73="confirmada",L73<>"",N73<>"",O73<>"",P73<>"",Q73<>"",R73<>"",S73<>"",T73<>"",U73="pasa",V73="aprobada",OR(X73="",X73="—")),AND(K73="revisada_redireccion",Q73<>"",R73<>"",S73<>"",T73<>"",U73="pasa",V73="aprobada",OR(X73="",X73="—"))),"SÍ","NO") -> NO
A74: curiel | B74: La Nación Heterosexual | C74: Ochy Curiel | D74: 2013 | E74: C · reparto de colonialidad y candidaturas | F74: C10 · Cuerpos, parentescos y eróticas | G74: reclasificación | H74: C01 | I74: 2 | J74: reparto de colonialidad | K74: sin_iniciar | U74: pendiente | V74: pendiente | W74: =IF(OR(AND(K74="confirmada",L74<>"",N74<>"",O74<>"",P74<>"",Q74<>"",R74<>"",S74<>"",T74<>"",U74="pasa",V74="aprobada",OR(X74="",X74="—")),AND(K74="revisada_redireccion",Q74<>"",R74<>"",S74<>"",T74<>"",U74="pasa",V74="aprobada",OR(X74="",X74="—"))),"SÍ","NO") -> NO
A75: shellererotic | B75: Citizenship from Below: Erotic Agency and Caribbean Freedom | C75: Mimi Sheller | D75: 2012 | E75: B · varias candidaturas preliminares | F75: C10 · Cuerpos, parentescos y eróticas | C7 · Soberanías, fronteras y ocupaciones | G75: reclasificación | H75: B01 | I75: 2 | J75: elección entre candidaturas | K75: sin_iniciar | U75: pendiente | V75: pendiente | W75: =IF(OR(AND(K75="confirmada",L75<>"",N75<>"",O75<>"",P75<>"",Q75<>"",R75<>"",S75<>"",T75<>"",U75="pasa",V75="aprobada",OR(X75="",X75="—")),AND(K75="revisada_redireccion",Q75<>"",R75<>"",S75<>"",T75<>"",U75="pasa",V75="aprobada",OR(X75="",X75="—"))),"SÍ","NO") -> NO
A76: ramadan | B76: Constructing Spiritual Blackness: Rastafari in Puerto Rico | C76: Omar Ramadan-Santiago | D76: 2021 | E76: B · varias candidaturas preliminares | F76: C9 · Memorias, espiritualidades y archivos vivos | C8 · Creolizaciones, traducciones y opacidades | G76: reclasificación | H76: B05 | I76: 8 | J76: elección entre candidaturas | K76: sin_iniciar | U76: pendiente | V76: pendiente | W76: =IF(OR(AND(K76="confirmada",L76<>"",N76<>"",O76<>"",P76<>"",Q76<>"",R76<>"",S76<>"",T76<>"",U76="pasa",V76="aprobada",OR(X76="",X76="—")),AND(K76="revisada_redireccion",Q76<>"",R76<>"",S76<>"",T76<>"",U76="pasa",V76="aprobada",OR(X76="",X76="—"))),"SÍ","NO") -> NO
A77: islandfutures | B77: Island Futures: Caribbean Survival in the Anthropocene | C77: Mimi Sheller | D77: 2020 | E77: C · reparto de colonialidad y candidaturas | F77: C6 · Huracanes, ecologías y materialidades vivas | G77: reclasificación | H77: C01 | I77: 13 | J77: reparto de colonialidad | K77: sin_iniciar | U77: pendiente | V77: pendiente | W77: =IF(OR(AND(K77="confirmada",L77<>"",N77<>"",O77<>"",P77<>"",Q77<>"",R77<>"",S77<>"",T77<>"",U77="pasa",V77="aprobada",OR(X77="",X77="—")),AND(K77="revisada_redireccion",Q77<>"",R77<>"",S77<>"",T77<>"",U77="pasa",V77="aprobada",OR(X77="",X77="—"))),"SÍ","NO") -> NO
A78: lara | B78: Queer Freedom: Black Sovereignty | C78: Ana-Maurine Lara | D78: 2020 | E78: B · varias candidaturas preliminares | F78: C10 · Cuerpos, parentescos y eróticas | C7 · Soberanías, fronteras y ocupaciones | G78: reclasificación | H78: B01 | I78: 4 | J78: elección entre candidaturas | K78: sin_iniciar | U78: pendiente | V78: pendiente | W78: =IF(OR(AND(K78="confirmada",L78<>"",N78<>"",O78<>"",P78<>"",Q78<>"",R78<>"",S78<>"",T78<>"",U78="pasa",V78="aprobada",OR(X78="",X78="—")),AND(K78="revisada_redireccion",Q78<>"",R78<>"",S78<>"",T78<>"",U78="pasa",V78="aprobada",OR(X78="",X78="—"))),"SÍ","NO") -> NO
A79: mintzarea | B79: El Caribe como área sociocultural | C79: Sidney W. Mintz | D79: 1966 | E79: C · reparto de colonialidad y candidaturas | F79: C4 · Postplantación, trabajo y desposesión | G79: reclasificación | H79: C01 | I79: 8 | J79: reparto de colonialidad | K79: sin_iniciar | U79: pendiente | V79: pendiente | W79: =IF(OR(AND(K79="confirmada",L79<>"",N79<>"",O79<>"",P79<>"",Q79<>"",R79<>"",S79<>"",T79<>"",U79="pasa",V79="aprobada",OR(X79="",X79="—")),AND(K79="revisada_redireccion",Q79<>"",R79<>"",S79<>"",T79<>"",U79="pasa",V79="aprobada",OR(X79="",X79="—"))),"SÍ","NO") -> NO
A80: gill | B80: Erotic Islands: Art and Activism in the Queer Caribbean | C80: Lyndon K. Gill | D80: 2018 | E80: A · candidatura preliminar única | F80: C10 · Cuerpos, parentescos y eróticas | G80: migración | H80: A01 | I80: 8 | J80: confirmación de candidatura única | K80: sin_iniciar | U80: pendiente | V80: pendiente | W80: =IF(OR(AND(K80="confirmada",L80<>"",N80<>"",O80<>"",P80<>"",Q80<>"",R80<>"",S80<>"",T80<>"",U80="pasa",V80="aprobada",OR(X80="",X80="—")),AND(K80="revisada_redireccion",Q80<>"",R80<>"",S80<>"",T80<>"",U80="pasa",V80="aprobada",OR(X80="",X80="—"))),"SÍ","NO") -> NO
A81: deere | B81: The Invention of Order: On the Coloniality of Space | C81: Don Thomas Deere | D81: 2025 | E81: D · reparto de colonialidad | G81: reclasificación | H81: DE01 | I81: 14 | J81: colonialidad sin destino derivable | K81: sin_iniciar | U81: pendiente | V81: pendiente | W81: =IF(OR(AND(K81="confirmada",L81<>"",N81<>"",O81<>"",P81<>"",Q81<>"",R81<>"",S81<>"",T81<>"",U81="pasa",V81="aprobada",OR(X81="",X81="—")),AND(K81="revisada_redireccion",Q81<>"",R81<>"",S81<>"",T81<>"",U81="pasa",V81="aprobada",OR(X81="",X81="—"))),"SÍ","NO") -> NO
A82: abello | B82: La isla encallada: el Caribe colombiano en el archipiélago | C82: Alberto Abello Vives | D82: 2015 | E82: C · reparto de colonialidad y candidaturas | F82: C7 · Soberanías, fronteras y ocupaciones | G82: reclasificación | H82: C02 | I82: 11 | J82: reparto de colonialidad | K82: sin_iniciar | U82: pendiente | V82: pendiente | W82: =IF(OR(AND(K82="confirmada",L82<>"",N82<>"",O82<>"",P82<>"",Q82<>"",R82<>"",S82<>"",T82<>"",U82="pasa",V82="aprobada",OR(X82="",X82="—")),AND(K82="revisada_redireccion",Q82<>"",R82<>"",S82<>"",T82<>"",U82="pasa",V82="aprobada",OR(X82="",X82="—"))),"SÍ","NO") -> NO
A83: benitez | B83: La isla que se repite / The Repeating Island | C83: Antonio Benítez Rojo | D83: 1989 | E83: B · varias candidaturas preliminares | F83: C8 · Creolizaciones, traducciones y opacidades | C4 · Postplantación, trabajo y desposesión | G83: división + reclasificación | H83: S01 | I83: 4 | J83: bloqueo editorial | K83: sin_iniciar | U83: pendiente | V83: pendiente | W83: =IF(OR(AND(K83="confirmada",L83<>"",N83<>"",O83<>"",P83<>"",Q83<>"",R83<>"",S83<>"",T83<>"",U83="pasa",V83="aprobada",OR(X83="",X83="—")),AND(K83="revisada_redireccion",Q83<>"",R83<>"",S83<>"",T83<>"",U83="pasa",V83="aprobada",OR(X83="",X83="—"))),"SÍ","NO") -> NO
A84: cesaire | B84: Discurso sobre el colonialismo | C84: Aimé Césaire | D84: 1950 | E84: D · reparto de colonialidad | G84: reclasificación | H84: DE01 | I84: 12 | J84: colonialidad sin destino derivable | K84: sin_iniciar | U84: pendiente | V84: pendiente | W84: =IF(OR(AND(K84="confirmada",L84<>"",N84<>"",O84<>"",P84<>"",Q84<>"",R84<>"",S84<>"",T84<>"",U84="pasa",V84="aprobada",OR(X84="",X84="—")),AND(K84="revisada_redireccion",Q84<>"",R84<>"",S84<>"",T84<>"",U84="pasa",V84="aprobada",OR(X84="",X84="—"))),"SÍ","NO") -> NO
A85: fanon | B85: Piel negra, máscaras blancas | C85: Frantz Fanon | D85: 1952 | E85: C · reparto de colonialidad y candidaturas | F85: C10 · Cuerpos, parentescos y eróticas | G85: reclasificación | H85: C01 | I85: 1 | J85: reparto de colonialidad | K85: sin_iniciar | U85: pendiente | V85: pendiente | W85: =IF(OR(AND(K85="confirmada",L85<>"",N85<>"",O85<>"",P85<>"",Q85<>"",R85<>"",S85<>"",T85<>"",U85="pasa",V85="aprobada",OR(X85="",X85="—")),AND(K85="revisada_redireccion",Q85<>"",R85<>"",S85<>"",T85<>"",U85="pasa",V85="aprobada",OR(X85="",X85="—"))),"SÍ","NO") -> NO
A86: james | B86: The Black Jacobins: Toussaint L'Ouverture and the San Domingo Revolution | C86: C.L.R. James | D86: 1938 | E86: C · reparto de colonialidad y candidaturas | F86: C3 · Fugas, cimarronajes y emancipaciones | C7 · Soberanías, fronteras y ocupaciones | G86: reclasificación | H86: C01 | I86: 4 | J86: reparto de colonialidad | K86: sin_iniciar | U86: pendiente | V86: pendiente | W86: =IF(OR(AND(K86="confirmada",L86<>"",N86<>"",O86<>"",P86<>"",Q86<>"",R86<>"",S86<>"",T86<>"",U86="pasa",V86="aprobada",OR(X86="",X86="—")),AND(K86="revisada_redireccion",Q86<>"",R86<>"",S86<>"",T86<>"",U86="pasa",V86="aprobada",OR(X86="",X86="—"))),"SÍ","NO") -> NO
A87: trouillotsilencing | B87: Silenciando el pasado: el poder y la producción de la Historia | C87: Michel-Rolph Trouillot | D87: 1995 | E87: C · reparto de colonialidad y candidaturas | F87: C9 · Memorias, espiritualidades y archivos vivos | G87: reclasificación | H87: C04 | I87: 11 | J87: reparto de colonialidad | K87: sin_iniciar | U87: pendiente | V87: pendiente | W87: =IF(OR(AND(K87="confirmada",L87<>"",N87<>"",O87<>"",P87<>"",Q87<>"",R87<>"",S87<>"",T87<>"",U87="pasa",V87="aprobada",OR(X87="",X87="—")),AND(K87="revisada_redireccion",Q87<>"",R87<>"",S87<>"",T87<>"",U87="pasa",V87="aprobada",OR(X87="",X87="—"))),"SÍ","NO") -> NO
A88: brownreaper | B88: The Reaper's Garden: Death and Power in the World of Atlantic Slavery | C88: Vincent Brown | D88: 2008 | E88: A · candidatura preliminar única | F88: C6 · Huracanes, ecologías y materialidades vivas | G88: migración | H88: A02 | I88: 9 | J88: confirmación de candidatura única | K88: sin_iniciar | U88: pendiente | V88: pendiente | W88: =IF(OR(AND(K88="confirmada",L88<>"",N88<>"",O88<>"",P88<>"",Q88<>"",R88<>"",S88<>"",T88<>"",U88="pasa",V88="aprobada",OR(X88="",X88="—")),AND(K88="revisada_redireccion",Q88<>"",R88<>"",S88<>"",T88<>"",U88="pasa",V88="aprobada",OR(X88="",X88="—"))),"SÍ","NO") -> NO
A89: kempadoo | B89: Sexing the Caribbean: Gender, Race and Sexual Labor | C89: Kamala Kempadoo | D89: 2004 | E89: A · candidatura preliminar única | F89: C10 · Cuerpos, parentescos y eróticas | G89: migración | H89: A01 | I89: 4 | J89: confirmación de candidatura única | K89: sin_iniciar | U89: pendiente | V89: pendiente | W89: =IF(OR(AND(K89="confirmada",L89<>"",N89<>"",O89<>"",P89<>"",Q89<>"",R89<>"",S89<>"",T89<>"",U89="pasa",V89="aprobada",OR(X89="",X89="—")),AND(K89="revisada_redireccion",Q89<>"",R89<>"",S89<>"",T89<>"",U89="pasa",V89="aprobada",OR(X89="",X89="—"))),"SÍ","NO") -> NO
A90: kingisland | B90: Island Bodies: Transgressive Sexualities in the Caribbean Imagination | C90: Rosamond S. King | D90: 2014 | E90: B · varias candidaturas preliminares | F90: C10 · Cuerpos, parentescos y eróticas | C8 · Creolizaciones, traducciones y opacidades | G90: reclasificación | H90: B01 | I90: 8 | J90: elección entre candidaturas | K90: sin_iniciar | U90: pendiente | V90: pendiente | W90: =IF(OR(AND(K90="confirmada",L90<>"",N90<>"",O90<>"",P90<>"",Q90<>"",R90<>"",S90<>"",T90<>"",U90="pasa",V90="aprobada",OR(X90="",X90="—")),AND(K90="revisada_redireccion",Q90<>"",R90<>"",S90<>"",T90<>"",U90="pasa",V90="aprobada",OR(X90="",X90="—"))),"SÍ","NO") -> NO
A91: fuentesdispossessed | B91: Dispossessed Lives: Enslaved Women, Violence, and the Archive | C91: Marisa J. Fuentes | D91: 2016 | E91: A · candidatura preliminar única | F91: C10 · Cuerpos, parentescos y eróticas | G91: migración | H91: A01 | I91: 10 | J91: confirmación de candidatura única | K91: sin_iniciar | U91: pendiente | V91: pendiente | W91: =IF(OR(AND(K91="confirmada",L91<>"",N91<>"",O91<>"",P91<>"",Q91<>"",R91<>"",S91<>"",T91<>"",U91="pasa",V91="aprobada",OR(X91="",X91="—")),AND(K91="revisada_redireccion",Q91<>"",R91<>"",S91<>"",T91<>"",U91="pasa",V91="aprobada",OR(X91="",X91="—"))),"SÍ","NO") -> NO
A92: bollandbelize | B92: The Formation of a Colonial Society: Belize, From Conquest to Crown Colony | C92: O. Nigel Bolland | D92: 1977 | E92: C · reparto de colonialidad y candidaturas | F92: C4 · Postplantación, trabajo y desposesión | G92: reclasificación | H92: C01 | I92: 6 | J92: reparto de colonialidad | K92: sin_iniciar | U92: pendiente | V92: pendiente | W92: =IF(OR(AND(K92="confirmada",L92<>"",N92<>"",O92<>"",P92<>"",Q92<>"",R92<>"",S92<>"",T92<>"",U92="pasa",V92="aprobada",OR(X92="",X92="—")),AND(K92="revisada_redireccion",Q92<>"",R92<>"",S92<>"",T92<>"",U92="pasa",V92="aprobada",OR(X92="",X92="—"))),"SÍ","NO") -> NO
A93: hintzen | B93: The Costs of Regime Survival: Racial Mobilization, Elite Domination and Control of the State in Guyana and Trinidad | C93: Percy C. Hintzen | D93: 1989 | E93: A · candidatura preliminar única | F93: C7 · Soberanías, fronteras y ocupaciones | G93: migración | H93: A02 | I93: 16 | J93: confirmación de candidatura única | K93: sin_iniciar | U93: pendiente | V93: pendiente | W93: =IF(OR(AND(K93="confirmada",L93<>"",N93<>"",O93<>"",P93<>"",Q93<>"",R93<>"",S93<>"",T93<>"",U93="pasa",V93="aprobada",OR(X93="",X93="—")),AND(K93="revisada_redireccion",Q93<>"",R93<>"",S93<>"",T93<>"",U93="pasa",V93="aprobada",OR(X93="",X93="—"))),"SÍ","NO") -> NO
A94: rainforestwarriors | B94: Rainforest Warriors: Human Rights on Trial | C94: Richard Price | D94: 2011 | E94: B · varias candidaturas preliminares | F94: C3 · Fugas, cimarronajes y emancipaciones | C7 · Soberanías, fronteras y ocupaciones | G94: reclasificación | H94: B02 | I94: 1 | J94: elección entre candidaturas | K94: sin_iniciar | U94: pendiente | V94: pendiente | W94: =IF(OR(AND(K94="confirmada",L94<>"",N94<>"",O94<>"",P94<>"",Q94<>"",R94<>"",S94<>"",T94<>"",U94="pasa",V94="aprobada",OR(X94="",X94="—")),AND(K94="revisada_redireccion",Q94<>"",R94<>"",S94<>"",T94<>"",U94="pasa",V94="aprobada",OR(X94="",X94="—"))),"SÍ","NO") -> NO
A95: quinnblackpower | B95: Black Power in the Caribbean | C95: Kate Quinn (ed.) | D95: 2014 | E95: B · varias candidaturas preliminares | F95: C7 · Soberanías, fronteras y ocupaciones | C9 · Memorias, espiritualidades y archivos vivos | G95: reclasificación | H95: B03 | I95: 9 | J95: elección entre candidaturas | K95: sin_iniciar | U95: pendiente | V95: pendiente | W95: =IF(OR(AND(K95="confirmada",L95<>"",N95<>"",O95<>"",P95<>"",Q95<>"",R95<>"",S95<>"",T95<>"",U95="pasa",V95="aprobada",OR(X95="",X95="—")),AND(K95="revisada_redireccion",Q95<>"",R95<>"",S95<>"",T95<>"",U95="pasa",V95="aprobada",OR(X95="",X95="—"))),"SÍ","NO") -> NO
A96: russwurm | B96: The Struggles of John Brown Russwurm: The Life and Writings of a Pan-Africanist Pioneer, 1799-1851 | C96: Winston James | D96: 2010 | E96: B · varias candidaturas preliminares | F96: C9 · Memorias, espiritualidades y archivos vivos | C7 · Soberanías, fronteras y ocupaciones | G96: reclasificación | H96: B05 | I96: 6 | J96: elección entre candidaturas | K96: sin_iniciar | U96: pendiente | V96: pendiente | W96: =IF(OR(AND(K96="confirmada",L96<>"",N96<>"",O96<>"",P96<>"",Q96<>"",R96<>"",S96<>"",T96<>"",U96="pasa",V96="aprobada",OR(X96="",X96="—")),AND(K96="revisada_redireccion",Q96<>"",R96<>"",S96<>"",T96<>"",U96="pasa",V96="aprobada",OR(X96="",X96="—"))),"SÍ","NO") -> NO
... A98: helgnuncamas | B98: ¡Nunca más esclavos! Una historia comparada de los esclavos que se liberaron en las Américas | C98: Aline Helg | D98: 2016 / trad. esp. 2018 | E98: A · candidatura preliminar única | F98: C3 · Fugas, cimarronajes y emancipaciones | G98: migración | H98: A01 | I98: 12 | J98: confirmación de candidatura única | K98: sin_iniciar | U98: pendiente | V98: pendiente | W98: =IF(OR(AND(K98="confirmada",L98<>"",N98<>"",O98<>"",P98<>"",Q98<>"",R98<>"",S98<>"",T98<>"",U98="pasa",V98="aprobada",OR(X98="",X98="—")),AND(K98="revisada_redireccion",Q98<>"",R98<>"",S98<>"",T98<>"",U98="pasa",V98="aprobada",OR(X98="",X98="—"))),"SÍ","NO") -> NO
A99: robinsonmarxismo | B99: Marxismo negro: la formación de la tradición radical negra | C99: Cedric J. Robinson | D99: 1983 | E99: D · reparto de colonialidad | G99: reclasificación | H99: DE01 | I99: 3 | J99: colonialidad sin destino derivable | K99: sin_iniciar | U99: pendiente | V99: pendiente | W99: =IF(OR(AND(K99="confirmada",L99<>"",N99<>"",O99<>"",P99<>"",Q99<>"",R99<>"",S99<>"",T99<>"",U99="pasa",V99="aprobada",OR(X99="",X99="—")),AND(K99="revisada_redireccion",Q99<>"",R99<>"",S99<>"",T99<>"",U99="pasa",V99="aprobada",OR(X99="",X99="—"))),"SÍ","NO") -> NO
A100: bassiacuoso | B100: Un territorio acuoso: geografías marineras y el Gran Caribe transimperial de la Nueva Granada | C100: Ernesto Bassi | D100: 2016 / trad. esp. 2021 | E100: C · reparto de colonialidad y candidaturas | F100: C7 · Soberanías, fronteras y ocupaciones | G100: reclasificación | H100: P00 | I100: 7 | J100: piloto aprobado | K100: confirmada | L100: rutas_diasporas_territorios_acuosos | M100: soberanias_fronteras_ocupaciones | N100: reconstruir un archivo; cartografiar; seguir una ruta; comparar orillas; teorizar | O100: {"publicacion":{"valor":2016,"era":"EC","precision":"exacta"},"traduccion_es":{"valor":2021,"era":"EC","precision":"exacta"},"periodo_estudiado":{"inicio":{"valor":1760,"era":"EC","precision":"exacta"},"fin":{"valor":1860,"era":"EC","precision":"exacta"}}} | P100: orillas: Gran Caribe [territorio estudiado] | Q100: https://www.dukeupress.edu/an-aqueous-territory https://editorial.uninorte.edu.co/gpd-un-territorio-acuoso-9789587891669.html | R100: La obra organiza su argumento alrededor de circulaciones marítimas, geografías vividas y un Gran Caribe transimperial. | S100: Dirección académica de Pensamiento Caribe | T100: 46242 | U100: pasa | V100: aprobada | W100: =IF(OR(AND(K100="confirmada",L100<>"",N100<>"",O100<>"",P100<>"",Q100<>"",R100<>"",S100<>"",T100<>"",U100="pasa",V100="aprobada",OR(X100="",X100="—")),AND(K100="revisada_redireccion",Q100<>"",R100<>"",S100<>"",T100<>"",U100="pasa",V100="aprobada",OR(X100="",X100="—"))),"SÍ","NO") -> NO | X100: rutas_con_paginas
A101: rediker | B101: Barco de esclavos: una historia humana | C101: Marcus Rediker | D101: 2007 | E101: A · candidatura preliminar única | F101: C9 · Memorias, espiritualidades y archivos vivos | G101: migración | H101: A03 | I101: 17 | J101: confirmación de candidatura única | K101: sin_iniciar | U101: pendiente | V101: pendiente | W101: =IF(OR(AND(K101="confirmada",L101<>"",N101<>"",O101<>"",P101<>"",Q101<>"",R101<>"",S101<>"",T101<>"",U101="pasa",V101="aprobada",OR(X101="",X101="—")),AND(K101="revisada_redireccion",Q101<>"",R101<>"",S101<>"",T101<>"",U101="pasa",V101="aprobada",OR(X101="",X101="—"))),"SÍ","NO") -> NO
A102: gosinenature | B102: Nature's Wild: Love, Sex, and Law in the Caribbean | C102: Andil Gosine | D102: 2021 | E102: C · reparto de colonialidad y candidaturas | F102: C10 · Cuerpos, parentescos y eróticas | G102: reclasificación | H102: C01 | I102: 3 | J102: reparto de colonialidad | K102: sin_iniciar | U102: pendiente | V102: pendiente | W102: =IF(OR(AND(K102="confirmada",L102<>"",N102<>"",O102<>"",P102<>"",Q102<>"",R102<>"",S102<>"",T102<>"",U102="pasa",V102="aprobada",OR(X102="",X102="—")),AND(K102="revisada_redireccion",Q102<>"",R102<>"",S102<>"",T102<>"",U102="pasa",V102="aprobada",OR(X102="",X102="—"))),"SÍ","NO") -> NO
A103: headleyreparaciones | B103: A Philosophical Investigation into the Possibility/Impossibility of Reparations for Caribbean Slavery: Assessing the Legal Challenges | C103: Clevis Headley | D103: 2026 | E103: A · candidatura preliminar única | F103: C9 · Memorias, espiritualidades y archivos vivos | G103: migración | H103: A03 | I103: 10 | J103: confirmación de candidatura única | K103: sin_iniciar | U103: pendiente | V103: pendiente | W103: =IF(OR(AND(K103="confirmada",L103<>"",N103<>"",O103<>"",P103<>"",Q103<>"",R103<>"",S103<>"",T103<>"",U103="pasa",V103="aprobada",OR(X103="",X103="—")),AND(K103="revisada_redireccion",Q103<>"",R103<>"",S103<>"",T103<>"",U103="pasa",V103="aprobada",OR(X103="",X103="—"))),"SÍ","NO") -> NO
A104: jaffeconcrete | B104: Concrete Jungles: Urban Pollution and the Politics of Difference in the Caribbean | C104: Rivke Jaffe | D104: 2016 | E104: E · sin correspondencia directa en la taxonomía anterior | G104: reclasificación | H104: DE01 | I104: 8 | J104: sin correspondencia directa | K104: sin_iniciar | U104: pendiente | V104: pendiente | W104: =IF(OR(AND(K104="confirmada",L104<>"",N104<>"",O104<>"",P104<>"",Q104<>"",R104<>"",S104<>"",T104<>"",U104="pasa",V104="aprobada",OR(X104="",X104="—")),AND(K104="revisada_redireccion",Q104<>"",R104<>"",S104<>"",T104<>"",U104="pasa",V104="aprobada",OR(X104="",X104="—"))),"SÍ","NO") -> NO
A105: pardomosquerahoffmann | B105: Afrodescendientes en las Américas: trayectorias sociales e identitarias. 150 años de la abolición de la esclavitud en Colombia | C105: Mauricio Pardo, Claudia Mosquera y Odile Hoffmann (eds.) | D105: 2002 | E105: A · candidatura preliminar única | F105: C9 · Memorias, espiritualidades y archivos vivos | G105: migración | H105: A03 | I105: 14 | J105: confirmación de candidatura única | K105: sin_iniciar | U105: pendiente | V105: pendiente | W105: =IF(OR(AND(K105="confirmada",L105<>"",N105<>"",O105<>"",P105<>"",Q105<>"",R105<>"",S105<>"",T105<>"",U105="pasa",V105="aprobada",OR(X105="",X105="—")),AND(K105="revisada_redireccion",Q105<>"",R105<>"",S105<>"",T105<>"",U105="pasa",V105="aprobada",OR(X105="",X105="—"))),"SÍ","NO") -> NO
A106: scher | B106: Carnival and the Formation of a Caribbean Transnation | C106: Philip W. Scher | D106: 2003 | E106: B · varias candidaturas preliminares | F106: C8 · Creolizaciones, traducciones y opacidades | C9 · Memorias, espiritualidades y archivos vivos | G106: reclasificación | H106: B04 | I106: 8 | J106: elección entre candidaturas | K106: sin_iniciar | U106: pendiente | V106: pendiente | W106: =IF(OR(AND(K106="confirmada",L106<>"",N106<>"",O106<>"",P106<>"",Q106<>"",R106<>"",S106<>"",T106<>"",U106="pasa",V106="aprobada",OR(X106="",X106="—")),AND(K106="revisada_redireccion",Q106<>"",R106<>"",S106<>"",T106<>"",U106="pasa",V106="aprobada",OR(X106="",X106="—"))),"SÍ","NO") -> NO
A107: hallafricanslouisiana | B107: Africans in Colonial Louisiana: The Development of Afro-Creole Culture in the Eighteenth Century | C107: Gwendolyn Midlo Hall | D107: 1992 | E107: B · varias candidaturas preliminares | F107: C8 · Creolizaciones, traducciones y opacidades | C4 · Postplantación, trabajo y desposesión | G107: reclasificación | H107: B04 | I107: 2 | J107: elección entre candidaturas | K107: sin_iniciar | U107: pendiente | V107: pendiente | W107: =IF(OR(AND(K107="confirmada",L107<>"",N107<>"",O107<>"",P107<>"",Q107<>"",R107<>"",S107<>"",T107<>"",U107="pasa",V107="aprobada",OR(X107="",X107="—")),AND(K107="revisada_redireccion",Q107<>"",R107<>"",S107<>"",T107<>"",U107="pasa",V107="aprobada",OR(X107="",X107="—"))),"SÍ","NO") -> NO
A108: creolenieworleans | B108: Creole New Orleans: Race and Americanization | C108: Arnold R. Hirsch y Joseph Logsdon (eds.) | D108: 1992 | E108: B · varias candidaturas preliminares | F108: C8 · Creolizaciones, traducciones y opacidades | C9 · Memorias, espiritualidades y archivos vivos | G108: reclasificación | H108: B04 | I108: 9 | J108: elección entre candidaturas | K108: sin_iniciar | U108: pendiente | V108: pendiente | W108: =IF(OR(AND(K108="confirmada",L108<>"",N108<>"",O108<>"",P108<>"",Q108<>"",R108<>"",S108<>"",T108<>"",U108="pasa",V108="aprobada",OR(X108="",X108="—")),AND(K108="revisada_redireccion",Q108<>"",R108<>"",S108<>"",T108<>"",U108="pasa",V108="aprobada",OR(X108="",X108="—"))),"SÍ","NO") -> NO
...

Sheet Plan relaciones
A1: Atlas 2.0 · plan de las 588 relaciones | B1: Atlas 2.0 · plan de las 588 relaciones | C1: Atlas 2.0 · plan de las 588 relaciones | D1: Atlas 2.0 · plan de las 588 relaciones | E1: Atlas 2.0 · plan de las 588 relaciones | F1: Atlas 2.0 · plan de las 588 relaciones | G1: Atlas 2.0 · plan de las 588 relaciones | H1: Atlas 2.0 · plan de las 588 relaciones | I1: Atlas 2.0 · plan de las 588 relaciones | J1: Atlas 2.0 · plan de las 588 relaciones | K1: Atlas 2.0 · plan de las 588 relaciones | L1: Atlas 2.0 · plan de las 588 relaciones | M1: Atlas 2.0 · plan de las 588 relaciones | N1: Atlas 2.0 · plan de las 588 relaciones | O1: Atlas 2.0 · plan de las 588 relaciones | P1: Atlas 2.0 · plan de las 588 relaciones | Q1: Atlas 2.0 · plan de las 588 relaciones | R1: Atlas 2.0 · plan de las 588 relaciones | S1: Atlas 2.0 · plan de las 588 relaciones | T1: Atlas 2.0 · plan de las 588 relaciones | U1: Atlas 2.0 · plan de las 588 relaciones
A2: Cada relación recibe un estado explícito y se revisa en el lote en que ambos extremos ya están disponibles. Fricción y cruce lingüístico son campos distintos. | B2: Cada relación recibe un estado explícito y se revisa en el lote en que ambos extremos ya están disponibles. Fricción y cruce lingüístico son campos distintos. | C2: Cada relación recibe un estado explícito y se revisa en el lote en que ambos extremos ya están disponibles. Fricción y cruce lingüístico son campos distintos. | D2: Cada relación recibe un estado explícito y se revisa en el lote en que ambos extremos ya están disponibles. Fricción y cruce lingüístico son campos distintos. | E2: Cada relación recibe un estado explícito y se revisa en el lote en que ambos extremos ya están disponibles. Fricción y cruce lingüístico son campos distintos. | F2: Cada relación recibe un estado explícito y se revisa en el lote en que ambos extremos ya están disponibles. Fricción y cruce lingüístico son campos distintos. | G2: Cada relación recibe un estado explícito y se revisa en el lote en que ambos extremos ya están disponibles. Fricción y cruce lingüístico son campos distintos. | H2: Cada relación recibe un estado explícito y se revisa en el lote en que ambos extremos ya están disponibles. Fricción y cruce lingüístico son campos distintos. | I2: Cada relación recibe un estado explícito y se revisa en el lote en que ambos extremos ya están disponibles. Fricción y cruce lingüístico son campos distintos. | J2: Cada relación recibe un estado explícito y se revisa en el lote en que ambos extremos ya están disponibles. Fricción y cruce lingüístico son campos distintos. | K2: Cada relación recibe un estado explícito y se revisa en el lote en que ambos extremos ya están disponibles. Fricción y cruce lingüístico son campos distintos. | L2: Cada relación recibe un estado explícito y se revisa en el lote en que ambos extremos ya están disponibles. Fricción y cruce lingüístico son campos distintos. | M2: Cada relación recibe un estado explícito y se revisa en el lote en que ambos extremos ya están disponibles. Fricción y cruce lingüístico son campos distintos. | N2: Cada relación recibe un estado explícito y se revisa en el lote en que ambos extremos ya están disponibles. Fricción y cruce lingüístico son campos distintos. | O2: Cada relación recibe un estado explícito y se revisa en el lote en que ambos extremos ya están disponibles. Fricción y cruce lingüístico son campos distintos. | P2: Cada relación recibe un estado explícito y se revisa en el lote en que ambos extremos ya están disponibles. Fricción y cruce lingüístico son campos distintos. | Q2: Cada relación recibe un estado explícito y se revisa en el lote en que ambos extremos ya están disponibles. Fricción y cruce lingüístico son campos distintos. | R2: Cada relación recibe un estado explícito y se revisa en el lote en que ambos extremos ya están disponibles. Fricción y cruce lingüístico son campos distintos. | S2: Cada relación recibe un estado explícito y se revisa en el lote en que ambos extremos ya están disponibles. Fricción y cruce lingüístico son campos distintos. | T2: Cada relación recibe un estado explícito y se revisa en el lote en que ambos extremos ya están disponibles. Fricción y cruce lingüístico son campos distintos. | U2: Cada relación recibe un estado explícito y se revisa en el lote en que ambos extremos ya están disponibles. Fricción y cruce lingüístico son campos distintos.
A4: Relación | B4: a heredado | C4: b heredado | D4: a migrado | E4: b migrado | F4: Tipo heredado | G4: Fuente heredada | H4: Estado fuente 1.15 | I4: Decisión piloto | J4: Estado inicial 2.0 | K4: Lote a | L4: Lote b | M4: Alcance | N4: Lote de revisión | O4: Fricción | P4: Cruce lingüístico | Q4: Fuente / páginas 2.0 | R4: Estado revisión | S4: QA técnico | T4: Aprobación | U4: Lista para generar
A5: R0001 | B5: mintz | C5: trouillot | D5: mintz | E5: trouillot | F5: resonancia | G5: Por corroborar. | H5: por_corroborar | J5: por_corroborar | K5: P00 | L5: C04 | M5: frontera | N5: C04 | O5: pendiente | P5: pendiente | R5: sin_iniciar | S5: pendiente | T5: pendiente | U5: =IF(AND(R5="revisada",S5="pasa",T5="aprobada",O5<>"pendiente",P5<>"pendiente",OR(J5="por_corroborar",AND(J5="corroborada",Q5<>""))),"SÍ","NO") -> NO
A6: R0002 | B6: trouillot | C6: casimir | D6: trouillot | E6: casimir | F6: resonancia | G6: Comparten el fenómeno Colonialidad. Por corroborar el vínculo directo. | H6: por_corroborar | J6: por_corroborar | K6: C04 | L6: C01 | M6: frontera | N6: C04 | O6: pendiente | P6: pendiente | R6: sin_iniciar | S6: pendiente | T6: pendiente | U6: =IF(AND(R6="revisada",S6="pasa",T6="aprobada",O6<>"pendiente",P6<>"pendiente",OR(J6="por_corroborar",AND(J6="corroborada",Q6<>""))),"SÍ","NO") -> NO
A7: R0003 | B7: mintz | C7: ortiz | D7: mintz | E7: ortiz | F7: disonancia | G7: Economía política anglófona (Mintz) frente a transculturación cultural hispana (Ortiz): tensión de énfasis. | H7: corroborada | J7: corroborada | K7: P00 | L7: S01 | M7: frontera | N7: S01 | O7: pendiente | P7: pendiente | R7: sin_iniciar | S7: pendiente | T7: pendiente | U7: =IF(AND(R7="revisada",S7="pasa",T7="aprobada",O7<>"pendiente",P7<>"pendiente",OR(J7="por_corroborar",AND(J7="corroborada",Q7<>""))),"SÍ","NO") -> NO
A8: R0004 | B8: ortiz | C8: glissant | D8: ortiz | E8: glissant | F8: resonancia | G8: Comparten el fenómeno Creolización / oralitura. Por corroborar el vínculo directo. | H8: por_corroborar | J8: por_corroborar | K8: S01 | L8: S01 | M8: interna | N8: S01 | O8: pendiente | P8: pendiente | R8: sin_iniciar | S8: pendiente | T8: pendiente | U8: =IF(AND(R8="revisada",S8="pasa",T8="aprobada",O8<>"pendiente",P8<>"pendiente",OR(J8="por_corroborar",AND(J8="corroborada",Q8<>""))),"SÍ","NO") -> NO
A9: R0005 | B9: glissant | C9: brathwaite | D9: glissant | E9: brathwaite | F9: resonancia | G9: Comparten el fenómeno Creolización / oralitura. Por corroborar el vínculo directo. | H9: por_corroborar | J9: por_corroborar | K9: S01 | L9: S01 | M9: interna | N9: S01 | O9: pendiente | P9: pendiente | R9: sin_iniciar | S9: pendiente | T9: pendiente | U9: =IF(AND(R9="revisada",S9="pasa",T9="aprobada",O9<>"pendiente",P9<>"pendiente",OR(J9="por_corroborar",AND(J9="corroborada",Q9<>""))),"SÍ","NO") -> NO
A10: R0006 | B10: glissant | C10: creolite | D10: glissant | E10: creolite | F10: disonancia | G10: La créolité de Bernabé, Chamoiseau y Confiant se distancia de la poética de la Relación de Glissant. | H10: corroborada | J10: corroborada | K10: S01 | L10: A03 | M10: frontera | N10: A03 | O10: pendiente | P10: pendiente | R10: sin_iniciar | S10: pendiente | T10: pendiente | U10: =IF(AND(R10="revisada",S10="pasa",T10="aprobada",O10<>"pendiente",P10<>"pendiente",OR(J10="por_corroborar",AND(J10="corroborada",Q10<>""))),"SÍ","NO") -> NO
A11: R0007 | B11: price | C11: fouchard | D11: price | E11: fouchard | F11: resonancia | G11: Comparten el fenómeno Cimarronaje / fuga. Por corroborar el vínculo directo. | H11: por_corroborar | J11: por_corroborar | K11: P00 | L11: B01 | M11: frontera | N11: B01 | O11: pendiente | P11: pendiente | R11: sin_iniciar | S11: pendiente | T11: pendiente | U11: =IF(AND(R11="revisada",S11="pasa",T11="aprobada",O11<>"pendiente",P11<>"pendiente",OR(J11="por_corroborar",AND(J11="corroborada",Q11<>""))),"SÍ","NO") -> NO
A12: R0008 | B12: price | C12: totumo | D12: price | E12: totumo | F12: disonancia | G12: Comparatismo académico del cimarronaje (Price) frente a la memoria local palenquera del Totumo. | H12: corroborada | I12: degradar_a_por_corroborar | J12: por_corroborar | K12: P00 | L12: P00 | M12: interna | N12: P00 | O12: no | P12: sí | R12: revisada | S12: pasa | T12: aprobada | U12: =IF(AND(R12="revisada",S12="pasa",T12="aprobada",O12<>"pendiente",P12<>"pendiente",OR(J12="por_corroborar",AND(J12="corroborada",Q12<>""))),"SÍ","NO") -> SÍ
A13: R0009 | B13: fouchard | C13: casimir | D13: fouchard | E13: casimir | F13: resonancia | G13: Por corroborar. | H13: por_corroborar | J13: por_corroborar | K13: B01 | L13: C01 | M13: frontera | N13: C01 | O13: pendiente | P13: pendiente | R13: sin_iniciar | S13: pendiente | T13: pendiente | U13: =IF(AND(R13="revisada",S13="pasa",T13="aprobada",O13<>"pendiente",P13<>"pendiente",OR(J13="por_corroborar",AND(J13="corroborada",Q13<>""))),"SÍ","NO") -> NO
A14: R0010 | B14: fouchard | C14: roberts | D14: fouchard | E14: roberts | F14: resonancia | G14: Comparten el fenómeno Cimarronaje / fuga. Por corroborar el vínculo directo. | H14: por_corroborar | J14: por_corroborar | K14: B01 | L14: B01 | M14: interna | N14: B01 | O14: pendiente | P14: pendiente | R14: sin_iniciar | S14: pendiente | T14: pendiente | U14: =IF(AND(R14="revisada",S14="pasa",T14="aprobada",O14<>"pendiente",P14<>"pendiente",OR(J14="por_corroborar",AND(J14="corroborada",Q14<>""))),"SÍ","NO") -> NO
A15: R0011 | B15: roberts | C15: quintero | D15: roberts | E15: quintero | F15: resonancia | G15: Comparten el fenómeno Cimarronaje / fuga. Por corroborar el vínculo directo. | H15: por_corroborar | J15: por_corroborar | K15: B01 | L15: B03 | M15: frontera | N15: B03 | O15: pendiente | P15: pendiente | R15: sin_iniciar | S15: pendiente | T15: pendiente | U15: =IF(AND(R15="revisada",S15="pasa",T15="aprobada",O15<>"pendiente",P15<>"pendiente",OR(J15="por_corroborar",AND(J15="corroborada",Q15<>""))),"SÍ","NO") -> NO
A16: R0012 | B16: cabrera | C16: tambu | D16: cabrera | E16: tambu | F16: resonancia | G16: Comparten el fenómeno Memoria y espiritualidad. Por corroborar el vínculo directo. | H16: por_corroborar | J16: por_corroborar | K16: B05 | L16: B05 | M16: interna | N16: B05 | O16: pendiente | P16: pendiente | R16: sin_iniciar | S16: pendiente | T16: pendiente | U16: =IF(AND(R16="revisada",S16="pasa",T16="aprobada",O16<>"pendiente",P16<>"pendiente",OR(J16="por_corroborar",AND(J16="corroborada",Q16<>""))),"SÍ","NO") -> NO
A17: R0013 | B17: bonilla | C17: aftershocks | D17: bonilla | E17: aftershocks | F17: resonancia | G17: Comparten el fenómeno Soberanías. Por corroborar el vínculo directo. | H17: por_corroborar | J17: por_corroborar | K17: C02 | L17: B03 | M17: frontera | N17: C02 | O17: pendiente | P17: pendiente | R17: sin_iniciar | S17: pendiente | T17: pendiente | U17: =IF(AND(R17="revisada",S17="pasa",T17="aprobada",O17<>"pendiente",P17<>"pendiente",OR(J17="por_corroborar",AND(J17="corroborada",Q17<>""))),"SÍ","NO") -> NO
A18: R0014 | B18: bonilla | C18: ferdinand | D18: bonilla | E18: ferdinand | F18: resonancia | G18: Comparten el fenómeno Colonialidad. Por corroborar el vínculo directo. | H18: por_corroborar | J18: por_corroborar | K18: C02 | L18: C01 | M18: frontera | N18: C02 | O18: pendiente | P18: pendiente | R18: sin_iniciar | S18: pendiente | T18: pendiente | U18: =IF(AND(R18="revisada",S18="pasa",T18="aprobada",O18<>"pendiente",P18<>"pendiente",OR(J18="por_corroborar",AND(J18="corroborada",Q18<>""))),"SÍ","NO") -> NO
A19: R0015 | B19: ferdinand | C19: beyondsun | D19: ferdinand | E19: beyondsun | F19: resonancia | G19: Comparten el fenómeno Catástrofes climáticas. Por corroborar el vínculo directo. | H19: por_corroborar | J19: por_corroborar | K19: C01 | L19: A02 | M19: frontera | N19: C01 | O19: pendiente | P19: pendiente | R19: sin_iniciar | S19: pendiente | T19: pendiente | U19: =IF(AND(R19="revisada",S19="pasa",T19="aprobada",O19<>"pendiente",P19<>"pendiente",OR(J19="por_corroborar",AND(J19="corroborada",Q19<>""))),"SÍ","NO") -> NO
A20: R0016 | B20: rodney | C20: gudynas | D20: rodney | E20: gudynas | F20: resonancia | G20: Comparten el fenómeno Capitalismo racial. Por corroborar el vínculo directo. | H20: por_corroborar | J20: por_corroborar | K20: DE01 | L20: A02 | M20: frontera | N20: DE01 | O20: pendiente | P20: pendiente | R20: sin_iniciar | S20: pendiente | T20: pendiente | U20: =IF(AND(R20="revisada",S20="pasa",T20="aprobada",O20<>"pendiente",P20<>"pendiente",OR(J20="por_corroborar",AND(J20="corroborada",Q20<>""))),"SÍ","NO") -> NO
A21: R0017 | B21: rodney | C21: casimir | D21: rodney | E21: casimir | F21: resonancia | G21: Comparten el fenómeno Colonialidad. Por corroborar el vínculo directo. | H21: por_corroborar | J21: por_corroborar | K21: DE01 | L21: C01 | M21: frontera | N21: DE01 | O21: pendiente | P21: pendiente | R21: sin_iniciar | S21: pendiente | T21: pendiente | U21: =IF(AND(R21="revisada",S21="pasa",T21="aprobada",O21<>"pendiente",P21<>"pendiente",OR(J21="por_corroborar",AND(J21="corroborada",Q21<>""))),"SÍ","NO") -> NO
A22: R0018 | B22: lindskoog | C22: bonilla | D22: lindskoog | E22: bonilla | F22: resonancia | G22: Comparten el fenómeno Soberanías. Por corroborar el vínculo directo. | H22: por_corroborar | J22: por_corroborar | K22: A03 | L22: C02 | M22: frontera | N22: C02 | O22: pendiente | P22: pendiente | R22: sin_iniciar | S22: pendiente | T22: pendiente | U22: =IF(AND(R22="revisada",S22="pasa",T22="aprobada",O22<>"pendiente",P22<>"pendiente",OR(J22="por_corroborar",AND(J22="corroborada",Q22<>""))),"SÍ","NO") -> NO
A23: R0019 | B23: chande | C23: vete | D23: chande | E23: vete | F23: resonancia | G23: Comparten el fenómeno Creolización / oralitura. Por corroborar el vínculo directo. | H23: por_corroborar | J23: por_corroborar | K23: P00 | L23: B04 | M23: frontera | N23: B04 | O23: pendiente | P23: pendiente | R23: sin_iniciar | S23: pendiente | T23: pendiente | U23: =IF(AND(R23="revisada",S23="pasa",T23="aprobada",O23<>"pendiente",P23<>"pendiente",OR(J23="por_corroborar",AND(J23="corroborada",Q23<>""))),"SÍ","NO") -> NO
A24: R0020 | B24: esquiva | C24: rodney | D24: esquiva | E24: rodney | F24: resonancia | G24: Comparten el fenómeno Capitalismo racial. Por corroborar el vínculo directo. | H24: por_corroborar | J24: por_corroborar | K24: S01 | L24: DE01 | M24: frontera | N24: DE01 | O24: pendiente | P24: pendiente | R24: sin_iniciar | S24: pendiente | T24: pendiente | U24: =IF(AND(R24="revisada",S24="pasa",T24="aprobada",O24<>"pendiente",P24<>"pendiente",OR(J24="por_corroborar",AND(J24="corroborada",Q24<>""))),"SÍ","NO") -> NO
... A424: R0420 | B424: garciapenaborders | C424: prestolmasacre | D424: garciapenaborders | E424: prestolmasacre | F424: resonancia | G424: Cita el libro por su título exacto: «un testimonio El masacre se pasa a pie by Freddy Prestol Castillo (Santo Domingo, 1973)». | H424: corroborada | J424: corroborada | K424: C03 | L424: A03 | M424: frontera | N424: C03 | O424: pendiente | P424: pendiente | R424: sin_iniciar | S424: pendiente | T424: pendiente | U424: =IF(AND(R424="revisada",S424="pasa",T424="aprobada",O424<>"pendiente",P424<>"pendiente",OR(J424="por_corroborar",AND(J424="corroborada",Q424<>""))),"SÍ","NO") -> NO
A425: R0421 | B425: stewardpuertorico | C425: mintz | D425: steward | E425: mintz | F425: resonancia | G425: Coautoría directa: Sidney W. Mintz figura como investigador del mismo proyecto («Dr. Sidney W. Mintz, then of Columbia University»), no como cita externa. | H425: corroborada | I425: redirigir_extremo_y_conservar | J425: corroborada | K425: P00 | L425: P00 | M425: interna | N425: P00 | O425: no | P425: no | Q425: Coautoría directa de Sidney W. Mintz en el proyecto The People of Puerto Rico. | R425: revisada | S425: pasa | T425: aprobada | U425: =IF(AND(R425="revisada",S425="pasa",T425="aprobada",O425<>"pendiente",P425<>"pendiente",OR(J425="por_corroborar",AND(J425="corroborada",Q425<>""))),"SÍ","NO") -> SÍ
A426: R0422 | B426: mitchellalibi | C426: robinsonmarxismo | D426: mitchellalibi | E426: robinsonmarxismo | F426: resonancia | G426: Cita el libro por su título original en inglés como autoridad: «Cedric Robinson, Black Marxism: The Making of the Black Radical Tradition», mismo texto catalogado en su edición en español. | H426: corroborada | J426: corroborada | K426: DE01 | L426: DE01 | M426: interna | N426: DE01 | O426: pendiente | P426: pendiente | R426: sin_iniciar | S426: pendiente | T426: pendiente | U426: =IF(AND(R426="revisada",S426="pasa",T426="aprobada",O426<>"pendiente",P426<>"pendiente",OR(J426="por_corroborar",AND(J426="corroborada",Q426<>""))),"SÍ","NO") -> NO
A427: R0423 | B427: londonoargonauts | C427: rappaportcobarde | D427: londonoargonauts | E427: rappaportcobarde | F427: resonancia | G427: Cita el libro por su título exacto en inglés: «Rappaport, J. (2020). Cowards Don't Make History: Orlando Fals Borda and the Origins of Participatory Action Research», misma obra catalogada en su edición en español. | H427: corroborada | J427: corroborada | K427: S01 | L427: B03 | M427: frontera | N427: B03 | O427: pendiente | P427: pendiente | R427: sin_iniciar | S427: pendiente | T427: pendiente | U427: =IF(AND(R427="revisada",S427="pasa",T427="aprobada",O427<>"pendiente",P427<>"pendiente",OR(J427="por_corroborar",AND(J427="corroborada",Q427<>""))),"SÍ","NO") -> NO
A428: R0424 | B428: crawfordturtlemen | C428: schwartz_seaofstorms | D428: crawfordturtlemen | E428: schwartz_seaofstorms | F428: resonancia | G428: Cita el libro por su título exacto en notas: «Schwartz, Sea of Storms». | H428: corroborada | J428: corroborada | K428: B03 | L428: C01 | M428: frontera | N428: C01 | O428: pendiente | P428: pendiente | R428: sin_iniciar | S428: pendiente | T428: pendiente | U428: =IF(AND(R428="revisada",S428="pasa",T428="aprobada",O428<>"pendiente",P428<>"pendiente",OR(J428="por_corroborar",AND(J428="corroborada",Q428<>""))),"SÍ","NO") -> NO
A429: R0425 | B429: crawfordturtlemen | C429: johnson_climatecuba | D429: crawfordturtlemen | E429: johnson_climatecuba | F429: resonancia | G429: Cita el libro por su título exacto en notas: «Johnson, Climate and Catastrophe [in Cuba]». | H429: corroborada | J429: corroborada | K429: B03 | L429: C01 | M429: frontera | N429: C01 | O429: pendiente | P429: pendiente | R429: sin_iniciar | S429: pendiente | T429: pendiente | U429: =IF(AND(R429="revisada",S429="pasa",T429="aprobada",O429<>"pendiente",P429<>"pendiente",OR(J429="por_corroborar",AND(J429="corroborada",Q429<>""))),"SÍ","NO") -> NO
A430: R0426 | B430: alvarezboro | C430: chicamusicaafricana | D430: alvarezboro | E430: chicamusicaafricana | F430: resonancia | G430: Comparten lugar (Cartagena) y el eje de la vida afrocaribeña contemporánea en la ciudad —violencia y marginalidad de un lado, cultura picotera del otro, en barrios contiguos. Por corroborar el vínculo directo. | H430: por_corroborar | J430: por_corroborar | K430: S01 | L430: B04 | M430: frontera | N430: B04 | O430: pendiente | P430: pendiente | R430: sin_iniciar | S430: pendiente | T430: pendiente | U430: =IF(AND(R430="revisada",S430="pasa",T430="aprobada",O430<>"pendiente",P430<>"pendiente",OR(J430="por_corroborar",AND(J430="corroborada",Q430<>""))),"SÍ","NO") -> NO
A431: R0427 | B431: belisodelirium | C431: palmiengangas | D431: belisodelirium | E431: palmiengangas | F431: resonancia | G431: Comparten lugar (Cuba) y el eje del cuerpo religioso afrocubano: la autora se formó en santería cubana antes de escribir sobre violencia policial. Por corroborar el vínculo directo. | H431: por_corroborar | J431: por_corroborar | K431: A01 | L431: C04 | M431: frontera | N431: C04 | O431: pendiente | P431: pendiente | R431: sin_iniciar | S431: pendiente | T431: pendiente | U431: =IF(AND(R431="revisada",S431="pasa",T431="aprobada",O431<>"pendiente",P431<>"pendiente",OR(J431="por_corroborar",AND(J431="corroborada",Q431<>""))),"SÍ","NO") -> NO
A432: R0428 | B432: castorspiritual | C432: james | D432: castorspiritual | E432: james | F432: resonancia | G432: Comparten el fenómeno Soberanías: el libro rastrea explícitamente la ruta del Black Power trinitario a la religión ifá, linaje intelectual que reclama a C.L.R. James. Por corroborar el vínculo directo. | H432: por_corroborar | J432: por_corroborar | K432: B05 | L432: C01 | M432: frontera | N432: C01 | O432: pendiente | P432: pendiente | R432: sin_iniciar | S432: pendiente | T432: pendiente | U432: =IF(AND(R432="revisada",S432="pasa",T432="aprobada",O432<>"pendiente",P432<>"pendiente",OR(J432="por_corroborar",AND(J432="corroborada",Q432<>""))),"SÍ","NO") -> NO
A433: R0429 | B433: godreauscripts | C433: zambrana | D433: godreauscripts | E433: zambrana | F433: resonancia | G433: Comparten lugar (Puerto Rico) y el fenómeno Colonialidad: ambas leen la administración colonial estadounidense sobre la isla desde ángulos distintos (raza cultural vs. deuda). Por corroborar el vínculo directo. | H433: por_corroborar | J433: por_corroborar | K433: C02 | L433: DE01 | M433: frontera | N433: DE01 | O433: pendiente | P433: pendiente | R433: sin_iniciar | S433: pendiente | T433: pendiente | U433: =IF(AND(R433="revisada",S433="pasa",T433="aprobada",O433<>"pendiente",P433<>"pendiente",OR(J433="por_corroborar",AND(J433="corroborada",Q433<>""))),"SÍ","NO") -> NO
A434: R0430 | B434: williamscapitalismo | C434: james | D434: williamscapitalismo | E434: james | F434: resonancia | G434: Williams y James se formaron juntos en Trinidad y el libro de 1944 discute de frente Los jacobinos negros: la misma revolución, leída desde la contabilidad del azúcar en vez de la insurrección. Cita verificada en el ejemplar. | H434: corroborada | J434: corroborada | K434: P00 | L434: C01 | M434: frontera | N434: C01 | O434: pendiente | P434: pendiente | R434: sin_iniciar | S434: pendiente | T434: pendiente | U434: =IF(AND(R434="revisada",S434="pasa",T434="aprobada",O434<>"pendiente",P434<>"pendiente",OR(J434="por_corroborar",AND(J434="corroborada",Q434<>""))),"SÍ","NO") -> NO
A435: R0431 | B435: robinsonmarxismo | C435: williamscapitalismo | D435: robinsonmarxismo | E435: williamscapitalismo | F435: resonancia | G435: Robinson toma de Williams la premisa de que la acumulación europea se montó sobre la esclavitud, y le reprocha haberse quedado en la economía sin nombrar la raza. Cita verificada en el ejemplar (13 menciones). | H435: corroborada | J435: corroborada | K435: DE01 | L435: P00 | M435: frontera | N435: DE01 | O435: pendiente | P435: pendiente | R435: sin_iniciar | S435: pendiente | T435: pendiente | U435: =IF(AND(R435="revisada",S435="pasa",T435="aprobada",O435<>"pendiente",P435<>"pendiente",OR(J435="por_corroborar",AND(J435="corroborada",Q435<>""))),"SÍ","NO") -> NO
A436: R0432 | B436: rediker | C436: williamscapitalismo | D436: rediker | E436: williamscapitalismo | F436: resonancia | G436: Rediker reconstruye en el barco negrero la maquinaria que Williams describió en el balance comercial. Cita verificada en el ejemplar. | H436: corroborada | J436: corroborada | K436: A03 | L436: P00 | M436: frontera | N436: A03 | O436: pendiente | P436: pendiente | R436: sin_iniciar | S436: pendiente | T436: pendiente | U436: =IF(AND(R436="revisada",S436="pasa",T436="aprobada",O436<>"pendiente",P436<>"pendiente",OR(J436="por_corroborar",AND(J436="corroborada",Q436<>""))),"SÍ","NO") -> NO
A437: R0433 | B437: benitez | C437: williamscapitalismo | D437: benitez | E437: williamscapitalismo | F437: resonancia | G437: La máquina de plantación de Benítez Rojo presupone la tesis de Williams sobre el azúcar como motor del capital atlántico. Cita verificada en el ejemplar. | H437: corroborada | J437: corroborada | K437: S01 | L437: P00 | M437: frontera | N437: S01 | O437: pendiente | P437: pendiente | R437: sin_iniciar | S437: pendiente | T437: pendiente | U437: =IF(AND(R437="revisada",S437="pasa",T437="aprobada",O437<>"pendiente",P437<>"pendiente",OR(J437="por_corroborar",AND(J437="corroborada",Q437<>""))),"SÍ","NO") -> NO
... A587: R0583 | B587: keeganhofman | C587: gonzalezsojourners | D587: keeganhofman | E587: gonzalezsojourners | F587: resonancia | G587: Keegan y Hofman citan a González para la formación garífuna en San Vicente. Cita verificada en el ejemplar. | H587: corroborada | J587: corroborada | K587: P00 | L587: B02 | M587: frontera | N587: B02 | O587: pendiente | P587: pendiente | R587: sin_iniciar | S587: pendiente | T587: pendiente | U587: =IF(AND(R587="revisada",S587="pasa",T587="aprobada",O587<>"pendiente",P587<>"pendiente",OR(J587="por_corroborar",AND(J587="corroborada",Q587<>""))),"SÍ","NO") -> NO
A588: R0584 | B588: keeganhofman | C588: mintz | D588: keeganhofman | E588: mintz | F588: resonancia | G588: Keegan y Hofman discuten el área sociocultural de Mintz para preguntarse si el archipiélago era una unidad antes de la colonia. Cita verificada en el ejemplar. | H588: corroborada | I588: conservar | J588: corroborada | K588: P00 | L588: P00 | M588: interna | N588: P00 | O588: no | P588: no | Q588: Cita a Mintz verificada en el ejemplar; páginas por registrar en la ficha final. | R588: revisada | S588: pasa | T588: aprobada | U588: =IF(AND(R588="revisada",S588="pasa",T588="aprobada",O588<>"pendiente",P588<>"pendiente",OR(J588="por_corroborar",AND(J588="corroborada",Q588<>""))),"SÍ","NO") -> SÍ
A589: R0585 | B589: keeganhofman | C589: atkinsonearliest | D589: keeganhofman | E589: atkinsonearliest | F589: resonancia | G589: Keegan y Hofman usan el volumen jamaiquino de Atkinson para el taíno insular. Cita verificada en el ejemplar (23 menciones). | H589: corroborada | J589: corroborada | K589: P00 | L589: C04 | M589: frontera | N589: C04 | O589: pendiente | P589: pendiente | R589: sin_iniciar | S589: pendiente | T589: pendiente | U589: =IF(AND(R589="revisada",S589="pasa",T589="aprobada",O589<>"pendiente",P589<>"pendiente",OR(J589="por_corroborar",AND(J589="corroborada",Q589<>""))),"SÍ","NO") -> NO
A590: R0586 | B590: crawfordturtlemen | C590: keeganhofman | D590: crawfordturtlemen | E590: keeganhofman | F590: resonancia | G590: Crawford apoya en Keegan y Hofman la larga historia de navegación y pesca precolombina. Cita verificada en el ejemplar. | H590: corroborada | J590: corroborada | K590: B03 | L590: P00 | M590: frontera | N590: B03 | O590: pendiente | P590: pendiente | R590: sin_iniciar | S590: pendiente | T590: pendiente | U590: =IF(AND(R590="revisada",S590="pasa",T590="aprobada",O590<>"pendiente",P590<>"pendiente",OR(J590="por_corroborar",AND(J590="corroborada",Q590<>""))),"SÍ","NO") -> NO
A591: R0587 | B591: bollandbelize | C591: atkinsonearliest | D591: bollandbelize | E591: atkinsonearliest | F591: resonancia | G591: Comparten el fenómeno Colonialidad. Por corroborar el vínculo directo. | H591: por_corroborar | J591: por_corroborar | K591: C01 | L591: C04 | M591: frontera | N591: C04 | O591: pendiente | P591: pendiente | R591: sin_iniciar | S591: pendiente | T591: pendiente | U591: =IF(AND(R591="revisada",S591="pasa",T591="aprobada",O591<>"pendiente",P591<>"pendiente",OR(J591="por_corroborar",AND(J591="corroborada",Q591<>""))),"SÍ","NO") -> NO
A592: R0588 | B592: atkinsonearliest | C592: whiteheadtiger | D592: atkinsonearliest | E592: whiteheadtiger | F592: resonancia | G592: Comparten el fenómeno Memoria y espiritualidad. Por corroborar el vínculo directo. | H592: por_corroborar | J592: por_corroborar | K592: C04 | L592: C04 | M592: interna | N592: C04 | O592: pendiente | P592: pendiente | R592: sin_iniciar | S592: pendiente | T592: pendiente | U592: =IF(AND(R592="revisada",S592="pasa",T592="aprobada",O592<>"pendiente",P592<>"pendiente",OR(J592="por_corroborar",AND(J592="corroborada",Q592<>""))),"SÍ","NO") -> NO

Sheet Protocolo
A1: Atlas 2.0 · protocolo por lote | B1: Atlas 2.0 · protocolo por lote | C1: Atlas 2.0 · protocolo por lote | D1: Atlas 2.0 · protocolo por lote | E1: Atlas 2.0 · protocolo por lote | F1: Atlas 2.0 · protocolo por lote
A2: Secuencia obligatoria. Saltar una puerta impide marcar el lote como cerrado. | B2: Secuencia obligatoria. Saltar una puerta impide marcar el lote como cerrado. | C2: Secuencia obligatoria. Saltar una puerta impide marcar el lote como cerrado. | D2: Secuencia obligatoria. Saltar una puerta impide marcar el lote como cerrado. | E2: Secuencia obligatoria. Saltar una puerta impide marcar el lote como cerrado. | F2: Secuencia obligatoria. Saltar una puerta impide marcar el lote como cerrado.
A4: Paso | B4: Puerta | C4: Responsable | D4: Entrada | E4: Acción | F4: Criterio de aceptación
A5: 1 | B5: Congelar fuente | C5: Edición técnica | D5: SHA-256 y recuentos de v1.15.0 | E5: Registrar huella, 233 entradas, 588 relaciones y 30 lugares. | F5: La fuente coincide exactamente con el manifiesto del lote.
A6: 2 | B6: Generar manifiesto | C6: Edición técnica | D6: IDs del lote y relaciones asignadas | E6: Extraer solo el lote; no escribir en datos-atlas.js/json. | F6: Cobertura exacta, sin duplicados ni extremos huérfanos.
A7: 3 | B7: Reunir textos | C7: Investigación | D7: Obras del lote | E7: Conseguir texto completo o declarar el límite de lectura. | F7: Cada decisión dice qué se consultó; no se clasifica por título.
A8: 4 | B8: Completar entrada | C8: Revisión editorial | D8: Texto y metadatos | E8: Corriente, operaciones, temporalidades, orillas, marcas y fuentes. | F8: Los campos obligatorios están completos o el pendiente está declarado.
A9: 5 | B9: Revisar relaciones | C9: Revisión editorial | D9: Relaciones cuyo lote de revisión es el actual | E9: Declarar corroboración, fuente/páginas, fricción y cruce lingüístico. | F9: Ninguna corroborada sin fuente; ninguna fricción sin argumento.
A10: 6 | B10: Revisión de pares | C10: Segundo lector | D10: Ficha y evidencia | E10: Confirmar, devolver o mantener pendiente. | F10: No hay confirmación por inferencia automática.
A11: 7 | B11: Generar salida | C11: Edición técnica | D11: Decisiones aprobadas | E11: Ejecutar generador reproducible en carpeta aislada. | F11: Dos ejecuciones producen bytes idénticos.
A12: 8 | B12: Validar | C12: Edición técnica | D12: Salida generada | E12: Ejecutar reglas de esquema e integridad. | F12: 0 errores y 0 advertencias.
A13: 9 | B13: Revisar diferencias | C13: Dirección académica | D13: Diff, recuentos y fichas | E13: Comprobar entradas, relaciones, redirecciones y campos heredados. | F13: Solo cambió lo autorizado en el lote.
A14: 10 | B14: Aprobar lote | C14: Dirección académica | D14: Expediente del lote | E14: Registrar responsable, fecha, fundamento y decisión. | F14: Todas las filas tienen aprobación o pendiente explícito.
A15: 11 | B15: Commit reversible | C15: Edición técnica | D15: Lote aprobado | E15: Crear un único commit; no hacer merge a main. | F15: Rama limpia y sincronizada; reversión probada o documentada.
A16: 12 | B16: Cerrar bitácora | C16: Coordinación | D16: Resultado del commit | E16: Actualizar Control, Lotes y rastro de cifras. | F16: El siguiente lote conoce su dependencia exacta.

Sheet Reglas
A1: Atlas 2.0 · reglas bloqueantes | B1: Atlas 2.0 · reglas bloqueantes | C1: Atlas 2.0 · reglas bloqueantes | D1: Atlas 2.0 · reglas bloqueantes
A2: Las reglas proceden del esquema aprobado y de los seis hallazgos del piloto. | B2: Las reglas proceden del esquema aprobado y de los seis hallazgos del piloto. | C2: Las reglas proceden del esquema aprobado y de los seis hallazgos del piloto. | D2: Las reglas proceden del esquema aprobado y de los seis hallazgos del piloto.
A4: N. | B4: Origen | C4: Regla | D4: Bloqueante
A5: 1 | B5: esquema 2.0 | C5: Procedencia ausente o fuera del vocabulario cerrado. | D5: sí
A6: 2 | B6: esquema 2.0 | C6: Entrada con procedencia_verificada en falso que pase a estado confirmada. | D6: sí
A7: 3 | B7: esquema 2.0 | C7: Entrada sin autoría identificable con procedencia_verificada en verdadero. | D7: sí
A8: 4 | B8: esquema 2.0 | C8: Proceso ausente, vacío o con algún valor fuera del vocabulario cerrado. | D8: sí
A9: 5 | B9: esquema 2.0 | C9: Combinación prohibida de procedencia y proceso, según _combinaciones_prohibidas. | D9: sí
A10: 6 | B10: esquema 2.0 | C10: Entrada en estado candidatura_preliminar sin corriente_candidata. | D10: sí
A11: 7 | B11: esquema 2.0 | C11: Entrada en estado confirmada sin fundamento escrito. | D11: sí
A12: 8 | B12: esquema 2.0 | C12: Entrada de siembra con corriente_candidata: no pasó por la taxonomía anterior. | D12: sí
A13: 9 | B13: esquema 2.0 | C13: Identificador duplicado o inexistente. | D13: sí
A14: 10 | B14: esquema 2.0 | C14: Corriente principal ausente, inexistente o repetida. | D14: sí
A15: 11 | B15: esquema 2.0 | C15: Más de dos corrientes secundarias. | D15: sí
A16: 12 | B16: esquema 2.0 | C16: Corriente secundaria igual a la principal. | D16: sí
... A35: 31 | B35: piloto · entrada compuesta | C35: obras_componentes conserva el identificador público y registra corriente/temporalidad por componente. | D35: sí

Sheet Piloto aprobado
A1: Atlas 2.0 · piloto aprobado | B1: Atlas 2.0 · piloto aprobado | C1: Atlas 2.0 · piloto aprobado | D1: Atlas 2.0 · piloto aprobado | E1: Atlas 2.0 · piloto aprobado | F1: Atlas 2.0 · piloto aprobado | G1: Atlas 2.0 · piloto aprobado | H1: Atlas 2.0 · piloto aprobado | I1: Atlas 2.0 · piloto aprobado | J1: Atlas 2.0 · piloto aprobado | K1: Atlas 2.0 · piloto aprobado | L1: Atlas 2.0 · piloto aprobado
A2: El piloto prueba la arquitectura; una clasificación confirmada puede conservar pendientes documentales antes de estar lista para la migración final. | B2: El piloto prueba la arquitectura; una clasificación confirmada puede conservar pendientes documentales antes de estar lista para la migración final. | C2: El piloto prueba la arquitectura; una clasificación confirmada puede conservar pendientes documentales antes de estar lista para la migración final. | D2: El piloto prueba la arquitectura; una clasificación confirmada puede conservar pendientes documentales antes de estar lista para la migración final. | E2: El piloto prueba la arquitectura; una clasificación confirmada puede conservar pendientes documentales antes de estar lista para la migración final. | F2: El piloto prueba la arquitectura; una clasificación confirmada puede conservar pendientes documentales antes de estar lista para la migración final. | G2: El piloto prueba la arquitectura; una clasificación confirmada puede conservar pendientes documentales antes de estar lista para la migración final. | H2: El piloto prueba la arquitectura; una clasificación confirmada puede conservar pendientes documentales antes de estar lista para la migración final. | I2: El piloto prueba la arquitectura; una clasificación confirmada puede conservar pendientes documentales antes de estar lista para la migración final. | J2: El piloto prueba la arquitectura; una clasificación confirmada puede conservar pendientes documentales antes de estar lista para la migración final. | K2: El piloto prueba la arquitectura; una clasificación confirmada puede conservar pendientes documentales antes de estar lista para la migración final. | L2: El piloto prueba la arquitectura; una clasificación confirmada puede conservar pendientes documentales antes de estar lista para la migración final.
A4: id | B4: Decisión | C4: Estado | D4: Principal | E4: Secundarias | F4: Operaciones | G4: Temporalidades | H4: Orillas | I4: Fuentes | J4: Fundamento | K4: Pendientes | L4: Lista final
A5: mintz | B5: mantener_pendiente | C5: pendiente_revision_con_texto | G5: {"valor_heredado":"1974–85","publicacion":null,"requiere_revision":true} | J5: El nodo reúne dos obras con argumentos diferentes; no se confirma una corriente única hasta revisar cada componente. | K5: corriente_por_componente; mecanismo_capitalismo_racial; operaciones; orillas | L5: =INDEX('Plan 233'!$W$5:$W$237,MATCH(A5,'Plan 233'!$A$5:$A$237,0)) -> NO
A6: price | B6: confirmar | C6: confirmada | D6: fugas_cimarronajes_emancipaciones | F6: reconstruir un archivo; comparar orillas | G6: {"publicacion":{"valor":1973,"era":"EC","precision":"exacta"}} | I6: https://search.worldcat.org/oclc/805137?tab=details https://www.press.jhu.edu/books/title/1940/maroon-societies | J6: El volumen organiza una comparación hemisférica de comunidades cimarronas y combina fuentes históricas y estudios antropológicos. | K6: orillas | L6: =INDEX('Plan 233'!$W$5:$W$237,MATCH(A6,'Plan 233'!$A$5:$A$237,0)) -> NO
A7: totumo | B7: confirmar_con_correccion | C7: confirmada | D7: fugas_cimarronajes_emancipaciones | F7: reconstruir un archivo; confrontar una categoría | G7: {"publicacion":{"valor":2020,"era":"EC","precision":"exacta"},"periodo_estudiado":{"inicio":{"valor":1714,"era":"EC","precision":"exacta"},"fin":{"valor":1767,"era":"EC","precision":"exacta"}}} | I7: https://revistas.uniatlantico.edu.co/index.php/Historia_Caribe/article/view/2403 https://doi.org/10.15648/hc.37.2020.9 | J7: El artículo reconstruye acuerdos entre cimarrones y autoridades coloniales y cuestiona la idealización del palenque como libertad absoluta. | K7: orillas | L7: =INDEX('Plan 233'!$W$5:$W$237,MATCH(A7,'Plan 233'!$A$5:$A$237,0)) -> NO
A8: chande | B8: confirmar_con_correccion | C8: confirmada | D8: memorias_espiritualidades_archivos_vivos | E8: creolizaciones_traducciones_opacidades | F8: producir etnografía; escuchar; preservar una memoria; documentar una práctica; teorizar | G8: {"publicacion":{"valor":2016,"era":"EC","precision":"exacta"}} | H8: orillas: La Loma, El Paso, Cesar [territorio estudiado] | I8: https://dialnet.unirioja.es/descarga/articulo/5888296.pdf https://doi.org/10.15648/cl.24.2016.6 | J8: El texto comprende el Chandé como pensamiento, saber y memoria mediante diálogo comunitario y respeto por el silencio de sabedoras y sabedores. | K8: fechas_del_trabajo_de_campo; duracion_historica; coordenadas_orilla | L8: =INDEX('Plan 233'!$W$5:$W$237,MATCH(A8,'Plan 233'!$A$5:$A$237,0)) -> NO
A9: steward | B9: fusionar_y_confirmar | C9: confirmada | D9: postplantacion_trabajo_desposesion | F9: producir etnografía; comparar orillas; teorizar | G9: {"publicacion":{"valor":1956,"era":"EC","precision":"exacta"}} | I9: https://eric.ed.gov/?id=ED019306 https://files.archon.library.illinois.edu/uasfa/1502021.pdf | J9: La obra compara subculturas puertorriqueñas configuradas por entornos y regímenes económicos locales; el identificador más antiguo conserva los enlaces citables. | K9: orillas | L9: =INDEX('Plan 233'!$W$5:$W$237,MATCH(A9,'Plan 233'!$A$5:$A$237,0)) -> NO
A10: stewardpuertorico | B10: fusionar_y_redirigir | C10: revisada_redireccion | G10: {"valor_heredado":"1956","publicacion":1956,"requiere_revision":false} | I10: https://books.google.com/books/about/The_People_of_Puerto_Rico.html?id=UVkf0gEACAAJ https://files.archon.library.illinois.edu/uasfa/1502021.pdf | J10: Es la misma obra que steward; sus metadatos y relaciones se conservan mediante fusión y redirección. | K10: — | L10: =INDEX('Plan 233'!$W$5:$W$237,MATCH(A10,'Plan 233'!$A$5:$A$237,0)) -> SÍ
A11: bassiacuoso | B11: confirmar | C11: confirmada | D11: rutas_diasporas_territorios_acuosos | E11: soberanias_fronteras_ocupaciones | F11: reconstruir un archivo; cartografiar; seguir una ruta; comparar orillas; teorizar | G11: {"publicacion":{"valor":2016,"era":"EC","precision":"exacta"},"traduccion_es":{"valor":2021,"era":"EC","precision":"exacta"},"periodo_estudiado":{"inicio":{"valor":1760,"era":"EC","precision":"exacta"},"fin":{"valor":1860,"era":"EC","precision":"exacta"}}} | H11: orillas: Gran Caribe [territorio estudiado] | I11: https://www.dukeupress.edu/an-aqueous-territory https://editorial.uninorte.edu.co/gpd-un-territorio-acuoso-9789587891669.html | J11: La obra organiza su argumento alrededor de circulaciones marítimas, geografías vividas y un Gran Caribe transimperial. | K11: rutas_con_paginas | L11: =INDEX('Plan 233'!$W$5:$W$237,MATCH(A11,'Plan 233'!$A$5:$A$237,0)) -> NO
A12: williamscapitalismo | B12: confirmar | C12: confirmada | D12: trata_esclavizacion_plantacion | E12: postplantacion_trabajo_desposesion | F12: reconstruir un archivo; teorizar; confrontar una categoría | G12: {"publicacion":{"valor":1944,"era":"EC","precision":"exacta"}} | I12: https://uncpress.org/9781469663685/capitalism-and-slavery-third-edition/ https://glc.yale.edu/sites/default/files/pdf/capatlism_and_slavery.pdf | J12: El libro sitúa la trata y la esclavización antillana en la formación del capitalismo británico y discute la abolición desde la transformación económica. | K12: periodo_estudiado_normalizado | L12: =INDEX('Plan 233'!$W$5:$W$237,MATCH(A12,'Plan 233'!$A$5:$A$237,0)) -> NO
A13: keeganhofman | B13: confirmar_con_ajuste_de_esquema | C13: confirmada | D13: invasiones_mundos_indigenas | E13: rutas_diasporas_territorios_acuosos | F13: cartografiar; comparar orillas; interpretar materialidades | G13: {"publicacion":{"valor":2017,"era":"EC","precision":"exacta"},"periodo_estudiado":{"inicio":null,"fin":{"valor":1492,"era":"EC","precision":"exacta"},"precision":"aproximada","descripcion":"Milenios anteriores a 1492; el inicio exacto debe extraerse del ejemplar antes de cargarlo."}} | H13: orillas: Archipiélago del Caribe [territorio estudiado] | I13: https://global.oup.com/academic/product/the-caribbean-before-columbus-9780190605247 https://academic.oup.com/book/11404/chapter/160078399 | J13: La síntesis arqueológica reconstruye poblamientos, redes interinsulares y mundos indígenas anteriores a la ocupación europea. | K13: inicio_periodo_estudiado_con_era | L13: =INDEX('Plan 233'!$W$5:$W$237,MATCH(A13,'Plan 233'!$A$5:$A$237,0)) -> NO
A14: bourgoisethnicity | B14: confirmar_con_ajuste_de_catalogo | C14: confirmada | D14: postplantacion_trabajo_desposesion | F14: producir etnografía; reconstruir un archivo; teorizar | G14: {"publicacion":{"valor":1989,"era":"EC","precision":"exacta"}} | H14: orillas: Costa Rica [territorio estudiado]; Panamá [territorio estudiado] | I14: https://www.philippebourgois.net/articles/Bourgois%201989%20Ethnicity%20at%20Work.pdf https://read.dukeupress.edu/hahr/article/70/2/349/146510/Ethnicity-at-Work-Divided-Labor-on-a-Central | J14: La obra muestra cómo una empresa bananera transnacional organiza la división étnica del trabajo y reproduce jerarquías raciales y de clase en Costa Rica y Panamá. | K14: periodos_historicos; fechas_trabajo_de_campo; tipo_de_violencia | L14: =INDEX('Plan 233'!$W$5:$W$237,MATCH(A14,'Plan 233'!$A$5:$A$237,0)) -> NO

Sheet Corrientes
A1: Atlas 2.0 · catálogo de corrientes | B1: Atlas 2.0 · catálogo de corrientes | C1: Atlas 2.0 · catálogo de corrientes | D1: Atlas 2.0 · catálogo de corrientes | E1: Atlas 2.0 · catálogo de corrientes | F1: Atlas 2.0 · catálogo de corrientes | G1: Atlas 2.0 · catálogo de corrientes
A2: Una obra entra en una corriente porque esa corriente organiza su argumento. El reparto numérico no es criterio de clasificación. | B2: Una obra entra en una corriente porque esa corriente organiza su argumento. El reparto numérico no es criterio de clasificación. | C2: Una obra entra en una corriente porque esa corriente organiza su argumento. El reparto numérico no es criterio de clasificación. | D2: Una obra entra en una corriente porque esa corriente organiza su argumento. El reparto numérico no es criterio de clasificación. | E2: Una obra entra en una corriente porque esa corriente organiza su argumento. El reparto numérico no es criterio de clasificación. | F2: Una obra entra en una corriente porque esa corriente organiza su argumento. El reparto numérico no es criterio de clasificación. | G2: Una obra entra en una corriente porque esa corriente organiza su argumento. El reparto numérico no es criterio de clasificación.
A4: Clave | B4: N. | C4: Etiqueta ES | D4: Etiqueta EN | E4: Provisional | F4: Correspondencia anterior | G4: Vía de constitución
A5: invasiones_mundos_indigenas | B5: 1 | C5: Invasiones, colonialidades y mundos indígenas | D5: Invasions, colonialities and Indigenous worlds | E5: sí | F5: sin correspondencia directa en la taxonomía anterior | G5: siembra dirigida
A6: trata_esclavizacion_plantacion | B6: 2 | C6: Trata, esclavización y plantación | D6: Slave trade, enslavement and plantation | E6: sí | F6: sin correspondencia directa en la taxonomía anterior | G6: siembra dirigida + revisión del corpus heredado
A7: fugas_cimarronajes_emancipaciones | B7: 3 | C7: Fugas, cimarronajes y emancipaciones | D7: Flight, marronage and emancipations | E7: sí | F7: con correspondencia en la taxonomía anterior | G7: revisión del corpus heredado + siembra dirigida
A8: postplantacion_trabajo_desposesion | B8: 4 | C8: Postplantación, trabajo y desposesión | D8: Post-plantation, labor and dispossession | E8: sí | F8: con correspondencia en la taxonomía anterior | G8: revisión del corpus heredado + siembra dirigida
A9: rutas_diasporas_territorios_acuosos | B9: 5 | C9: Rutas, diásporas y territorios acuosos | D9: Routes, diasporas and aqueous territories | E9: sí | F9: sin correspondencia directa en la taxonomía anterior | G9: siembra dirigida
A10: huracanes_ecologias_materialidades_vivas | B10: 6 | C10: Huracanes, ecologías y materialidades vivas | D10: Hurricanes, ecologies and living materialities | E10: sí | F10: con correspondencia en la taxonomía anterior | G10: revisión del corpus heredado + siembra dirigida
A11: soberanias_fronteras_ocupaciones | B11: 7 | C11: Soberanías, fronteras y ocupaciones | D11: Sovereignties, borders and occupations | E11: sí | F11: con correspondencia en la taxonomía anterior | G11: revisión del corpus heredado + siembra dirigida
A12: creolizaciones_traducciones_opacidades | B12: 8 | C12: Creolizaciones, traducciones y opacidades | D12: Creolizations, translations and opacities | E12: sí | F12: con correspondencia en la taxonomía anterior | G12: revisión del corpus heredado + siembra dirigida
A13: memorias_espiritualidades_archivos_vivos | B13: 9 | C13: Memorias, espiritualidades y archivos vivos | D13: Memories, spiritualities and living archives | E13: sí | F13: con correspondencia en la taxonomía anterior | G13: revisión del corpus heredado + siembra dirigida
A14: cuerpos_parentescos_eroticas | B14: 10 | C14: Cuerpos, parentescos y eróticas | D14: Bodies, kinships and erotics | E14: sí | F14: con correspondencia en la taxonomía anterior | G14: revisión del corpus heredado + siembra dirigida

Sheet Incidencias
A1: Atlas 2.0 · incidencias heredadas | B1: Atlas 2.0 · incidencias heredadas | C1: Atlas 2.0 · incidencias heredadas | D1: Atlas 2.0 · incidencias heredadas | E1: Atlas 2.0 · incidencias heredadas | F1: Atlas 2.0 · incidencias heredadas | G1: Atlas 2.0 · incidencias heredadas
A2: Las 37 incidencias de la Etapa 1 se conservan como control; el lote no las borra de la bitácora cuando se resuelven. | B2: Las 37 incidencias de la Etapa 1 se conservan como control; el lote no las borra de la bitácora cuando se resuelven. | C2: Las 37 incidencias de la Etapa 1 se conservan como control; el lote no las borra de la bitácora cuando se resuelven. | D2: Las 37 incidencias de la Etapa 1 se conservan como control; el lote no las borra de la bitácora cuando se resuelven. | E2: Las 37 incidencias de la Etapa 1 se conservan como control; el lote no las borra de la bitácora cuando se resuelven. | F2: Las 37 incidencias de la Etapa 1 se conservan como control; el lote no las borra de la bitácora cuando se resuelven. | G2: Las 37 incidencias de la Etapa 1 se conservan como control; el lote no las borra de la bitácora cuando se resuelven.
A4: Severidad | B4: Tipo | C4: Entrada o archivo | D4: Detalle | E4: Acción propuesta | F4: Lote asociado | G4: Estado
A5: crítica | B5: Error de clasificación en la interfaz | C5: tradCode(), con-el-agua-de-por-medio.html línea 713 | D5: La función busca la subcadena «hispano», que no existe dentro de «hispanófono». naveda_esclavoscordoba, alvarezboro y londonoargonauts quedan clasificadas como «comparado». | E5: Corregir la comparación. Mientras no se corrija, el mapa publicado dibuja fricciones epistémicas falsas sobre esas tres entradas. | F5: global | G5: pendiente
A6: crítica | B6: Fricción inferida sin argumento | C6: 429 relaciones | D6: 189 relaciones (44 %) reciben marca de fricción epistémica solo porque los dos extremos tienen distinta cadena en el campo tr. Ninguna declara argumento ni fuente. | E6: Convertir la fricción en campo editorial explícito. Lo que hoy se infiere pasa a «cruce lingüístico», tal como pide el punto 5.7 de la propuesta. | F6: global | G6: pendiente
A7: alta | B7: Campo sin vocabulario controlado | C7: campo tr (233 entradas) | D7: 104 valores distintos para 233 entradas. El campo mezcla lengua de publicación, procedencia o trayectoria de la autoría, territorio estudiado, escala comparativa y, en algunos casos, tema o método. | E7: T01 conserva tr y separa lengua_publicacion, orilla_produccion, territorio_estudiado y alcance_comparativo. Toda propuesta mecánica queda pendiente de revisión humana. | F7: T01 | G7: en_preparacion
A8: alta | B8: Cifra pública desactualizada | C8: proyectos/reflujo-guia.html, párrafo 136 | D8: Publica «131 obras anglófonas, 43 hispanas, 24 francófonas, 6 neerlandesas, 2 danesas», que suma 206 sobre un corpus de 203. El recuento con el mismo criterio da 121, 41, 21, 6 y 14 sin adscripción; ninguna entrada es danesa como lengua principal. | E8: Recontar y corregir, o retirar la cifra hasta que exista un campo de lengua fiable. | F8: global | G8: pendiente
A9: alta | B9: Duplicación | C9: steward / stewardpuertorico | D9: Dos entradas para The People of Puerto Rico (1956), mismo año, mismo lugar, autoría redactada de dos maneras y clasificación distinta (una con capitalismo_racial, la otra sin). | E9: Fusionar. Conservar el id con más relaciones y redirigir el ancla del otro para no romper enlaces citables. | F9: P00 | G9: pendiente
A10: alta | B10: Entrada compuesta | C10: mintz | D10: El título reúne 2 obras distintas bajo un solo identificador: Caribbean Transformations / Sweetness and Power (1974–85). | E10: Evaluar división en entradas separadas conservando el id actual como una de ellas. | F10: P00 | G10: pendiente
A11: alta | B11: Entrada compuesta | C11: ortiz | D11: El título reúne 2 obras distintas bajo un solo identificador: Contrapunteo cubano / Transculturación (1940). | E11: Evaluar división en entradas separadas conservando el id actual como una de ellas. | F11: S01 | G11: pendiente
A12: alta | B12: Entrada compuesta | C12: glissant | D12: El título reúne 2 obras distintas bajo un solo identificador: Poétique de la Relation / Le discours antillais (1981–90). | E12: Evaluar división en entradas separadas conservando el id actual como una de ellas. | F12: S01 | G12: pendiente
A13: alta | B13: Entrada compuesta | C13: brathwaite | D13: El título reúne 2 obras distintas bajo un solo identificador: Nation Language / Tidalectics (1984). | E13: Evaluar división en entradas separadas conservando el id actual como una de ellas. | F13: S01 | G13: pendiente
... A41: baja | B41: Lugar sin uso | C41: guajira | D41: Definido en el catálogo de lugares y no referido por ninguna entrada. | E41: Conservar si la siembra lo prevé; retirar si no. | F41: global | G41: pendiente

Sheet Rastro versiones
A1: Atlas 2.0 · rastro de versiones y recuentos | B1: Atlas 2.0 · rastro de versiones y recuentos | C1: Atlas 2.0 · rastro de versiones y recuentos | D1: Atlas 2.0 · rastro de versiones y recuentos | E1: Atlas 2.0 · rastro de versiones y recuentos | F1: Atlas 2.0 · rastro de versiones y recuentos | G1: Atlas 2.0 · rastro de versiones y recuentos | H1: Atlas 2.0 · rastro de versiones y recuentos
A2: Las cifras de 203 y 233 corresponden a versiones distintas. El control evita mezclarlas en metodología, interfaz y depósitos. | B2: Las cifras de 203 y 233 corresponden a versiones distintas. El control evita mezclarlas en metodología, interfaz y depósitos. | C2: Las cifras de 203 y 233 corresponden a versiones distintas. El control evita mezclarlas en metodología, interfaz y depósitos. | D2: Las cifras de 203 y 233 corresponden a versiones distintas. El control evita mezclarlas en metodología, interfaz y depósitos. | E2: Las cifras de 203 y 233 corresponden a versiones distintas. El control evita mezclarlas en metodología, interfaz y depósitos. | F2: Las cifras de 203 y 233 corresponden a versiones distintas. El control evita mezclarlas en metodología, interfaz y depósitos. | G2: Las cifras de 203 y 233 corresponden a versiones distintas. El control evita mezclarlas en metodología, interfaz y depósitos. | H2: Las cifras de 203 y 233 corresponden a versiones distintas. El control evita mezclarlas en metodología, interfaz y depósitos.
A4: Versión / estado | B4: Fecha | C4: Entradas | D4: Nodos efectivos | E4: Relaciones | F4: Corroboradas | G4: Por corroborar | H4: Nota
A5: v1.14.0 · fuente histórica | B5: 46237 | C5: 203 | D5: 203 | E5: 429 | F5: 233 | G5: 196 | H5: Arquitectura anterior; 28 lugares.
A6: v1.15.0 · fuente de migración | B6: 46241 | C6: 233 | D6: 233 | E6: 588 | F6: 382 | G6: 206 | H6: Corpus público vigente al diseñar este plan; 30 lugares.
A7: P00 · proyección aprobada | B7: 46242 | C7: 233 | D7: 232 | E7: 588 | F7: 381 | G7: 207 | H7: Una redirección; price–totumo baja a por corroborar; el corpus público no cambia.
A8: P00–A02 · capas cerradas | B8: 2026-08-08 | C8: 233 | D8: 232 | E8: 588 | F8: 362 | G8: 226 | H8: P00, S01, A01 y A02 reproducibles y válidos; commits base 99aec5b, 2343008, 58723f9 y 024bb41. fddd441 formaliza el marco conceptual. Corpus público intacto.

Sheet T01 revisión
A1: Atlas 2.0 · T01 · revisión controlada del campo tr
A2: La extracción mecánica conserva el rastro heredado y produce candidaturas no confirmadas. Las columnas de decisión humana permanecen vacías hasta revisión con fuente.
A4: id | B4: Título | C4: Autoría | D4: Lote intelectual | E4: tr original | F4: Lengua(s) detectada(s) | G4: Fragmento parentético | H4: Alertas / ambigüedad | I4: lengua_publicacion | J4: orilla_produccion | K4: territorio_estudiado | L4: alcance_comparativo | M4: fundamento_o_fuente | N4: estado_revision | O4: responsable | P4: fecha_revision | Q4: QA técnico | R4: aprobación académica | S4: listo_para_generar | T4: cohorte corpus
A5: mintz | B5: Caribbean Transformations / Sweetness and Power | C5: Sidney W. Mintz | D5: P00 | E5: anglófono (EE.UU.) | F5: inglés | G5: EE.UU. | H5: abreviaturas por normalizar; función territorial no demostrada | N5: pendiente_revision | Q5: pendiente | R5: pendiente | S5: NO | T5: matriz v1.14.0
A6: trouillot | B6: The Caribbean Region: An Open Frontier | C6: Michel-Rolph Trouillot | D6: C04 | E6: francófono (Haití) | F6: francés | G6: Haití | H6: función territorial no demostrada | N6: pendiente_revision | Q6: pendiente | R6: pendiente | S6: NO | T6: matriz v1.14.0
A7: casimir | B7: The Haitians: A Decolonial History | C7: Jean Casimir | D7: C01 | E7: francófono (Haití) | F7: francés | G7: Haití | H7: función territorial no demostrada | N7: pendiente_revision | Q7: pendiente | R7: pendiente | S7: NO | T7: matriz v1.14.0
A8: price | B8: Maroon Societies | C8: Richard Price (ed.) | D8: P00 | E8: anglófono (EE.UU./Surinam) | F8: inglés | G8: EE.UU./Surinam | H8: varias procedencias o territorios; abreviaturas por normalizar; función territorial no demostrada | N8: pendiente_revision | Q8: pendiente | R8: pendiente | S8: NO | T8: matriz v1.14.0
A9: fouchard | B9: Les marrons de la liberté | C9: Jean Fouchard | D9: B01 | E9: francófono (Haití) | F9: francés | G9: Haití | H9: función territorial no demostrada | N9: pendiente_revision | Q9: pendiente | R9: pendiente | S9: NO | T9: matriz v1.14.0
A10: roberts | B10: Freedom as Marronage | C10: Neil Roberts | D10: B01 | E10: anglófono (Antillas) | F10: inglés | G10: Antillas | H10: función territorial no demostrada | N10: pendiente_revision | Q10: pendiente | R10: pendiente | S10: NO | T10: matriz v1.14.0
A11: totumo | B11: Los acuerdos y la idealización del palenque en la provincia de Cartagena: el caso del Totumo (1714-1767) | C11: Dolcey Romero Jaramillo | D11: P00 | E11: hispano (Colombia) | F11: español | G11: Colombia | H11: función territorial no demostrada | N11: pendiente_revision | Q11: pendiente | R11: pendiente | S11: NO | T11: matriz v1.14.0
A12: ortiz | B12: Contrapunteo cubano / Transculturación | C12: Fernando Ortiz | D12: S01 | E12: hispano (Cuba) | F12: español | G12: Cuba | H12: función territorial no demostrada | N12: pendiente_revision | Q12: pendiente | R12: pendiente | S12: NO | T12: matriz v1.14.0
A13: glissant | B13: Poétique de la Relation / Le discours antillais | C13: Édouard Glissant | D13: S01 | E13: francófono (Martinica) | F13: francés | G13: Martinica | H13: función territorial no demostrada | N13: pendiente_revision | Q13: pendiente | R13: pendiente | S13: NO | T13: matriz v1.14.0
A14: brathwaite | B14: Nation Language / Tidalectics | C14: Kamau Brathwaite | D14: S01 | E14: anglófono (Barbados) | F14: inglés | G14: Barbados | H14: función territorial no demostrada | N14: pendiente_revision | Q14: pendiente | R14: pendiente | S14: NO | T14: matriz v1.14.0
A15: creolite | B15: Éloge de la créolité | C15: Bernabé, Chamoiseau, Confiant | D15: A03 | E15: francófono (Martinica) | F15: francés | G15: Martinica | H15: función territorial no demostrada | N15: pendiente_revision | Q15: pendiente | R15: pendiente | S15: NO | T15: matriz v1.14.0
A16: monahan | B16: Creolizing Practices of Freedom: Recognition and Dissonance / The Creolizing Subject: Race, Reason, and the Politics of Purity | C16: Michael Monahan | D16: S01 | E16: comparado (filosofía afrocaribe) | G16: filosofía afrocaribe | H16: sin lengua explícita; mezcla escala comparativa; mezcla tema, método o escala; función territorial no demostrada | N16: pendiente_revision | Q16: pendiente | R16: pendiente | S16: NO | T16: matriz v1.14.0
A17: vete | B17: The Caribbean Oral Tradition | C17: Hanétha Vété-Congolo (ed.) | D17: B04 | E17: francófono (Guadalupe) | F17: francés | G17: Guadalupe | H17: función territorial no demostrada | N17: pendiente_revision | Q17: pendiente | R17: pendiente | S17: NO | T17: matriz v1.14.0
A18: chande | B18: Sonoridades del Chandé en el Caribe seco | C18: borrador / archivo | D18: P00 | E18: hispano (Colombia) | F18: español | G18: Colombia | H18: función territorial no demostrada | N18: pendiente_revision | Q18: pendiente | R18: pendiente | S18: NO | T18: matriz v1.14.0
A19: quintero | B19: Cuerpo y cultura: las músicas «mulatas» y la subversión del baile | C19: Ángel Quintero Rivera | D19: B03 | E19: hispano (Puerto Rico) | F19: español | G19: Puerto Rico | H19: función territorial no demostrada | N19: pendiente_revision | Q19: pendiente | R19: pendiente | S19: NO | T19: matriz v1.14.0
A20: perezmorales | B20: Cartagena's Privateers | C20: Edgardo Pérez Morales | D20: DE01 | E20: hispano (Colombia) | F20: español | G20: Colombia | H20: función territorial no demostrada | N20: pendiente_revision | Q20: pendiente | R20: pendiente | S20: NO | T20: matriz v1.14.0
A21: sherwood | B21: After Abolition: Britain and the Slave Trade | C21: Marika Sherwood | D21: DE01 | E21: anglófono (R.U.) | F21: inglés | G21: R.U. | H21: abreviaturas por normalizar; función territorial no demostrada | N21: pendiente_revision | Q21: pendiente | R21: pendiente | S21: NO | T21: matriz v1.14.0
A22: cabrera | B22: El Monte | C22: Lydia Cabrera | D22: B05 | E22: hispano (Cuba) | F22: español | G22: Cuba | H22: función territorial no demostrada | N22: pendiente_revision | Q22: pendiente | R22: pendiente | S22: NO | T22: matriz v1.14.0
A23: tambu | B23: Tambú: Curaçao's African-Caribbean Ritual | C23: Nanette de Jong | D23: B05 | E23: neerlandés (Curaçao) | F23: neerlandés | G23: Curaçao | H23: función territorial no demostrada | N23: pendiente_revision | Q23: pendiente | R23: pendiente | S23: NO | T23: matriz v1.14.0
A24: bonilla | B24: Non-Sovereign Futures | C24: Yarimar Bonilla | D24: C02 | E24: francófono/anglófono (Guadalupe–PR) | F24: inglés | francés | G24: Guadalupe–PR | H24: múltiples lenguas; abreviaturas por normalizar; función territorial no demostrada | N24: pendiente_revision | Q24: pendiente | R24: pendiente | S24: NO | T24: matriz v1.14.0
A25: lindskoog | B25: Detain and Punish: Haitian Refugees | C25: Carl Lindskoog | D25: A03 | E25: anglófono (EE.UU.) | F25: inglés | G25: EE.UU. | H25: abreviaturas por normalizar; función territorial no demostrada | N25: pendiente_revision | Q25: pendiente | R25: pendiente | S25: NO | T25: matriz v1.14.0
A26: ferdinand | B26: Une écologie décoloniale | C26: Malcom Ferdinand | D26: C01 | E26: francófono (Martinica) | F26: francés | G26: Martinica | H26: función territorial no demostrada | N26: pendiente_revision | Q26: pendiente | R26: pendiente | S26: NO | T26: matriz v1.14.0
A27: beyondsun | B27: Beyond Sun and Sand | C27: Baver & Lynch (eds.) | D27: A02 | E27: anglófono (EE.UU./PR) | F27: inglés | G27: EE.UU./PR | H27: varias procedencias o territorios; abreviaturas por normalizar; función territorial no demostrada | N27: pendiente_revision | Q27: pendiente | R27: pendiente | S27: NO | T27: matriz v1.14.0
A28: aftershocks | B28: Aftershocks of Disaster (huracán María) | C28: Bonilla & LeBrón (eds.) | D28: B03 | E28: anglófono (PR) | F28: inglés | G28: PR | H28: abreviaturas por normalizar; función territorial no demostrada | N28: pendiente_revision | Q28: pendiente | R28: pendiente | S28: NO | T28: matriz v1.14.0
A29: rodney | B29: How Europe Underdeveloped Africa | C29: Walter Rodney | D29: DE01 | E29: anglófono (Guyana) | F29: inglés | G29: Guyana | H29: función territorial no demostrada | N29: pendiente_revision | Q29: pendiente | R29: pendiente | S29: NO | T29: matriz v1.14.0
A30: araujo | B30: Reparations for Slavery and the Slave Trade: A Transnational and Comparative History | C30: Ana Lucia Araujo | D30: A03 | E30: comparado (transnacional) | G30: transnacional | H30: sin lengua explícita; mezcla escala comparativa; mezcla tema, método o escala; función territorial no demostrada | N30: pendiente_revision | Q30: pendiente | R30: pendiente | S30: NO | T30: matriz v1.14.0
A31: manoalzada | B31: A mano alzada: diáspora intelectual afrocolombiana | C31: archivo | D31: S01 | E31: hispano (Colombia) | F31: español | G31: Colombia | H31: función territorial no demostrada | N31: pendiente_revision | Q31: pendiente | R31: pendiente | S31: NO | T31: matriz v1.14.0
A32: gudynas | B32: Extractivismos | C32: Eduardo Gudynas | D32: A02 | E32: hispano (América Latina) | F32: español | G32: América Latina | H32: función territorial no demostrada | N32: pendiente_revision | Q32: pendiente | R32: pendiente | S32: NO | T32: matriz v1.14.0
A33: esquiva | B33: La esquiva promesa de desarrollo | C33: archivo | D33: S01 | E33: hispano (Colombia) | F33: español | G33: Colombia | H33: función territorial no demostrada | N33: pendiente_revision | Q33: pendiente | R33: pendiente | S33: NO | T33: matriz v1.14.0
A34: workercane | B34: Worker in the Cane: A Puerto Rican Life History | C34: Sidney W. Mintz | D34: A02 | E34: anglófono (EE.UU.) | F34: inglés | G34: EE.UU. | H34: abreviaturas por normalizar; función territorial no demostrada | N34: pendiente_revision | Q34: pendiente | R34: pendiente | S34: NO | T34: matriz v1.14.0
A35: steward | B35: The People of Puerto Rico: A Study in Social Anthropology | C35: Julian Steward et al. (con Mintz, Wolf, Padilla Seda) | D35: P00 | E35: anglófono (EE.UU.) | F35: inglés | G35: EE.UU. | H35: abreviaturas por normalizar; función territorial no demostrada | N35: pendiente_revision | Q35: pendiente | R35: pendiente | S35: NO | T35: matriz v1.14.0
A36: olwigstjohn | B36: Cultural Adaptation and Resistance on St. John | C36: Karen Fog Olwig | D36: B02 | E36: anglófono (hoy EE.UU., antes colonia danesa) | F36: inglés | danés | G36: hoy EE.UU., antes colonia danesa | H36: múltiples lenguas; mezcla temporalidad colonial; abreviaturas por normalizar; función territorial no demostrada | N36: pendiente_revision | Q36: pendiente | R36: pendiente | S36: NO | T36: matriz v1.14.0
A37: hagedorn | B37: Divine Utterances: The Performance of Afro-Cuban Santería | C37: Katherine J. Hagedorn | D37: B05 | E37: anglófono (EE.UU.) | F37: inglés | G37: EE.UU. | H37: abreviaturas por normalizar; función territorial no demostrada | N37: pendiente_revision | Q37: pendiente | R37: pendiente | S37: NO | T37: matriz v1.14.0
A38: pricefirst | B38: First-Time: The Historical Vision of an Afro-American People | C38: Richard Price | D38: B02 | E38: anglófono (EE.UU./Surinam) | F38: inglés | G38: EE.UU./Surinam | H38: varias procedencias o territorios; abreviaturas por normalizar; función territorial no demostrada | N38: pendiente_revision | Q38: pendiente | R38: pendiente | S38: NO | T38: matriz v1.14.0
A39: dunham | B39: Island Possessed | C39: Katherine Dunham | D39: B05 | E39: anglófono (EE.UU.) | F39: inglés | G39: EE.UU. | H39: abreviaturas por normalizar; función territorial no demostrada | N39: pendiente_revision | Q39: pendiente | R39: pendiente | S39: NO | T39: matriz v1.14.0
A40: friedemannlengua | B40: Lengua y sociedad en el Palenque de San Basilio | C40: Carlos Patiño Rosselli & Nina S. de Friedemann | D40: B04 | E40: hispano (Colombia) | F40: español | G40: Colombia | H40: función territorial no demostrada | N40: pendiente_revision | Q40: pendiente | R40: pendiente | S40: NO | T40: matriz v1.14.0
A41: mamalola | B41: Mama Lola: A Vodou Priestess in Brooklyn | C41: Karen McCarthy Brown | D41: B05 | E41: anglófono (EE.UU., diáspora en Brooklyn) | F41: inglés | G41: EE.UU., diáspora en Brooklyn | H41: mezcla trayectoria diaspórica; abreviaturas por normalizar; función territorial no demostrada | N41: pendiente_revision | Q41: pendiente | R41: pendiente | S41: NO | T41: matriz v1.14.0
A42: besson | B42: Martha Brae's Two Histories | C42: Jean Besson | D42: B02 | E42: anglófono (Jamaica/R.U.) | F42: inglés | G42: Jamaica/R.U. | H42: varias procedencias o territorios; abreviaturas por normalizar; función territorial no demostrada | N42: pendiente_revision | Q42: pendiente | R42: pendiente | S42: NO | T42: matriz v1.14.0
... A56: modernblackness | B56: Modern Blackness: Nationalism, Globalization, and the Politics of Culture in Jamaica | C56: Deborah A. Thomas | D56: A03 | E56: anglófono (Jamaica/EE.UU.) | F56: inglés | G56: Jamaica/EE.UU. | H56: varias procedencias o territorios; abreviaturas por normalizar; función territorial no demostrada | N56: pendiente_revision | Q56: pendiente | R56: pendiente | S56: NO | T56: matriz v1.14.0
A57: citizenshipedge | B57: Citizenship on the Edge: Sex, Gender, Race | C57: Nancy J. Hirschmann & Deborah A. Thomas (eds.) | D57: B01 | E57: comparado (teoría política y etnografía) | G57: teoría política y etnografía | H57: sin lengua explícita; mezcla escala comparativa; mezcla tema, método o escala; función territorial no demostrada | N57: pendiente_revision | Q57: pendiente | R57: pendiente | S57: NO | T57: matriz v1.14.0
A58: politicallife | B58: Political Life in the Wake of the Plantation: Sovereignty, Witnessing, Repair | C58: Deborah A. Thomas | D58: A02 | E58: anglófono (Jamaica/EE.UU.) | F58: inglés | G58: Jamaica/EE.UU. | H58: varias procedencias o territorios; abreviaturas por normalizar; función territorial no demostrada | N58: pendiente_revision | Q58: pendiente | R58: pendiente | S58: NO | T58: matriz v1.14.0
A59: downtownladies | B59: Downtown Ladies: Informal Commercial Importers, a Haitian Anthropologist, and Self-Making in Jamaica | C59: Gina Athena Ulysse | D59: A01 | E59: anglófono (EE.UU./Haití) | F59: inglés | G59: EE.UU./Haití | H59: varias procedencias o territorios; abreviaturas por normalizar; función territorial no demostrada | N59: pendiente_revision | Q59: pendiente | R59: pendiente | S59: NO | T59: matriz v1.14.0
A60: reddock | B60: Women, Labour and Politics in Trinidad and Tobago: A History | C60: Rhoda Reddock | D60: A01 | E60: anglófono (Trinidad) | F60: inglés | G60: Trinidad | H60: función territorial no demostrada | N60: pendiente_revision | Q60: pendiente | R60: pendiente | S60: NO | T60: matriz v1.14.0
A61: caribjourneys | B61: Caribbean Journeys: An Ethnography of Migration and Home in Three Family Networks | C61: Karen Fog Olwig | D61: B03 | E61: anglófono (Dinamarca/Caribe) | F61: inglés | G61: Dinamarca/Caribe | H61: varias procedencias o territorios; función territorial no demostrada | N61: pendiente_revision | Q61: pendiente | R61: pendiente | S61: NO | T61: matriz v1.14.0
A62: globalculture | B62: Global Culture, Island Identity: Continuity and Change in the Afro-Caribbean Community of Nevis | C62: Karen Fog Olwig | D62: B02 | E62: anglófono (Dinamarca/Caribe) | F62: inglés | G62: Dinamarca/Caribe | H62: varias procedencias o territorios; función territorial no demostrada | N62: pendiente_revision | Q62: pendiente | R62: pendiente | S62: NO | T62: matriz v1.14.0
A63: islandscity | B63: Islands in the City: West Indian Migration to New York | C63: Nancy Foner (ed.) | D63: A02 | E63: anglófono (EE.UU./Antillas) | F63: inglés | G63: EE.UU./Antillas | H63: varias procedencias o territorios; abreviaturas por normalizar; función territorial no demostrada | N63: pendiente_revision | Q63: pendiente | R63: pendiente | S63: NO | T63: matriz v1.14.0
A64: callaloonation | B64: Callaloo Nation: Metaphors of Race and Religious Identity among South Asians in Trinidad | C64: Aisha Khan | D64: B04 | E64: anglófono (Trinidad/EE.UU.) | F64: inglés | G64: Trinidad/EE.UU. | H64: varias procedencias o territorios; abreviaturas por normalizar; función territorial no demostrada | N64: pendiente_revision | Q64: pendiente | R64: pendiente | S64: NO | T64: matriz v1.14.0
A65: reconfdominic | B65: Reconfiguring Dominicanness | C65: Kimberly Eison Simmons | D65: DE01 | E65: anglófono (EE.UU./Rep. Dominicana) | F65: inglés | G65: EE.UU./Rep. Dominicana | H65: varias procedencias o territorios; abreviaturas por normalizar; función territorial no demostrada | N65: pendiente_revision | Q65: pendiente | R65: pendiente | S65: NO | T65: matriz v1.14.0
A66: cuijla | B66: Cuijla: Esbozo etnográfico de un pueblo negro | C66: Gonzalo Aguirre Beltrán | D66: B02 | E66: hispano (México) | F66: español | G66: México | H66: función territorial no demostrada | N66: pendiente_revision | Q66: pendiente | R66: pendiente | S66: NO | T66: matriz v1.14.0
A67: chocolatecorn | B67: Chocolate and Corn Flour: History, Race, and Place in the Making of Black Mexico | C67: Laura A. Lewis | D67: C03 | E67: anglófono (EE.UU./México) | F67: inglés | G67: EE.UU./México | H67: varias procedencias o territorios; abreviaturas por normalizar; función territorial no demostrada | N67: pendiente_revision | Q67: pendiente | R67: pendiente | S67: NO | T67: matriz v1.14.0
A68: womenancestors | B68: Women and the Ancestors: Black Carib Kinship and Ritual | C68: Virginia Kerns | D68: B01 | E68: anglófono (EE.UU./Belice) | F68: inglés | G68: EE.UU./Belice | H68: varias procedencias o territorios; abreviaturas por normalizar; función territorial no demostrada | N68: pendiente_revision | Q68: pendiente | R68: pendiente | S68: NO | T68: matriz v1.14.0
A69: afrocentroam | B69: Afro Central Americans in New York City: Garifuna Tales of Transnational Movements in Racialized Space | C69: Sarah England | D69: A02 | E69: anglófono (EE.UU./Honduras) | F69: inglés | G69: EE.UU./Honduras | H69: varias procedencias o territorios; abreviaturas por normalizar; función territorial no demostrada | N69: pendiente_revision | Q69: pendiente | R69: pendiente | S69: NO | T69: matriz v1.14.0
... A80: gill | B80: Erotic Islands: Art and Activism in the Queer Caribbean | C80: Lyndon K. Gill | D80: A01 | E80: anglófono (Trinidad/EE.UU.) | F80: inglés | G80: Trinidad/EE.UU. | H80: varias procedencias o territorios; abreviaturas por normalizar; función territorial no demostrada | N80: pendiente_revision | Q80: pendiente | R80: pendiente | S80: NO | T80: matriz v1.14.0
A81: deere | B81: The Invention of Order: On the Coloniality of Space | C81: Don Thomas Deere | D81: DE01 | E81: comparado (teoría decolonial americana) | G81: teoría decolonial americana | H81: sin lengua explícita; mezcla escala comparativa; mezcla tema, método o escala; función territorial no demostrada | N81: pendiente_revision | Q81: pendiente | R81: pendiente | S81: NO | T81: matriz v1.14.0
A82: abello | B82: La isla encallada: el Caribe colombiano en el archipiélago | C82: Alberto Abello Vives | D82: C02 | E82: hispano (Colombia) | F82: español | G82: Colombia | H82: función territorial no demostrada | N82: pendiente_revision | Q82: pendiente | R82: pendiente | S82: NO | T82: matriz v1.14.0
A83: benitez | B83: La isla que se repite / The Repeating Island | C83: Antonio Benítez Rojo | D83: S01 | E83: hispano (Cuba) | F83: español | G83: Cuba | H83: función territorial no demostrada | N83: pendiente_revision | Q83: pendiente | R83: pendiente | S83: NO | T83: matriz v1.14.0
A84: cesaire | B84: Discurso sobre el colonialismo | C84: Aimé Césaire | D84: DE01 | E84: francófono (Martinica) | F84: francés | G84: Martinica | H84: función territorial no demostrada | N84: pendiente_revision | Q84: pendiente | R84: pendiente | S84: NO | T84: matriz v1.14.0
A85: fanon | B85: Piel negra, máscaras blancas | C85: Frantz Fanon | D85: C01 | E85: francófono (Martinica/Francia) | F85: francés | G85: Martinica/Francia | H85: varias procedencias o territorios; función territorial no demostrada | N85: pendiente_revision | Q85: pendiente | R85: pendiente | S85: NO | T85: matriz v1.14.0
A86: james | B86: The Black Jacobins: Toussaint L'Ouverture and the San Domingo Revolution | C86: C.L.R. James | D86: C01 | E86: anglófono (Trinidad) | F86: inglés | G86: Trinidad | H86: función territorial no demostrada | N86: pendiente_revision | Q86: pendiente | R86: pendiente | S86: NO | T86: matriz v1.14.0
A87: trouillotsilencing | B87: Silenciando el pasado: el poder y la producción de la Historia | C87: Michel-Rolph Trouillot | D87: C04 | E87: anglófono (EE.UU./Haití) | F87: inglés | G87: EE.UU./Haití | H87: varias procedencias o territorios; abreviaturas por normalizar; función territorial no demostrada | N87: pendiente_revision | Q87: pendiente | R87: pendiente | S87: NO | T87: matriz v1.14.0
A88: brownreaper | B88: The Reaper's Garden: Death and Power in the World of Atlantic Slavery | C88: Vincent Brown | D88: A02 | E88: anglófono (EE.UU.) | F88: inglés | G88: EE.UU. | H88: abreviaturas por normalizar; función territorial no demostrada | N88: pendiente_revision | Q88: pendiente | R88: pendiente | S88: NO | T88: matriz v1.14.0
A89: kempadoo | B89: Sexing the Caribbean: Gender, Race and Sexual Labor | C89: Kamala Kempadoo | D89: A01 | E89: anglófono (Guyana/Canadá) | F89: inglés | G89: Guyana/Canadá | H89: varias procedencias o territorios; función territorial no demostrada | N89: pendiente_revision | Q89: pendiente | R89: pendiente | S89: NO | T89: matriz v1.14.0
A90: kingisland | B90: Island Bodies: Transgressive Sexualities in the Caribbean Imagination | C90: Rosamond S. King | D90: B01 | E90: comparado (anglófono/francófono/hispano/neerlandés) | F90: inglés | francés | español | neerlandés | G90: anglófono/francófono/hispano/neerlandés | H90: múltiples lenguas; mezcla escala comparativa; varias procedencias o territorios; función territorial no demostrada | N90: pendiente_revision | Q90: pendiente | R90: pendiente | S90: NO | T90: matriz v1.14.0
A91: fuentesdispossessed | B91: Dispossessed Lives: Enslaved Women, Violence, and the Archive | C91: Marisa J. Fuentes | D91: A01 | E91: anglófono (EE.UU.) | F91: inglés | G91: EE.UU. | H91: abreviaturas por normalizar; función territorial no demostrada | N91: pendiente_revision | Q91: pendiente | R91: pendiente | S91: NO | T91: matriz v1.14.0
A92: bollandbelize | B92: The Formation of a Colonial Society: Belize, From Conquest to Crown Colony | C92: O. Nigel Bolland | D92: C01 | E92: anglófono (Belice/R.U.) | F92: inglés | G92: Belice/R.U. | H92: varias procedencias o territorios; abreviaturas por normalizar; función territorial no demostrada | N92: pendiente_revision | Q92: pendiente | R92: pendiente | S92: NO | T92: matriz v1.14.0
A93: hintzen | B93: The Costs of Regime Survival: Racial Mobilization, Elite Domination and Control of the State in Guyana and Trinidad | C93: Percy C. Hintzen | D93: A02 | E93: anglófono (Guyana/Trinidad) | F93: inglés | G93: Guyana/Trinidad | H93: varias procedencias o territorios; función territorial no demostrada | N93: pendiente_revision | Q93: pendiente | R93: pendiente | S93: NO | T93: matriz v1.14.0
... A98: helgnuncamas | B98: ¡Nunca más esclavos! Una historia comparada de los esclavos que se liberaron en las Américas | C98: Aline Helg | D98: A01 | E98: hispano (Suiza/Colombia) | F98: español | G98: Suiza/Colombia | H98: varias procedencias o territorios; función territorial no demostrada | N98: pendiente_revision | Q98: pendiente | R98: pendiente | S98: NO | T98: matriz v1.14.0
A99: robinsonmarxismo | B99: Marxismo negro: la formación de la tradición radical negra | C99: Cedric J. Robinson | D99: DE01 | E99: comparado (transnacional) | G99: transnacional | H99: sin lengua explícita; mezcla escala comparativa; mezcla tema, método o escala; función territorial no demostrada | N99: pendiente_revision | Q99: pendiente | R99: pendiente | S99: NO | T99: matriz v1.14.0
A100: bassiacuoso | B100: Un territorio acuoso: geografías marineras y el Gran Caribe transimperial de la Nueva Granada | C100: Ernesto Bassi | D100: P00 | E100: hispano (Colombia) | F100: español | G100: Colombia | H100: función territorial no demostrada | N100: pendiente_revision | Q100: pendiente | R100: pendiente | S100: NO | T100: matriz v1.14.0
A101: rediker | B101: Barco de esclavos: una historia humana | C101: Marcus Rediker | D101: A03 | E101: comparado (transnacional) | G101: transnacional | H101: sin lengua explícita; mezcla escala comparativa; mezcla tema, método o escala; función territorial no demostrada | N101: pendiente_revision | Q101: pendiente | R101: pendiente | S101: NO | T101: matriz v1.14.0
A102: gosinenature | B102: Nature's Wild: Love, Sex, and Law in the Caribbean | C102: Andil Gosine | D102: C01 | E102: anglófono (Trinidad/Canadá) | F102: inglés | G102: Trinidad/Canadá | H102: varias procedencias o territorios; función territorial no demostrada | N102: pendiente_revision | Q102: pendiente | R102: pendiente | S102: NO | T102: matriz v1.14.0
A103: headleyreparaciones | B103: A Philosophical Investigation into the Possibility/Impossibility of Reparations for Caribbean Slavery: Assessing the Legal Challenges | C103: Clevis Headley | D103: A03 | E103: comparado (transnacional) | G103: transnacional | H103: sin lengua explícita; mezcla escala comparativa; mezcla tema, método o escala; función territorial no demostrada | N103: pendiente_revision | Q103: pendiente | R103: pendiente | S103: NO | T103: matriz v1.14.0
A104: jaffeconcrete | B104: Concrete Jungles: Urban Pollution and the Politics of Difference in the Caribbean | C104: Rivke Jaffe | D104: DE01 | E104: neerlandés/anglófono (Curazao/Jamaica) | F104: inglés | neerlandés | G104: Curazao/Jamaica | H104: múltiples lenguas; varias procedencias o territorios; función territorial no demostrada | N104: pendiente_revision | Q104: pendiente | R104: pendiente | S104: NO | T104: matriz v1.14.0
A105: pardomosquerahoffmann | B105: Afrodescendientes en las Américas: trayectorias sociales e identitarias. 150 años de la abolición de la esclavitud en Colombia | C105: Mauricio Pardo, Claudia Mosquera y Odile Hoffmann (eds.) | D105: A03 | E105: hispano (Colombia/Francia) | F105: español | G105: Colombia/Francia | H105: varias procedencias o territorios; función territorial no demostrada | N105: pendiente_revision | Q105: pendiente | R105: pendiente | S105: NO | T105: matriz v1.14.0
A106: scher | B106: Carnival and the Formation of a Caribbean Transnation | C106: Philip W. Scher | D106: B04 | E106: anglófono (Trinidad/EE.UU.) | F106: inglés | G106: Trinidad/EE.UU. | H106: varias procedencias o territorios; abreviaturas por normalizar; función territorial no demostrada | N106: pendiente_revision | Q106: pendiente | R106: pendiente | S106: NO | T106: matriz v1.14.0
A107: hallafricanslouisiana | B107: Africans in Colonial Louisiana: The Development of Afro-Creole Culture in the Eighteenth Century | C107: Gwendolyn Midlo Hall | D107: B04 | E107: francófono/anglófono (Luisiana) | F107: inglés | francés | G107: Luisiana | H107: múltiples lenguas; función territorial no demostrada | N107: pendiente_revision | Q107: pendiente | R107: pendiente | S107: NO | T107: matriz v1.14.0
A108: creolenieworleans | B108: Creole New Orleans: Race and Americanization | C108: Arnold R. Hirsch y Joseph Logsdon (eds.) | D108: B04 | E108: francófono/anglófono (Luisiana) | F108: inglés | francés | G108: Luisiana | H108: múltiples lenguas; función territorial no demostrada | N108: pendiente_revision | Q108: pendiente | R108: pendiente | S108: NO | T108: matriz v1.14.0
A109: ramsaranlewis | B109: Caribbean Masala: Indian Identity in Guyana and Trinidad | C109: Dave Ramsaran y Linden F. Lewis | D109: B04 | E109: anglófono (Guyana/Trinidad) | F109: inglés | G109: Guyana/Trinidad | H109: varias procedencias o territorios; función territorial no demostrada | N109: pendiente_revision | Q109: pendiente | R109: pendiente | S109: NO | T109: matriz v1.14.0
A110: gonzalezsojourners | B110: Sojourners of the Caribbean: Ethnogenesis and Ethnohistory of the Garifuna | C110: Nancie L. González | D110: B02 | E110: anglófono (Belice/Honduras) | F110: inglés | G110: Belice/Honduras | H110: varias procedencias o territorios; función territorial no demostrada | N110: pendiente_revision | Q110: pendiente | R110: pendiente | S110: NO | T110: matriz v1.14.0
A111: andersonblackindigenous | B111: Black and Indigenous: Garifuna Activism and Consumer Culture in Honduras | C111: Mark Anderson | D111: B05 | E111: anglófono (Honduras) | F111: inglés | G111: Honduras | H111: función territorial no demostrada | N111: pendiente_revision | Q111: pendiente | R111: pendiente | S111: NO | T111: matriz v1.14.0
A112: munrohaitirising | B112: Haiti Rising: Haitian History, Culture and the Earthquake of 2010 | C112: Martin Munro (ed.) | D112: B03 | E112: anglófono/francófono (Haití) | F112: inglés | francés | G112: Haití | H112: múltiples lenguas; función territorial no demostrada | N112: pendiente_revision | Q112: pendiente | R112: pendiente | S112: NO | T112: matriz v1.14.0
A113: meniketinevis | B113: Sugar Cane Capitalism and Environmental Transformation: An Archaeology of Colonial Nevis, West Indies | C113: Marco G. Meniketti | D113: B02 | E113: anglófono (EE.UU.) | F113: inglés | G113: EE.UU. | H113: abreviaturas por normalizar; función territorial no demostrada | N113: pendiente_revision | Q113: pendiente | R113: pendiente | S113: NO | T113: matriz v1.14.0
A114: handlerlangebarbados | B114: Plantation Slavery in Barbados: An Archaeological and Historical Investigation | C114: Jerome S. Handler y Frederick W. Lange | D114: A02 | E114: anglófono (EE.UU.) | F114: inglés | G114: EE.UU. | H114: abreviaturas por normalizar; función territorial no demostrada | N114: pendiente_revision | Q114: pendiente | R114: pendiente | S114: NO | T114: matriz v1.14.0
A115: kutzinskisugar | B115: Sugar's Secrets: Race and the Erotics of Cuban Nationalism | C115: Vera M. Kutzinski | D115: A01 | E115: anglófono (EE.UU.) | F115: inglés | G115: EE.UU. | H115: abreviaturas por normalizar; función territorial no demostrada | N115: pendiente_revision | Q115: pendiente | R115: pendiente | S115: NO | T115: matriz v1.14.0
... A151: sonicbodies | B151: Sonic Bodies: Reggae Sound Systems, Performance Techniques, and Ways of Knowing | C151: Julian Henriques | D151: B03 | E151: anglófono (Jamaica/R.U.) | F151: inglés | G151: Jamaica/R.U. | H151: varias procedencias o territorios; abreviaturas por normalizar; función territorial no demostrada | N151: pendiente_revision | Q151: pendiente | R151: pendiente | S151: NO | T151: matriz v1.14.0
A152: yountaesecular | B152: The Coloniality of the Secular: Race, Religion, and Poetics of World-Making | C152: An Yountae | D152: C04 | E152: comparado (transnacional) | G152: transnacional | H152: sin lengua explícita; mezcla escala comparativa; mezcla tema, método o escala; función territorial no demostrada | N152: pendiente_revision | Q152: pendiente | R152: pendiente | S152: NO | T152: matriz v1.14.0
A153: branddoor | B153: A Map to the Door of No Return: Notes to Belonging | C153: Dionne Brand | D153: C04 | E153: anglófono (Trinidad/Canadá) | F153: inglés | G153: Trinidad/Canadá | H153: varias procedencias o territorios; función territorial no demostrada | N153: pendiente_revision | Q153: pendiente | R153: pendiente | S153: NO | T153: matriz v1.14.0
A154: grosfoguelcolonial | B154: Colonial Subjects: Puerto Ricans in a Global Perspective | C154: Ramón Grosfoguel | D154: C02 | E154: hispano (Puerto Rico) | F154: español | G154: Puerto Rico | H154: función territorial no demostrada | N154: pendiente_revision | Q154: pendiente | R154: pendiente | S154: NO | T154: matriz v1.14.0
A155: bahadurcoolie | B155: Coolie Woman: The Odyssey of Indenture | C155: Gaiutra Bahadur | D155: B02 | E155: anglófono (Guyana/EE.UU.) | F155: inglés | G155: Guyana/EE.UU. | H155: varias procedencias o territorios; abreviaturas por normalizar; función territorial no demostrada | N155: pendiente_revision | Q155: pendiente | R155: pendiente | S155: NO | T155: matriz v1.14.0
A156: zapataarbol | B156: El árbol brujo de la libertad | C156: Manuel Zapata Olivella | D156: B05 | E156: hispano (Colombia) | F156: español | G156: Colombia | H156: función territorial no demostrada | N156: pendiente_revision | Q156: pendiente | R156: pendiente | S156: NO | T156: matriz v1.14.0
A157: almanzaorilla | B157: La orilla de Calibán: el rastro de la filosofía afrocaribe en el siglo XX | C157: Roberto Almanza Hernández | D157: C03 | E157: hispano (Colombia) | F157: español | G157: Colombia | H157: función territorial no demostrada | N157: pendiente_revision | Q157: pendiente | R157: pendiente | S157: NO | T157: matriz v1.14.0
A158: goldbergabolition | B158: Abolition Time: Grammars of Law, Poetics of Justice | C158: Jess A. Goldberg | D158: A03 | E158: anglófono (EE. UU./Guyana) | F158: inglés | G158: EE. UU./Guyana | H158: varias procedencias o territorios; abreviaturas por normalizar; función territorial no demostrada | N158: pendiente_revision | Q158: pendiente | R158: pendiente | S158: NO | T158: matriz v1.14.0
A159: hurboncomprendre | B159: Comprendre Haïti: essai sur l'État, la nation, la culture | C159: Laënnec Hurbon | D159: C02 | E159: francófono (Haití) | F159: francés | G159: Haití | H159: función territorial no demostrada | N159: pendiente_revision | Q159: pendiente | R159: pendiente | S159: NO | T159: matriz v1.14.0
A160: rifkinfictions | B160: Fictions of Land and Flesh: Blackness, Indigeneity, Speculation | C160: Mark Rifkin | D160: B03 | E160: anglófono (EE. UU./Jamaica) | F160: inglés | G160: EE. UU./Jamaica | H160: varias procedencias o territorios; abreviaturas por normalizar; función territorial no demostrada | N160: pendiente_revision | Q160: pendiente | R160: pendiente | S160: NO | T160: matriz v1.14.0
A161: whiteheadtiger | B161: Lords of the Tiger Spirit: A History of the Caribs in Colonial Venezuela and Guyana, 1498–1820 | C161: Neil L. Whitehead | D161: C04 | E161: anglófono (R. U./Guyana) | F161: inglés | G161: R. U./Guyana | H161: varias procedencias o territorios; abreviaturas por normalizar; función territorial no demostrada | N161: pendiente_revision | Q161: pendiente | R161: pendiente | S161: NO | T161: matriz v1.14.0
A162: olsencartagena | B162: Slavery and Salvation in Colonial Cartagena de Indias | C162: Margaret M. Olsen | D162: C04 | E162: anglófono (EE. UU./Colombia) | F162: inglés | G162: EE. UU./Colombia | H162: varias procedencias o territorios; abreviaturas por normalizar; función territorial no demostrada | N162: pendiente_revision | Q162: pendiente | R162: pendiente | S162: NO | T162: matriz v1.14.0
A163: cosgrovegarifuna | B163: Surviving the Americas: Garifuna Persistence from Nicaragua to New York City | C163: Cosgrove, Idiáquez, Bent & Gorvetzian | D163: B05 | E163: anglófono (EE. UU./Nicaragua) | F163: inglés | G163: EE. UU./Nicaragua | H163: varias procedencias o territorios; abreviaturas por normalizar; función territorial no demostrada | N163: pendiente_revision | Q163: pendiente | R163: pendiente | S163: NO | T163: matriz v1.14.0
...

Sheet Valores tr
A1: Atlas 2.0 · inventario de 104 valores heredados de tr
A2: Inventario descriptivo: no convierte las cadenas heredadas en decisiones editoriales.
A4: tr original | B4: Frecuencia | C4: Lengua(s) detectada(s) | D4: IDs de ejemplo | E4: Alertas
A5: anglófono (EE.UU.) | B5: 38 | C5: inglés | D5: mintz | lindskoog | workercane | steward | hagedorn | dunham | tellmyhorse | palmiengangas | E5: abreviaturas por normalizar; función territorial no demostrada
A6: hispano (Colombia) | B6: 20 | C6: español | D6: totumo | chande | perezmorales | manoalzada | esquiva | friedemannlengua | escalante | figueroa | E6: función territorial no demostrada
A7: anglófono (Jamaica/EE.UU.) | B7: 8 | C7: inglés | D7: truebornmaroons | exceptviolence | modernblackness | politicallife | russwurm | james_bannerethiopia | knight_genesisnacionalismo | goffedarklab | E7: varias procedencias o territorios; abreviaturas por normalizar; función territorial no demostrada
A8: anglófono (Trinidad) | B8: 8 | C8: inglés | D8: taylor | reddock | alexander | james | mohammed_generosrealidades | brereton_racerelationstrinidad | williamscapitalismo | looklaichinese | E8: función territorial no demostrada
A9: anglófono (Jamaica) | B9: 7 | C9: inglés | D9: chevannes | wynterblackmetamorphosis | mgsmithplural | clarkemymother | meeks_postcolonial | shepherdmaharani | atkinsonearliest | E9: función territorial no demostrada
A10: francófono (Haití) | B10: 7 | C10: francés | D10: trouillot | casimir | fouchard | pricemars | firmin | hurboncomprendre | hurbondictadura | E10: función territorial no demostrada
A11: anglófono (EE.UU./Caribe) | B11: 5 | C11: inglés | D11: tinsley | shellererotic | islandfutures | deloughrey | shellerconsuming | E11: varias procedencias o territorios; abreviaturas por normalizar; función territorial no demostrada
A12: anglófono (EE.UU./Surinam) | B12: 5 | C12: inglés | D12: price | pricefirst | travelstooy | alabi | rainforestwarriors | E12: varias procedencias o territorios; abreviaturas por normalizar; función territorial no demostrada
A13: comparado (transnacional) | B13: 5 | D13: araujo | robinsonmarxismo | rediker | headleyreparaciones | yountaesecular | E13: sin lengua explícita; mezcla escala comparativa; mezcla tema, método o escala; función territorial no demostrada
A14: anglófono (Trinidad/EE.UU.) | B14: 4 | C14: inglés | D14: callaloonation | gill | scher | brownetropic | E14: varias procedencias o territorios; abreviaturas por normalizar; función territorial no demostrada
A15: francófono (Martinica) | B15: 4 | C15: francés | D15: glissant | creolite | ferdinand | cesaire | E15: función territorial no demostrada
A16: hispano (Cuba) | B16: 4 | C16: español | D16: ortiz | cabrera | benitez | morenofraginals | E16: función territorial no demostrada
A17: hispano (Puerto Rico) | B17: 4 | C17: español | D17: quintero | lebroncimarronaje | grosfoguelcolonial | zambrana | E17: función territorial no demostrada
A18: anglófono (Barbados) | B18: 3 | C18: inglés | D18: brathwaite | brathwaitearchipelago | barrowfamily | E18: función territorial no demostrada
A19: anglófono (EE.UU./Haití) | B19: 3 | C19: inglés | D19: downtownladies | trouillotsilencing | ulysseWhyHaiti | E19: varias procedencias o territorios; abreviaturas por normalizar; función territorial no demostrada
A20: anglófono (Trinidad/Canadá) | B20: 3 | C20: inglés | D20: gosinenature | branddoor | bestlevitt | E20: varias procedencias o territorios; función territorial no demostrada
A21: anglófono (Antigua/EE.UU.) | B21: 2 | C21: inglés | D21: kincaidsmallplace | henrycaliban | E21: varias procedencias o territorios; abreviaturas por normalizar; función territorial no demostrada
A22: anglófono (Barbados/Jamaica) | B22: 2 | C22: inglés | D22: bogueslammingreader | becklessavingsouls | E22: varias procedencias o territorios; función territorial no demostrada
A23: anglófono (comparado) | B23: 2 | C23: inglés | D23: lightfoot | johnsonbelize | E23: mezcla escala comparativa; función territorial no demostrada
A24: anglófono (Dinamarca/Caribe) | B24: 2 | C24: inglés | D24: caribjourneys | globalculture | E24: varias procedencias o territorios; función territorial no demostrada
A25: anglófono (EE.UU./Rep. Dominicana) | B25: 2 | C25: inglés | D25: reconfdominic | lara | E25: varias procedencias o territorios; abreviaturas por normalizar; función territorial no demostrada
... A28: anglófono (Jamaica/R.U.) | B28: 2 | C28: inglés | D28: besson | sonicbodies | E28: varias procedencias o territorios; abreviaturas por normalizar; función territorial no demostrada
A29: comparado | B29: 2 | D29: fischer | scottconscripts | E29: sin lengua explícita; mezcla escala comparativa
A30: comparado (anglófono Caribe) | B30: 2 | C30: inglés | D30: quinnblackpower | puriradical | E30: mezcla escala comparativa; función territorial no demostrada
A31: francófono (Guadalupe) | B31: 2 | C31: francés | D31: vete | bebelgislerleonora | E31: función territorial no demostrada
A32: francófono (Haití) / anglófono | B32: 2 | C32: inglés | francés | D32: benedictykokken_haitiexception | trouillottransformaciones | E32: múltiples lenguas; función territorial no demostrada
A33: francófono/anglófono (Luisiana) | B33: 2 | C33: inglés | francés | D33: hallafricanslouisiana | creolenieworleans | E33: múltiples lenguas; función territorial no demostrada
A34: hispano (Rep. Dominicana/Colombia) | B34: 2 | C34: español | D34: curiel | sangbenvolviendo | E34: varias procedencias o territorios; función territorial no demostrada
A35: hispano (Suiza/Colombia) | B35: 2 | C35: español | D35: helgnuncamas | helglibertyequality | E35: varias procedencias o territorios; función territorial no demostrada
A36: hispanófono (Colombia) | B36: 2 | C36: español | D36: alvarezboro | londonoargonauts | E36: función territorial no demostrada
A37: neerlandés (Países Bajos/Caribe) | B37: 2 | C37: neerlandés | D37: oostindiedecolonising | kloosterrealm | E37: varias procedencias o territorios; función territorial no demostrada
A38: anglófono (Antillas) | B38: 1 | C38: inglés | D38: roberts | E38: función territorial no demostrada
A39: anglófono (Bahamas/Trinidad) | B39: 1 | C39: inglés | D39: nixon_resistingparadise | E39: varias procedencias o territorios; función territorial no demostrada
A40: anglófono (Belice/Honduras) | B40: 1 | C40: inglés | D40: gonzalezsojourners | E40: varias procedencias o territorios; función territorial no demostrada
A41: anglófono (Belice/R.U.) | B41: 1 | C41: inglés | D41: bollandbelize | E41: varias procedencias o territorios; abreviaturas por normalizar; función territorial no demostrada
... A84: comparado (anglófono/francófono/hispano/neerlandés) | B84: 1 | C84: inglés | francés | español | neerlandés | D84: kingisland | E84: múltiples lenguas; mezcla escala comparativa; varias procedencias o territorios; función territorial no demostrada
A85: comparado (cuenca completa) | B85: 1 | D85: mcneillmosquito | E85: sin lengua explícita; mezcla escala comparativa; mezcla tema, método o escala; función territorial no demostrada
A86: comparado (filosofía afrocaribe) | B86: 1 | D86: monahan | E86: sin lengua explícita; mezcla escala comparativa; mezcla tema, método o escala; función territorial no demostrada
A87: comparado (Guayanas) | B87: 1 | D87: hoeftetrajectories | E87: sin lengua explícita; mezcla escala comparativa; función territorial no demostrada
A88: comparado (Mauricio/Reino Unido) | B88: 1 | D88: hazareesingh | E88: sin lengua explícita; mezcla escala comparativa; varias procedencias o territorios; función territorial no demostrada
A89: comparado (métodos comparados) | B89: 1 | D89: archipelagicthinking | E89: sin lengua explícita; mezcla escala comparativa; mezcla tema, método o escala; función territorial no demostrada
A90: comparado (teoría decolonial americana) | B90: 1 | D90: deere | E90: sin lengua explícita; mezcla escala comparativa; mezcla tema, método o escala; función territorial no demostrada
A91: comparado (teoría política y etnografía) | B91: 1 | D91: citizenshipedge | E91: sin lengua explícita; mezcla escala comparativa; mezcla tema, método o escala; función territorial no demostrada
A92: comparado (transatlántico) | B92: 1 | D92: millerbassey | E92: sin lengua explícita; mezcla escala comparativa; mezcla tema, método o escala; función territorial no demostrada
A93: francófono (Francia/Colombia) | B93: 1 | C93: francés | D93: cunin | E93: varias procedencias o territorios; función territorial no demostrada
A94: francófono (Martinica/Francia) | B94: 1 | C94: francés | D94: fanon | E94: varias procedencias o territorios; función territorial no demostrada
A95: francófono/anglófono (Guadalupe–PR) | B95: 1 | C95: inglés | francés | D95: bonilla | E95: múltiples lenguas; abreviaturas por normalizar; función territorial no demostrada
A96: hispano (América Latina) | B96: 1 | C96: español | D96: gudynas | E96: función territorial no demostrada
A97: hispano (Colombia/Francia) | B97: 1 | C97: español | D97: pardomosquerahoffmann | E97: varias procedencias o territorios; función territorial no demostrada
A98: hispano (México) | B98: 1 | C98: español | D98: cuijla | E98: función territorial no demostrada
A99: hispano (Noruega/Colombia) | B99: 1 | C99: español | D99: saetheridentidades | E99: varias procedencias o territorios; función territorial no demostrada
A100: hispano (Puerto Rico/comparado) | B100: 1 | C100: español | D100: martinezsanmiguel | E100: mezcla escala comparativa; varias procedencias o territorios; función territorial no demostrada
A101: hispano (Puerto Rico/EE.UU.) | B101: 1 | C101: español | D101: felicianosantos | E101: varias procedencias o territorios; abreviaturas por normalizar; función territorial no demostrada
A102: hispano (República Dominicana) | B102: 1 | C102: español | D102: prestolmasacre | E102: función territorial no demostrada
A103: hispanófono (México) | B103: 1 | C103: español | D103: naveda_esclavoscordoba | E103: función territorial no demostrada
A104: neerlandés (Curaçao) | B104: 1 | C104: neerlandés | D104: tambu | E104: función territorial no demostrada
... A108: neerlandófono (Curazao) / anglófono | B108: 1 | C108: inglés | neerlandés | D108: vanderpijl_equaliberty | E108: múltiples lenguas; función territorial no demostrada

Sheet Nuevas 30
A1: Atlas 2.0 · treinta entradas añadidas en v1.15.0
A2: Comparación por id contra matriz-migracion-atlas.xlsx. Se incorporan al control sin reclasificación automática.
A4: id | B4: Título | C4: Autoría | D4: Año | E4: Tipo | F4: Lugar heredado | G4: tr original | H4: Lote intelectual | I4: Estado T01
A5: williamscapitalismo | B5: Capitalismo y esclavitud (Capitalism and Slavery) | C5: Eric Williams | D5: 1944 / ed. esp. 2011 | E5: obra | F5: trinidad | G5: anglófono (Trinidad) | H5: P00 | I5: pendiente_revision
A6: wynterblackmetamorphosis | B6: Black Metamorphosis: New Natives in a New World | C6: Sylvia Wynter | D6: c. 1970 (manuscrito inédito) | E6: obra | F6: jamaica | G6: anglófono (Jamaica) | H6: B04 | I6: pendiente_revision
A7: mgsmithplural | B7: The Plural Society in the British West Indies | C7: M. G. Smith | D7: 1965 | E7: obra | F7: jamaica | G7: anglófono (Jamaica) | H7: C03 | I7: pendiente_revision
A8: rtsmithmatrifocal | B8: The Matrifocal Family: Power, Pluralism and Politics | C8: Raymond T. Smith | D8: 1996 | E8: obra | F8: guyana | G8: anglófono (R.U./Guyana) | H8: B01 | I8: pendiente_revision
A9: clarkemymother | B9: My Mother Who Fathered Me: A Study of the Families in Three Selected Communities of Jamaica | C9: Edith Clarke | D9: 1957 | E9: obra | F9: jamaica | G9: anglófono (Jamaica) | H9: B01 | I9: pendiente_revision
A10: barrowfamily | B10: Family in the Caribbean: Themes and Perspectives | C10: Christine Barrow | D10: 1996 | E10: obra | F10: barbados | G10: anglófono (Barbados) | H10: B01 | I10: pendiente_revision
A11: mintzpricebirth | B11: The Birth of African-American Culture: An Anthropological Perspective | C11: Sidney W. Mintz y Richard Price | D11: 1976 / 1992 (ed. port. 2003) | E11: obra | F11: suriname | G11: anglófono (EE.UU.) | H11: B04 | I11: pendiente_revision
A12: trouillottransformaciones | B12: Transformaciones globales: la antropología y el mundo moderno (Global Transformations) | C12: Michel-Rolph Trouillot | D12: 2003 / trad. esp. 2011 | E12: obra | F12: haiti | G12: francófono (Haití) / anglófono | H12: C04 | I12: pendiente_revision
A13: morenofraginals | B13: El ingenio: complejo económico social cubano del azúcar | C13: Manuel Moreno Fraginals | D13: 1964 / ed. ampliada 1978 | E13: obra | F13: cuba | G13: hispano (Cuba) | H13: A01 | I13: pendiente_revision
A14: meeks_postcolonial | B14: After the Postcolonial Caribbean: Memory, Imagination, Hope | C14: Brian Meeks | D14: 2022 | E14: obra | F14: jamaica | G14: anglófono (Jamaica) | H14: B03 | I14: pendiente_revision
A15: oostindiedecolonising | B15: Decolonising the Caribbean: Dutch Policies in a Comparative Perspective | C15: Gert Oostindie e Inge Klinkers | D15: 2003 | E15: obra | F15: curazao | G15: neerlandés (Países Bajos/Caribe) | H15: C02 | I15: pendiente_revision
... A34: atkinsonearliest | B34: The Earliest Inhabitants: The Dynamics of the Jamaican Taíno | C34: Lesley-Gail Atkinson (ed.) | D34: 2006 | E34: obra | F34: jamaica | G34: anglófono (Jamaica) | H34: C04 | I34: pendiente_revision

Sheet Reglas T01
A1: Atlas 2.0 · reglas bloqueantes de T01
A2: Estas reglas protegen la opacidad documental: una cadena heredada puede conservar ambigüedad hasta que una fuente permita decidir.
A4: N. | B4: Regla | C4: Razón | D4: Bloqueante
A5: 1 | B5: tr original se conserva sin alteración durante toda la transición. | C5: Permite reversión, comparación y auditoría. | D5: sí
A6: 2 | B6: La detección mecánica de lengua es candidatura, nunca decisión final. | C6: anglófono o hispano puede describir tradición, autoría o edición, no necesariamente la lengua exacta del ejemplar. | D6: sí
A7: 3 | B7: Ningún lugar entre paréntesis recibe función por inferencia. | C7: EE.UU./Jamaica no revela si se trata de producción, trayectoria, circulación o territorio estudiado. | D7: sí
A8: 4 | B8: lengua_publicacion usa vocabulario controlado y fuente bibliográfica. | C8: La lengua pertenece a la edición catalogada, no a una geografía supuesta. | D8: sí
A9: 5 | B9: orilla_produccion y territorio_estudiado se deciden por separado. | C9: La posición desde la que se escribe no equivale al territorio que la obra estudia. | D9: sí
A10: 6 | B10: alcance_comparativo no se deduce de una barra entre topónimos. | C10: La barra puede nombrar trayectoria del autor, coautoría o circulación editorial. | D10: sí
A11: 7 | B11: Los valores comparado, transnacional o transatlántico exigen fundamento. | C11: Son escalas analíticas, no lenguas. | D11: sí
A12: 8 | B12: Las 30 entradas de v1.15.0 se incorporan al control sin reclasificar corrientes. | C12: Actualizar cobertura no autoriza decisiones intelectuales nuevas. | D12: sí
A13: 9 | B13: T01 no modifica relaciones ni convierte cruces lingüísticos en fricción. | C13: La fricción epistémica exige argumento y evidencia propios. | D13: sí
A14: 10 | B14: Solo una fila revisada, aprobada y con QA=pasa puede marcarse SI. | C14: Evita publicar propuestas mecánicas como hechos confirmados. | D14: sí

Sheet Control T01
A1: Atlas 2.0 · control del lote técnico T01
A2: Base: datos-atlas.json v1.15.0 · 233 obras · 588 relaciones · 30 lugares. No modifica la fuente pública ni autoriza A03.
A4: Indicador | B4: Valor | D4: Puertas de cierre | E4: Puertas de cierre | F4: Puertas de cierre | G4: Puertas de cierre | H4: Puertas de cierre
A5: Entradas en T01 | B5: =COUNTA('T01 revisión'!$A$5:$A$237) -> 233 | D5: 1. Los 233 valores de tr se conservan literalmente.
A6: Entradas nuevas v1.15.0 | B6: =COUNTIF('T01 revisión'!$T$5:$T$237,"alta v1.15.0") -> 30 | D6: 2. Las 30 entradas nuevas están identificadas por id.
A7: Valores distintos de tr | B7: =COUNTA('Valores tr'!$A$5:$A$108) -> 104 | D7: 3. Toda lengua final tiene fundamento bibliográfico.
A8: Pendientes de revisión | B8: =COUNTIF('T01 revisión'!$N$5:$N$237,"pendiente_revision") -> 233 | D8: 4. Toda orilla declara su función; ningún topónimo se interpreta solo.
A9: Listas para generar | B9: =COUNTIF('T01 revisión'!$S$5:$S$237,"SI") -> 0 | D9: 5. Estado revisada exige responsable y fecha.
A10: Lengua final vacía | B10: =COUNTBLANK('T01 revisión'!$I$5:$I$237) -> 233 | D10: 6. QA=pasa y aprobación=aprobada preceden a listo=SI.
A11: Filas con alertas | B11: =COUNTA('T01 revisión'!$H$5:$H$237) -> 233 | D11: 7. T01 no altera relaciones, fricciones, corrientes ni el corpus público.
A13: Decisión operativa: T01 se ejecuta antes de A03. Las candidaturas mecánicas no migran al esquema 2.0 hasta aprobación humana.

Sheet Memoria operativa
A1: Atlas 2.0 · memoria operativa T01 | B1: Atlas 2.0 · memoria operativa T01 | C1: Atlas 2.0 · memoria operativa T01 | D1: Atlas 2.0 · memoria operativa T01 | E1: Atlas 2.0 · memoria operativa T01 | F1: Atlas 2.0 · memoria operativa T01
A2: Continuidad estable del trabajo articulado entre ChatGPT, Claude y la dirección académica. Estas reglas gobiernan el lote y no autorizan cambios en el corpus público. | B2: Continuidad estable del trabajo articulado entre ChatGPT, Claude y la dirección académica. Estas reglas gobiernan el lote y no autorizan cambios en el corpus público. | C2: Continuidad estable del trabajo articulado entre ChatGPT, Claude y la dirección académica. Estas reglas gobiernan el lote y no autorizan cambios en el corpus público. | D2: Continuidad estable del trabajo articulado entre ChatGPT, Claude y la dirección académica. Estas reglas gobiernan el lote y no autorizan cambios en el corpus público. | E2: Continuidad estable del trabajo articulado entre ChatGPT, Claude y la dirección académica. Estas reglas gobiernan el lote y no autorizan cambios en el corpus público. | F2: Continuidad estable del trabajo articulado entre ChatGPT, Claude y la dirección académica. Estas reglas gobiernan el lote y no autorizan cambios en el corpus público.
A4: N.º | B4: Decisión estable | C4: Aplicación | D4: Prohibición | E4: Evidencia de cierre | F4: Estado
A5: 1 | B5: Orden de trabajo | C5: T01 se ejecuta antes de A03. | D5: No abrir A03 mientras T01 no cierre. | E5: T01 con QA y aprobación académica. | F5: vigente
A6: 2 | B6: Base canónica de trabajo | C6: 233 obras, 588 relaciones y 30 lugares. | D6: No volver a la matriz de 203 como base operativa. | E6: Identificadores únicos y recuentos reconciliados. | F6: vigente
A7: 3 | B7: Capas ya cerradas | C7: Preservar P00, S01, A01 y A02. | D7: No reclasificarlas ni reabrirlas desde T01. | E7: Sin cambios en hojas ni artefactos cerrados. | F7: vigente
A8: 4 | B8: Rastro heredado | C8: Conservar tr original, literal y visible. | D8: No normalizar ni sobrescribir tr. | E8: 233 valores originales presentes. | F8: vigente
A9: 5 | B9: Desagregación | C9: Separar lengua_publicacion, orilla_produccion, territorio_estudiado y alcance_comparativo. | D9: No convertir topónimos, nacionalidad, editorial, tema o método en esos campos por inferencia. | E9: Fuente, fundamento y localización por decisión. | F9: vigente
A10: 6 | B10: Cascada de modelos | C10: ChatGPT hace la primera pasada; Claude revisa B, C y muestra de A de forma ciega. | D10: Claude no recibe inicialmente la salida de ChatGPT. | E10: Salidas comparables con el mismo esquema. | F10: vigente
A11: 7 | B11: Riesgo A | C11: Caso factual sencillo; Claude revisa muestra determinística cercana al 15 %. | D11: No confundir sencillez bibliográfica con aprobación automática. | E11: Evidencia localizable y muestra humana cercana al 10 %. | F11: vigente
A12: 8 | B12: Riesgo B | C12: Caso mixto; doble dictamen ciego. | D12: No cerrar si hay desacuerdo o evidencia insuficiente. | E12: Comparación de los cuatro campos y fuentes. | F12: vigente
A13: 9 | B13: Riesgo C | C13: Caso compuesto, crítico o interpretativo; doble dictamen y revisión humana obligatoria. | D13: No resolver por consenso de modelos. | E13: Decisión académica explícita. | F13: vigente
A14: 10 | B14: Autoridad | C14: Los modelos proponen; la dirección académica confirma. | D14: Ninguna IA aprueba obras, relaciones ni interpretaciones. | E14: Responsable, fecha, QA=pasa y aprobación=aprobada. | F14: vigente
A15: 11 | B15: Fuentes | C15: Toda afirmación debe remitir a fuente y página/sección localizable. | D15: No usar título, memoria, afinidad temática o resumen automático como prueba suficiente. | E15: Fuente primaria o referencia autorizada. | F15: vigente
A16: 12 | B16: Monahan | C16: Caso de calibración: la entrada reúne libros de 2011 y 2023; el PDF disponible documenta solo el de 2023. | D16: No extrapolar la revisión del libro de 2023 al de 2011. | E16: Segunda fuente y decisión sobre división de la entrada. | F16: en_revision
... A18: 14 | B18: Auditoría | C18: Conservar respuestas de ambos modelos, desacuerdos y campos no verificables. | D18: No borrar silencios ni forzar certeza. | E18: Rastro completo en Control IA. | F18: vigente

Sheet Protocolo IA
A1: Atlas 2.0 · protocolo maestro ChatGPT–Claude | B1: Atlas 2.0 · protocolo maestro ChatGPT–Claude | C1: Atlas 2.0 · protocolo maestro ChatGPT–Claude | D1: Atlas 2.0 · protocolo maestro ChatGPT–Claude | E1: Atlas 2.0 · protocolo maestro ChatGPT–Claude | F1: Atlas 2.0 · protocolo maestro ChatGPT–Claude | G1: Atlas 2.0 · protocolo maestro ChatGPT–Claude
A2: Sistema en cascada: evidencia comparable, revisión ciega y escalamiento por riesgo. Coincidencia sin evidencia no constituye consenso válido. | B2: Sistema en cascada: evidencia comparable, revisión ciega y escalamiento por riesgo. Coincidencia sin evidencia no constituye consenso válido. | C2: Sistema en cascada: evidencia comparable, revisión ciega y escalamiento por riesgo. Coincidencia sin evidencia no constituye consenso válido. | D2: Sistema en cascada: evidencia comparable, revisión ciega y escalamiento por riesgo. Coincidencia sin evidencia no constituye consenso válido. | E2: Sistema en cascada: evidencia comparable, revisión ciega y escalamiento por riesgo. Coincidencia sin evidencia no constituye consenso válido. | F2: Sistema en cascada: evidencia comparable, revisión ciega y escalamiento por riesgo. Coincidencia sin evidencia no constituye consenso válido. | G2: Sistema en cascada: evidencia comparable, revisión ciega y escalamiento por riesgo. Coincidencia sin evidencia no constituye consenso válido.
A4: Fase | B4: Actor | C4: Entrada | D4: Acción | E4: Salida obligatoria | F4: Puerta de control | G4: Estado inicial
A5: 0. Preparación | B5: ChatGPT | C5: T01 revisión + fuente disponible | D5: Conservar id y tr; verificar granularidad bibliográfica; proponer riesgo. | E5: Registro estructurado y campos no verificables. | F5: No hay cambio en corpus. | G5: iniciada
A6: 1. Calibración | B6: Ambos modelos | C6: 24 casos seleccionados + mismas fuentes | D6: Dictámenes independientes con el mismo esquema. | E6: Dos salidas ciegas por caso. | F6: Dirección académica fija patrón de 24. | G6: GPT completo; Claude pendiente
A7: 2. Preclasificación | B7: ChatGPT | C7: 233 entradas y fuentes disponibles | D7: Primera pasada; riesgo A/B/C; propuesta con evidencia. | E7: 233 registros estructurados. | F7: No prellenar decisión humana. | G7: pendiente
A8: 3. Revisión selectiva | B8: Claude | C8: Todos B y C + muestra de A | D8: Revisar sin ver la salida de ChatGPT. | E8: Dictamen independiente. | F8: Misma edición o fuente identificada. | G8: pendiente
A9: 4. Comparación | B9: Control IA | C9: Salidas de ambos modelos | D9: Comparar cuatro campos y suficiencia de evidencia. | E9: Consenso, desacuerdo o no verificable. | F9: La coincidencia textual no suple evidencia. | G9: pendiente
A10: 5. Decisión | B10: Dirección académica | C10: Cola de excepciones + muestra | D10: Resolver C, desacuerdos, vacíos y muestra A. | E10: Decisión, responsable y fecha. | F10: Toda interpretación exige aprobación humana. | G10: pendiente
A11: 6. QA | B11: ChatGPT + validador | C11: Dictámenes aprobados | D11: Recuentos, vocabularios, fuentes, id y campos obligatorios. | E11: QA pasa/falla y reporte. | F11: 0 errores antes de integrar. | G11: pendiente
A12: 7. Integración | B12: ChatGPT | C12: Solo filas listas | D12: Incorporar al plan maestro en lote reversible. | E12: T01 preparado para repositorio. | F12: No tocar corpus público sin autorización. | G12: pendiente
A15: Riesgo | B15: Criterio | C15: ChatGPT | D15: Claude | E15: Control humano | F15: Lectura completa | G15: Resultado posible
... A26: fundamento_o_fuente | B26: Referencia, localización y explicación breve. | C26: Enlace sin indicar qué sustenta. | D26: No para cerrar. | E26: Ambos modelos deben aportar evidencia localizable. | F26: Insuficiente => cola de excepción. | G26: Máximo rigor con mínima carga documental.

Sheet Calibración 24
A1: Atlas 2.0 · conjunto de calibración de 24 entradas | B1: Atlas 2.0 · conjunto de calibración de 24 entradas | C1: Atlas 2.0 · conjunto de calibración de 24 entradas | D1: Atlas 2.0 · conjunto de calibración de 24 entradas | E1: Atlas 2.0 · conjunto de calibración de 24 entradas | F1: Atlas 2.0 · conjunto de calibración de 24 entradas | G1: Atlas 2.0 · conjunto de calibración de 24 entradas | H1: Atlas 2.0 · conjunto de calibración de 24 entradas | I1: Atlas 2.0 · conjunto de calibración de 24 entradas | J1: Atlas 2.0 · conjunto de calibración de 24 entradas | K1: Atlas 2.0 · conjunto de calibración de 24 entradas | L1: Atlas 2.0 · conjunto de calibración de 24 entradas | M1: Atlas 2.0 · conjunto de calibración de 24 entradas | N1: Atlas 2.0 · conjunto de calibración de 24 entradas | O1: Atlas 2.0 · conjunto de calibración de 24 entradas | P1: Atlas 2.0 · conjunto de calibración de 24 entradas | Q1: Atlas 2.0 · conjunto de calibración de 24 entradas | R1: Atlas 2.0 · conjunto de calibración de 24 entradas | S1: Atlas 2.0 · conjunto de calibración de 24 entradas | T1: Atlas 2.0 · conjunto de calibración de 24 entradas | U1: Atlas 2.0 · conjunto de calibración de 24 entradas | V1: Atlas 2.0 · conjunto de calibración de 24 entradas | W1: Atlas 2.0 · conjunto de calibración de 24 entradas
